Workbook

Sheet 存量房抵押
A1: 序号 | B1: 封包号 | C1: 业务合同编号 | D1: 借款人 | E1: 抵押人 | F1: 贷种 | G1: 不动产证明 | H1: 抵押金额 （万元） | I1: 借款期限 | J1: 抵押贷款时间 | K1: 到期日期 | L1: 客户经理
A2: 1 | B2: 20210430043600006304001 | C2: 360102782210404116613 | D2: 彭康腾 | E2: 彭康腾 戴丽霞 | F2: 商贷通 | G2: 赣（2021）吉安市不产证明第0015193号 | H2: 130 | I2: 10 | J2: 44313 | K2: 47965
A3: 2 | B3: 20210430043600006304002 | C3: 360103042210400994428 | D3: 陈珍贵 | E3: 陈珍贵 李小兵 | F3: 极速贷 | G3: 赣（2021）吉安市不产证明第0015461号 | H3: 35 | I3: 10 | J3: 44312 | K3: 47964
A4: 3 | B4: 20210508043600006304002 | C4: 36010304221040060168 | D4: 肖承斌 | E4: 肖承斌 胡永梅 | F4: 极速贷 | G4: 赣（2021）吉安市不产证明第0015680号 | H4: 35 | I4: 10 | J4: 44312 | K4: 47964
A5: 4 | B5: 20210508043600006304003 | C5: 3699950Q221050313026 | D5: 陶观青 | E5: 陶观青 涂时风 | F5: 网商贷 | G5: 赣（2021）吉安市不产证明第0016091号 | H5: 110 | I5: 10 | J5: 44323 | K5: 47975
A6: 5 | B6: 20210508043600006304004 | C6: 3699950Q221050250847 | D6: 周慎泰 | E6: 刘爱群 | F6: 极速贷 | G6: 赣（2021）吉安市不产证明第0015886号 | H6: 41 | I6: 10 | J6: 44321 | K6: 47973
A7: 6 | B7: 20210508043600006304005 | C7: 3699950Q1040177766 | D7: 程浩 | E7: 程浩 杨希 | F7: 网商贷 | G7: 赣（2021）吉安市不产证明第0015787号 | H7: 23 | I7: 10 | J7: 44315 | K7: 47967
A8: 7 | B8: 20210510043600006304001 | C8: 3699950Q221050311993 | D8: 易云清 | E8: 易云清 易彩秋 | F8: 网商贷 | G8: 赣（2021）吉安市不产证明第0016205号 | H8: 66 | I8: 10 | J8: 44323 | K8: 47975
A9: 8 | B9: 20210510043600006304002 | C9: 3699950Q221050288004 | D9: 戴利平 | E9: 戴利平 | F9: 网商贷 | G9: 赣（2021）吉安市不产证明第0016126号 | H9: 52 | I9: 10 | J9: 44322 | K9: 47974
A10: 9 | B10: 20210510043600006304003 | C10: 36010278221050306845 | D10: 王晓东 | E10: 王晓东 | F10: 商贷通 | G10: 赣（2021）吉安市不产证明第0016124号 | H10: 49 | I10: 10 | J10: 44323 | K10: 47975
A11: 10 | B11: 20210510043699950Q05001 | C11: 3699950Q1050287142 | D11: 刘婷 | E11: 刘婷 肖安亮 | F11: 个人二手房贷款 | G11: 赣（2021）吉安市不产证明第0016179号 | H11: 33 | I11: 30 | J11: 44324 | K11: 55281
A12: 11 | B12: 20210511043600006304003 | C12: 36010304221050358634 | D12: 胡艳珺 | E12: 胡铭珺 罗镕荣 | F12: 极速贷 | G12: 赣（2021）吉安市不产证明第0016235号 | H12: 50 | I12: 10 | J12: 44325 | K12: 47977
A13: 12 | B13: 20210511043600006304001 | C13: 36010278221050347481 | D13: 刘玉珍 | E13: 刘玉珍 张震 | F13: 商贷通 | G13: 赣（2021）吉安市不产证明第0016233号 | H13: 75 | I13: 10 | J13: 44324 | K13: 47976
... A25: 24 | B25: 20210525043600006304001 | C25: 3699950Q221050753606 | D25: 胡喆 | E25: 胡喆 | F25: 商贷通 | G25: 赣（2021）吉安市不产证明第0017674号 | H25: 62 | I25: 10 | J25: 44337 | K25: 47989
A26: 25 | B26: 20210526043699950Q05001 | C26: 3699950Q117035809963 | D26: 李安军 | E26: 李安军 刘正华 | F26: 一手房(转抵押) | G26: 赣（2021）吉安市不产证明第0017173号 | H26: 35 | I26: 10 | J26: 42817 | K26: 46469 | L26: 严姝玲
A27: 26 | B27: 20210527043600006304002 | C27: 3699950Q221050820273 | D27: 夏安平 | E27: 夏安平 徐婷 | F27: 网商贷 | G27: 赣（2021）吉安市不产证明第0017770号 | H27: 40 | I27: 10 | J27: 44340 | K27: 47992
A28: 27 | B28: 20210527043600006305003 | C28: 369995Q121054914405 | D28: 刘春燕 | E28: 刘春燕 | F28: 个人二手房贷款 | G28: 赣（2021）吉安市不产证明第0017991号 | H28: 35 | I28: 10 | J28: 44256 | K28: 46447
A29: 28 | B29: 20210528043601030405001 | C29: 36010316115070170003 | D29: 曾苏珍 | E29: 曾苏珍 | F29: 一手房(转抵押) | G29: 赣（2021）吉安市不动产证明第0016227号 | H29: 370000 | I29: 曾苏珍、薛涛 | J29: 42191 | K29: 47666 | L29: 万淑红
A30: 29 | B30: 20210528043601030405002 | C30: 36010316115070192366 | D30: 梁昌尧 | E30: 梁昌尧 | F30: 一手房(转抵押) | G30: 赣（2021）吉安市不动产证明第0016229号 | H30: 280000 | I30: 梁昌尧 | J30: 42195 | K30: 49500 | L30: 万淑红
A31: 30 | B31: 20210528043601030405003 | C31: 36010316115100946209 | D31: 温永佑 | E31: 温永佑 | F31: 一手房(转抵押) | G31: 赣（2021）吉安市不动产证明第0016232号 | H31: 230000 | I31: 温永佑、陈琼玉 | J31: 42292 | K31: 53250 | L31: 万淑红
A32: 31 | B32: 20210528043601030405004 | C32: 36010316115090588595 | D32: 许艳琼 | E32: 许艳琼 | F32: 一手房(转抵押) | G32: 赣（2021）吉安市不动产证明第0016228号 | H32: 290000 | I32: 许艳琼 | J32: 42243 | K32: 49548 | L32: 万淑红
A33: 32 | B33: 20210528043601030405008 | C33: 36010304121043623281 | D33: 陈仁慧 | E33: 陈仁慧 | F33: 一手房(转抵押) | G33: 赣（2021）吉安市不产证明第0014177号 | H33: 140000 | I33: 陈仁慧 | J33: 44308 | K33: 47960 | L33: 万淑红
A34: 33 | B34: 20210528043601030405009 | C34: 36010304121043630121 | D34: 熊琴 | E34: 熊琴 | F34: 一手房(转抵押) | G34: 赣（2021）吉安市不产证明第0013593号 | H34: 360000 | I34: 熊琴/田海 | J34: 44295 | K34: 47947 | L34: 万淑红
A35: 34 | B35: 20210528043601030405010 | C35: 3601030412104362094701 | D35: 郭群 | E35: 郭群 | F35: 一手房(转抵押) | G35: 赣（2021）吉安市不产证明第0017817号 | H35: 145000 | I35: 郭群 | J35: 44298 | K35: 47950
A36: 35 | B36: 20210528043601030405011 | C36: 3601030412104358372101 | D36: 谢启发 | E36: 谢启发 | F36: 一手房(转抵押) | G36: 赣（2021）吉安市不产证明第0016415号 | H36: 750000 | I36: 谢启发 | J36: 44294 | K36: 55251
A37: 36 | B37: 20210528043699950Q05001 | C37: 36010304121054370132 | D37: 林水凤 | E37: 林水凤 | F37: 一手房(转抵押) | G37: 赣（2021）吉安市不产证明第0016722号 | H37: 720000 | I37: 孙武堃/林水凤 | J37: 44333 | K37: 47985 | L37: 郭元
A38: 37 | B38: 20210528043601030405012 | C38: 3601030412104362328101 | D38: 赵琪 | E38: 赵琪 | F38: 一手房(转抵押) | G38: 赣（2021）吉安市不产证明第0014171号 | H38: 145000 | I38: 赵琪 | J38: 44301 | K38: 47953
A39: 38 | B39: 20210528043601030405013 | C39: 36010304121044143510 | D39: 李玲 | E39: 李玲 | F39: 一手房(转抵押) | G39: 赣（2021）吉安市不产证明第0017794号 | H39: 143000 | I39: 李玲 | J39: 44337 | K39: 47989 | L39: 万淑红
A40: 39 | B40: 20210528043601030405005 | C40: 36010304121033376725 | D40: 雷慧玲 | E40: 雷慧玲 | F40: 一手房(转抵押) | G40: 赣（2021）吉安市不动产证明第0013589号 | H40: 140000 | I40: 雷慧玲 | J40: 44286 | K40: 47938 | L40: 万淑红
A41: 40 | B41: 20210528043601030405006 | C41: 36010304121054676472 | D41: 严金金 | E41: 严金金 | F41: 一手房(转抵押) | G41: 赣（2021）吉安市不动产证明第0017806号 | H41: 140000 | I41: 严金金 | J41: 44337 | K41: 47989 | L41: 万淑红
A42: 41 | B42: 20210528043601030405007 | C42: 36010304121054512525 | D42: 王喜 | E42: 王喜 | F42: 一手房(转抵押) | G42: 赣（2021）吉安市不动产证明第0017802号 | H42: 140000 | I42: 王喜 | J42: 44327 | K42: 47979 | L42: 万淑红
A43: 42 | B43: 20210528043600006304001 | C43: 36010304221050807176 | D43: 王尧海 | E43: 王尧海 陈贱香 | F43: 商贷通 | G43: 赣（2021）吉安市不产证明第0018147号 | H43: 59 | I43: 10 | J43: 44340 | K43: 47262
A44: 43 | B44: 20210531043600006304001 | C44: 3699950Q221050953104 | D44: 伍芳兰 | E44: 杨小敏 伍芬兰 | F44: 网商贷 | G44: 赣（2021）吉安市不产证明第0018262号 | H44: 69 | I44: 10 | J44: 44343 | K44: 47995
A45: 44 | B45: 20210601043600006305001 | C45: 36010316221051058641 | D45: 刘娟 | E45: 刘娟 黄连真 | F45: 综消 | G45: 赣（2021）吉安市不产证明第0018457号 | H45: 48 | I45: 10 | J45: 44347 | K45: 49095
A46: 45 | B46: 20210601043600006304002 | C46: 3601030421050982150 | D46: 袁燕 | E46: 袁燕 吴小建 | F46: 商贷通 | G46: 赣（2021）吉安市不产证明第0018459号 | H46: 49 | I46: 10 | J46: 44343 | K46: 47995
A47: 46 | B47: 20210601043601030404001 | C47: 36010304221050935909 | D47: 吴艳萍 | E47: 吴艳萍 陈旺华 | F47: 政贷通 | G47: 赣（2021）吉安市不产证明第0018460号 | H47: 15 | I47: 2 | J47: 44342 | K47: 44799
A48: 47 | B48: 20210602043600006304001 | C48: 36010316221051062303 | D48: 罗琳萍 | E48: 罗琳萍 | F48: 商贷通 | G48: 赣（2021）吉安市不动产证明第0018674号 | H48: 90 | I48: 10 | J48: 44347 | K48: 47999
A49: 48 | B49: 20210602043600006305003 | C49: 36010304221051081408 | D49: 肖俊材 | E49: 肖俊材 唐莉 | F49: 综消 | G49: 赣（2021）吉安市不动产证明第0018641号 | H49: 45 | I49: 13 | J49: 44347 | K49: 49095
A50: 49 | B50: 20210602043600006304002 | C50: 36010304221051081915 | D50: 刘中华 | E50: 刘中华 吕花蓉 | F50: 极速贷 | G50: 赣（2021）吉安市不动产证明第0018641号 | H50: 67 | I50: 10 | J50: 44347 | K50: 47999
A51: 50 | B51: 20210603043600006304001 | C51: 3601030421061136238 | D51: 胡舵 | E51: 胡舵 邱晔 | F51: 极速贷 | G51: 赣（2021）吉安市不动产证明第0018829号 | H51: 42.6 | I51: 10 | J51: 44348 | K51: 48000
A52: 51 | B52: 20210607043600006304001 | C52: 3699950Q221061201712 | D52: 刘国标 | E52: 刘国标 刘秀英 | F52: 商贷通 | G52: 赣（2021）吉安市不动产证明第0019150号 | H52: 85 | I52: 7 | J52: 44350 | K52: 46907
A53: 52 | B53: 20210607043600006304002 | C53: 3699950Q221061195447 | D53: 刘超 | E53: 郭玉妹 | F53: 网商贷 | G53: 赣（2021）吉安市不动产证明第0019227号 | H53: 72 | I53: 10 | J53: 44350 | K53: 48002
A54: 53 | B54: 20210608043600006304002 | C54: 36010304221061223043 | D54: 郭慧敏 | E54: 郭慧敏 | F54: 极速贷 | G54: 赣（2021）吉安市不动产证明第0019371号 | H54: 25 | I54: 10 | J54: 44350 | K54: 48002
... A61: 60 | B61: 20210611043600006304005 | C61: 36010304221061420032 | D61: 王泽芳 | E61: 陈跃元 | F61: 极速贷 | G61: 赣（2021）吉安市不动产证明第0020067号 | H61: 120 | I61: 10 | J61: 44357 | K61: 48009
A62: 61 | B62: 20210611043600006305004 | C62: 3699950Q121065269769 | D62: 黄翠萍 | E62: 黄翠萍 张志武 | F62: 个人二手房贷款 | G62: 赣（2021）吉安市不动产证明第0019945号 | H62: 42 | I62: 30 | J62: 44354 | K62: 55311 | L62: 巫淑芬
A63: 62 | B63: 20210615043600006305001 | C63: 3699950Q221050880887 | D63: 周玉梅 | E63: 周玉梅 | F63: 综消 | G63: 赣（2021）吉安市不动产证明第0020152号 | H63: 39 | I63: 13 | J63: 44341 | K63: 49089
A64: 63 | B64: 20210615043600006304003 | C64: 36010304221061421506 | D64: 彭洋洋 | E64: 彭洋洋 王爱莉 | F64: 商贷通 | G64: 赣（2021）吉安市不动产证明第0020151号 | H64: 169 | I64: 10 | J64: 44357 | K64: 48009
A65: 64 | B65: 20210615043600006304004 | C65: 3699950Q221061417861 | D65: 张志强 | E65: 张志强 | F65: 网商贷 | G65: 赣（2021）吉安市不动产证明第0020150号 | H65: 95 | I65: 10 | J65: 44357 | K65: 48009
A66: 65 | B66: 20210615043600006305005 | C66: 36010304221061439034 | D66: 李火平 | E66: 李火平 杨莲英 | F66: 综消 | G66: 赣（2021）吉安市不动产证明第0020155号 | H66: 61 | I66: 13 | J66: 44357 | K66: 49105
A67: 66 | B67: 20210615043600006305006 | C67: 3699950Q121065344423 | D67: 王小花 | E67: 王小花 | F67: 个人二手房贷款 | G67: 赣（2021）吉安市不动产证明第0020156号 | H67: 40 | I67: 30 | J67: 44357 | K67: 55314 | L67: 巫淑芬
A68: 67 | B68: 20210616043600006304003 | C68: 36010316221061173410 | D68: 肖欣华 | E68: 王小军 | F68: 政贷通 | G68: 赣（2021）吉安市不产证明第0020281号 | H68: 20 | I68: 15个月 | J68: 44343 | K68: 44800
A69: 68 | B69: 20210616043600006304001 | C69: 3699950Q221061499461 | D69: 钟君 | E69: 钟君 | F69: 极速贷 | G69: 赣（2021）吉安市不产证明第0020363号 | H69: 49 | I69: 10 | J69: 44361 | K69: 48013
A70: 69 | B70: 20210618043600006304002 | C70: 3699950Q221061615651 | D70: 廖贤英 | E70: 袁澎 | F70: 网商贷 | G70: 赣（2021）吉安市不产证明第0020658号 | H70: 80 | I70: 10 | J70: 44364 | K70: 48016
A71: 70 | B71: 20210618043600006304003 | C71: 3699950Q221061456797 | D71: 张忠云 | E71: 张忠云 郭连凤 | F71: 商贷通 | G71: 赣（2021）吉安市不产证明第0020606号 | H71: 75 | I71: 10 | J71: 44358 | K71: 48010
A72: 71 | B72: 20210618043600006304005 | C72: 3699950Q221061466657 | D72: 张文娟 | E72: 张文娟 | F72: 政贷通 | G72: 赣（2021）吉安市不产证明第0020423号 | H72: 20 | I72: 15个月 | J72: 44358 | K72: 44815
A73: 72 | B73: 20210618043600006305006 | C73: 3699950Q121054524660 | D73: 晏金华 | E73: 晏金华 刘位禄 | F73: 个人二手房贷款 | G73: 赣（2021）吉安市不产证明第0020592号 | H73: 43 | I73: 13 | J73: 44358 | K73: 49106 | L73: 巫淑芬
A74: 73 | B74: 20210621043600006304001 | C74: 36010304221061624375 | D74: 张元华 | E74: 张元华 吴艳萍 | F74: 网商贷 | G74: 赣（2021）吉安市不产证明第0020775号 | H74: 59 | I74: 10 | J74: 44364 | K74: 48016
A75: 74 | B75: 20210621043699950Q05001 | C75: 3699950Q121065525957 | D75: 王星明 | E75: 王星明 | F75: 个人二手房贷款 | G75: 赣（2021）吉安市不产证明第0020712号 | H75: 40 | I75: 25 | J75: 44364 | K75: 53495 | L75: 巫淑芬
A76: 74 | B76: 20210622093600006301284 | C76: 103600063210616001201 | D76: 吉安市华彩装饰材料有限责任公司 | E76: 吉安市华彩装饰材料有限责任公司 | F76: 小企业 | G76: 赣（2021）吉安市不产证明第0020713号 | H76: 490 | I76: 6 | J76: 44365 | K76: 46555
A77: 75 | B77: 20210621043600006304002 | C77: 36010304221061582906 | D77: 彭立新 | E77: 彭立新 刘雪玲 | F77: 网商贷 | G77: 赣（2021）吉安市不产证明第0020776号 | H77: 60.8 | I77: 10 | J77: 44363 | K77: 48015
A78: 75 | B78: 20210622043600006304001 | C78: 3699950Q221061520396 | D78: 王智强 | E78: 王智强 | F78: 商贷通 | G78: 赣（2021）吉安市不产证明第0020989号 | H78: 100 | I78: 10 | J78: 44362 | K78: 48014
A79: 76 | B79: 20210622043600006304002 | C79: 3699950Q221061726345 | D79: 肖学文 | E79: 肖学文 | F79: 网商贷 | G79: 赣（2021）吉安市不产证明第0020998号 | H79: 600 | I79: 10 | J79: 44368 | K79: 46194
A80: 77 | B80: 20210615043601031605001 | C80: 36010316115069749322 | D80: 冯玲玲 | E80: 冯玲玲 | F80: 一手房(转抵押) | G80: 赣（2021）吉安市不产证明第0016006号 | H80: 53 | I80: 29 | J80: 42157 | K80: 52750 | L80: 严姝玲
A81: 78 | B81: 20210615043699950Q05002 | C81: 3699950Q116104296414 | D81: 赵小金 | E81: 赵小金 尹萍平 | F81: 一手房(转抵押) | G81: 赣（2021）吉安市不产证明第0016007号 | H81: 52.5 | I81: 30 | J81: 42660 | K81: 53617 | L81: 钟坤华
A82: 79 | B82: 20210615043699950Q05003 | C82: 36010316115100898432 | D82: 邹常刚 | E82: 邹常刚 段香兰 | F82: 一手房(转抵押) | G82: 赣（2021）吉安市不产证明第0016001号 | H82: 61 | I82: 20 | J82: 42291 | K82: 49596 | L82: 钟坤华
A83: 80 | B83: 20210615043699950Q05005 | C83: 3699950Q117015218793 | D83: 陈建飞 | E83: 陈建飞 | F83: 一手房(转抵押) | G83: 赣（2021）吉安市不产证明第0016123号 | H83: 60 | I83: 30 | J83: 42744 | K83: 53701 | L83: 黄静杰
A84: 81 | B84: 20210615043699950Q05006 | C84: 3699950Q116022044463 | D84: 卢美健 | E84: 卢美健 朱强 | F84: 一手房(转抵押) | G84: 赣（2021）吉安市不产证明第0016108号 | H84: 59 | I84: 20 | J84: 42427 | K84: 49732 | L84: 黄静杰
A85: 82 | B85: 20210615043699950Q05007 | C85: 3699950Q117087557187 | D85: 李嘉威 | E85: 李嘉威 | F85: 一手房(转抵押) | G85: 赣（2021）吉安市不产证明第0016096号 | H85: 64 | I85: 30 | J85: 42951 | K85: 53908 | L85: 黄静杰
A86: 83 | B86: 20210615043699950Q05008 | C86: 36010330116104341541 | D86: 翟鑫 | E86: 翟鑫 | F86: 一手房(转抵押) | G86: 赣（2021）吉安市不产证明第0016107号 | H86: 68 | I86: 30 | J86: 42664 | K86: 53621 | L86: 郭元
A87: 84 | B87: 20210615043699950Q05009 | C87: 36010316114117838673 | D87: 汤尔毅 | E87: 汤尔毅 易春燕 | F87: 一手房(转抵押) | G87: 赣（2021）吉安市不产证明第0016100号 | H87: 58 | I87: 30 | J87: 41961 | K87: 52919 | L87: 郭元
A88: 85 | B88: 20210615043699950Q05010 | C88: 36010316115059597137 | D88: 王平华 | E88: 王平华 熊晋 | F88: 一手房(转抵押) | G88: 赣（2021）吉安市不产证明第0016004号 | H88: 55 | I88: 15 | J88: 42144 | K88: 47623 | L88: 郭元
A89: 86 | B89: 20210615043699950Q05013 | C89: 36010316116011683813 | D89: 徐进 | E89: 徐进 邹婷 | F89: 一手房(转抵押) | G89: 赣（2021）吉安市不产证明第0016000号 | H89: 60 | I89: 20 | J89: 42305 | K89: 49610 | L89: 牛小美
A90: 87 | B90: 20210615043699950Q05016 | C90: 36010316115018230524 | D90: 李华 | E90: 李华 欧阳玲 | F90: 一手房(转抵押) | G90: 赣（2021）吉安市不产证明第0015997号 | H90: 63 | I90: 30 | J90: 42002 | K90: 52229 | L90: 牛小美
A91: 88 | B91: 20210618043699950Q05001 | C91: 36010316114056051255 | D91: 汪立红 | E91: 汪立红 胡小珍 | F91: 一手房(转抵押) | G91: 赣（2021）吉安市不产证明第0016118号 | H91: 19 | I91: 20 | J91: 41753 | K91: 49058 | L91: 牛小美
... A102: 99 | B102: 20210622043699950Q05010 | C102: 3699950Q117056515781 | D102: 刘青松 | E102: 刘青松 唐素萍 | F102: 一手房(转抵押) | G102: 赣（2021）吉安市不产证明第0015999号 | H102: 74 | I102: 30 | J102: 42859 | K102: 53816 | L102: 巫淑芬
A103: 100 | B103: 20210616043600006304003 | C103: 36010316221061173410 | D103: 肖欣华 | E103: 王小军 | F103: 政贷通 | G103: 赣（2021）吉安市不产证明第0020281号 | H103: 20 | I103: 15个月 | J103: 44343 | K103: 44800
A104: 101 | B104: 20210616043600006304001 | C104: 3699950Q221061499461 | D104: 钟君 | E104: 钟君 | F104: 极速贷 | G104: 赣（2021）吉安市不产证明第0020363号 | H104: 49 | I104: 10 | J104: 44361 | K104: 48013
A105: 102 | B105: 20210618043600006304002 | C105: 3699950Q221061615651 | D105: 廖贤英 | E105: 袁澎 | F105: 网商贷 | G105: 赣（2021）吉安市不产证明第0020658号 | H105: 80 | I105: 10 | J105: 44364 | K105: 48016
A106: 103 | B106: 20210618043600006304003 | C106: 3699950Q221061456797 | D106: 张忠云 | E106: 张忠云 郭连凤 | F106: 商贷通 | G106: 赣（2021）吉安市不产证明第0020606号 | H106: 75 | I106: 10 | J106: 44358 | K106: 48010
A107: 104 | B107: 20210618043600006304005 | C107: 3699950Q221061466657 | D107: 张文娟 | E107: 张文娟 | F107: 政贷通 | G107: 赣（2021）吉安市不产证明第0020423号 | H107: 20 | I107: 15个月 | J107: 44358 | K107: 44815
A108: 105 | B108: 20210618043600006305006 | C108: 3699950Q121054524660 | D108: 晏金华 | E108: 晏金华 刘位禄 | F108: 个人二手房贷款 | G108: 赣（2021）吉安市不产证明第0020592号 | H108: 43 | I108: 13 | J108: 44358 | K108: 49106 | L108: 巫淑芬
A109: 106 | B109: 20210622043699950Q05011 | C109: 3699950Q116063163009 | D109: 梁仁仕 | E109: 梁仁仕 肖秀兰 | F109: 一手房(转抵押) | G109: 赣（2021）吉安市不产证明第0019362号 | H109: 68 | I109: 28 | J109: 42538 | K109: 52765 | L109: 巫淑芬
A110: 107 | B110: 20210622043699950Q05012 | C110: 3699950Q117046313386 | D110: 陈善英 | E110: 陈善英 郭明晖 | F110: 一手房(转抵押) | G110: 赣（2021）吉安市不产证明第0019375号 | H110: 59 | I110: 20 | J110: 42849 | K110: 50154 | L110: 巫淑芬
A111: 108 | B111: 20210622043699950Q05013 | C111: 36010316115080344969 | D111: 夏焱华 | E111: 夏焱华 黄钲坤 | F111: 一手房(转抵押) | G111: 赣（2021）吉安市不产证明第0019367号 | H111: 40 | I111: 20 | J111: 42220 | K111: 49525 | L111: 黄静杰
A112: 109 | B112: 20210622043699950Q05014 | C112: 36010316115100901064 | D112: 龙秀逸 | E112: 龙秀逸 黄婷 | F112: 一手房(转抵押) | G112: 赣（2021）吉安市不产证明第0019365号 | H112: 50 | I112: 20 | J112: 42291 | K112: 49596 | L112: 黄静杰
A113: 110 | B113: 20210622043699950Q05001 | C113: 3699950Q116022043703 | D113: 薛海飞 | E113: 薛海飞 | F113: 一手房(转抵押) | G113: 赣（2021）吉安市不产证明第0019361号 | H113: 57 | I113: 25 | J113: 42426 | K113: 51558 | L113: 牛小美
A114: 111 | B114: 20210622043699950Q05002 | C114: 36010316115111136771 | D114: 罗永鸿 | E114: 罗永鸿 陈娟 | F114: 一手房(转抵押) | G114: 赣（2021）吉安市不产证明第0019376号 | H114: 57 | I114: 20 | J114: 42318 | K114: 49623 | L114: 牛小美
A115: 112 | B115: 20210622043699950Q05003 | C115: 3699950Q116032132509 | D115: 蒋俊颖 | E115: 蒋俊颖 陈红霞 | F115: 一手房(转抵押) | G115: 赣（2021）吉安市不产证明第0019374号 | H115: 57 | I115: 20 | J115: 42433 | K115: 49738 | L115: 牛小美
A116: 113 | B116: 20210622043699950Q05004 | C116: 3699950Q116073433832 | D116: 邹春根 | E116: 邹春根 高惠香 | F116: 一手房(转抵押) | G116: 赣（2021）吉安市不产证明第0019505号 | H116: 50 | I116: 15 | J116: 42565 | K116: 48043 | L116: 牛小美
A117: 114 | B117: 20210622043601031605001 | C117: 3699950Q116042397971 | D117: 谢强生 | E117: 谢强生 李丽 | F117: 一手房(转抵押) | G117: 赣（2021）吉安市不产证明第0019359号 | H117: 40 | I117: 15 | J117: 42459 | K117: 47207 | L117: 徐求芸
A118: 115 | B118: 20210622043601031605002 | C118: 36010316114087045662 | D118: 肖龙庆 | E118: 肖龙庆 刘小娥 | F118: 一手房(转抵押) | G118: 赣（2021）吉安市不产证明第0019366号 | H118: 27 | I118: 8 | J118: 41871 | K118: 44793 | L118: 严姝玲
A119: 116 | B119: 20210622043601031605003 | C119: 36010316115049065367 | D119: 刘桂香 | E119: 刘桂香 | F119: 一手房(转抵押) | G119: 赣（2021）吉安市不产证明第0019377号 | H119: 42 | I119: 15 | J119: 42088 | K119: 47567 | L119: 严姝玲
... A124: 121 | B124: 20210622043699950Q05018 | C124: 36010316115090700787 | D124: 罗春莲 | E124: 罗春莲 | F124: 一手房(转抵押) | G124: 赣（2021）吉安市不产证明第0016359号 | H124: 54 | I124: 20 | J124: 42265 | K124: 49570 | L124: 牛小美
A125: 122 | B125: 20210623043600006304001 | C125: 3699950Q221061680428 | D125: 罗艳 | E125: 罗艳 | F125: 网商贷 | G125: 赣（2021）吉安市不产证明第0021054号 | H125: 41 | I125: 10 | J125: 44367 | K125: 48019
A126: 123 | B126: 20210623043600006304002 | C126: 36010316221061728691 | D126: 刘辉 | E126: 刘辉 彭新风 | F126: 网商贷 | G126: 赣（2021）吉安市不产证明第0021061号 | H126: 56 | I126: 10 | J126: 44369 | K126: 48021
A127: 124 | B127: 20210623043600006304003 | C127: 3699950Q221061705246 | D127: 陆洁 | E127: 陆洁 | F127: 极速贷 | G127: 赣（2021）吉安市不产证明第0021105号 | H127: 63 | I127: 10 | J127: 44368 | K127: 48020
A128: 125 | B128: 20210624043600006305002 | C128: 36010304221061754150 | D128: 罗水斌 | E128: 罗水斌 李美平 | F128: 综消 | G128: 赣（2021）吉安市不产证明第0021316号 | H128: 56 | I128: 13 | J128: 44369 | K128: 49117
A129: 126 | B129: 20210624043600006304003 | C129: 3601030421061768850 | D129: 尹武 | E129: 尹武 周颖 | F129: 商贷通 | G129: 赣（2021）吉安市不产证明第0021254号 | H129: 70 | I129: 10 | J129: 44369 | K129: 48021
A130: 127 | B130: 20210624043600006304004 | C130: 3699950Q221061732625 | D130: 王程远 | E130: 王程远 | F130: 商贷通 | G130: 赣（2021）吉安市不产证明第0021269号 | H130: 69 | I130: 10 | J130: 44369 | K130: 48021
A131: 128 | B131: 20210624043600006304005 | C131: 3699950Q221061741083 | D131: 刘丽梅 | E131: 刘丽梅 张珏强 | F131: 商贷通 | G131: 赣（2021）吉安市不产证明第0021166号 | H131: 65 | I131: 10 | J131: 44369 | K131: 48021
...

Sheet 一手房
A1: 序号 | B1: 封包编号 | C1: 业务合同编号 | D1: 所属楼盘 | E1: 借款人 | F1: 身份证号 | G1: 抵押人 | H1: 权证编号 | I1: 权证类型（贷款种类：一手房) | J1: 抵押金额（万元） | K1: 抵押时间 | L1: 抵押期限 | M1: 联系方式 | N1: 客户经理 | O1: 债务期限（年）
A2: 1 | B2: 20210517043699950Q05001 | C2: 3699950Q116083619779 | D2: 恒大帝景五期（住宅） | E2: 刘圣锋 | F2: 362425198402103213 | G2: 刘圣锋 赵凤霞 | H2: 赣（2021）吉安市不产证明第0009667号 | I2: 抵押登记证明 | J2: 53 | K2: 42585 | L2: 53542 | M2: 18679617121 | N2: 徐求芸 | O2: =DATEDIF(K2,L2,"Y") -> 30
A3: 2 | B3: 20210518043699950Q05001 | C3: 3699950Q116083751487 | D3: 恒大帝景E-4 | E3: 雷婷 | F3: 362425198908091029 | G3: 贺书和 | H3: 赣（2021）吉安市不产证明第0009959号 | I3: 抵押登记证明 | J3: 49 | K3: 42599 | L3: 53556 | M3: 13686400903 | N3: 徐求芸 | O3: =DATEDIF(K3,L3,"Y") -> 30
A4: 3 | B4: 20210518043699950Q05002 | C4: 36010316115090639488 | D4: 恒大帝景三期 | E4: 欧阳春兰 | F4: 362422197502274323 | G4: 欧阳春兰 王文泰 | H4: 赣（2021）吉安市不产证明第0009758号 | I4: 抵押登记证明 | J4: 54 | K4: 42255 | L4: 49560 | M4: 13790092191 | N4: 牛小美 | O4: =DATEDIF(K4,L4,"Y") -> 20
A5: 4 | B5: 20210518043699950Q05017 | C5: 3699950Q116094017795 | D5: 恒大帝景五期（住宅） | E5: 黄松财 | F5: 362422198708166736 | G5: 黄松财 周桂秀 | H5: 赣（2021）吉安市不产证明第0009757号 | I5: 抵押登记证明 | J5: 60 | K5: 42623 | L5: 53580 | M5: 18026529348 | N5: 巫淑芬 | O5: =DATEDIF(K5,L5,"Y") -> 30
A6: 5 | B6: 20210518043699950Q05003 | C6: 3699950Q117025519079 | D6: 恒大帝景E-4 | E6: 王伟伟 | F6: 362422198709095925 | G6: 王伟伟 张小军 | H6: 赣（2021）吉安市不产证明第0009752号 | I6: 抵押登记证明 | J6: 83 | K6: 42775 | L6: 53732 | M6: 13686449042 | N6: 牛小美 | O6: =DATEDIF(K6,L6,"Y") -> 30
A7: 6 | B7: 20210517043699950Q05003 | C7: 36010316115070081532 | D7: 恒大帝景三期 | E7: 龙楚 | F7: 362430198409012032 | G7: 龙楚 欧阳月花 | H7: 赣（2021）吉安市不产证明第0009742号 | I7: 抵押登记证明 | J7: 53 | K7: 42195 | L7: 49500 | M7: 13586329330 | N7: 黄静杰 | O7: =DATEDIF(K7,L7,"Y") -> 20
A8: 7 | B8: 20210518043699950Q05004 | C8: 3699950Q116114644281 | D8: 恒大帝景E-4 | E8: 郑娇英 | F8: 362421198910058644 | G8: 郑娇英 康志勇 | H8: 赣（2021）吉安市不产证明第0009731号 | I8: 抵押登记证明 | J8: 46 | K8: 42691 | L8: 46343 | M8: 13970686763 | N8: 牛小美 | O8: =DATEDIF(K8,L8,"Y") -> 10
A9: 8 | B9: 20210518043699950Q05021 | C9: 3699950Q116052859587 | D9: 恒大帝景五期（住宅） | E9: 李志慧 | F9: 362422199012306213 | G9: 李志慧 罗艳珍 | H9: 赣（2021）吉安市不产证明第0009644号 | I9: 抵押登记证明 | J9: 37 | K9: 42508 | L9: 49813 | M9: 15921287433 | N9: 严姝玲 | O9: =DATEDIF(K9,L9,"Y") -> 20
A10: 9 | B10: 20210518043699950Q05025 | C10: 3699950Q116042576760 | D10: 恒大帝景五期（住宅） | E10: 刘桂平 | F10: 362421197609203836 | G10: 胡慧莲 刘桂平 | H10: 赣（2021）吉安市不产证明第0009574号 | I10: 抵押登记证明 | J10: 68 | K10: 42474 | L10: 51605 | M10: 13627961106 | N10: 严姝玲 | O10: =DATEDIF(K10,L10,"Y") -> 25
A11: 10 | B11: 20210518043699950Q05033 | C11: 3699950Q116094089980 | D11: 恒大帝景五期（住宅） | E11: 高启华 | F11: 36242619760914003X | G11: 高启华 熊清梅 | H11: 赣（2021）吉安市不产证明第0009573号 | I11: 抵押登记证明 | J11: 50 | K11: 42631 | L11: 49936 | M11: 13979611867 | N11: 牛小美 | O11: =DATEDIF(K11,L11,"Y") -> 20
A12: 11 | B12: 20210518043699950Q05027 | C12: 36010330117025495362 | D12: 恒大帝景E-4 | E12: 李臣 | F12: 362401198705182018 | G12: 李臣 胡晓珍 | H12: 赣（2021）吉安市不产证明第0009572号 | I12: 抵押登记证明 | J12: 59 | K12: 42797 | L12: 53754 | M12: 18170461220 | N12: 巫淑芬 | O12: =DATEDIF(K12,L12,"Y") -> 30
A13: 12 | B13: 20210518043699950Q05005 | C13: 36010316114035531900 | D13: 恒大帝景 | E13: 施燕琴 | F13: 362401197705210547 | G13: 施燕琴 彭裕庆 | H13: 赣（2021）吉安市不产证明第0009571号 | I13: 抵押登记证明 | J13: 58 | K13: 41690 | L13: 48995 | M13: 13970460002 | N13: 牛小美 | O13: =DATEDIF(K13,L13,"Y") -> 20
... A50: 49 | B50: 20210517043699950Q05006 | C50: 3699950Q118123740037 | D50: 梦想星城三期 | E50: 张满生 | F50: 362422198109256713 | G50: 张满生 李霞 | H50: 赣（2021）吉安市不产证明第0010283号 | I50: 抵押登记证明 | J50: 60 | K50: 43440 | L50: 52571 | M50: 15107062756 | N50: 黄静杰 | O50: =DATEDIF(K50,L50,"Y") -> 25
A51: 50 | B51: 20210518043699950Q05045 | C51: 3699950Q119066531017 | D51: 梦想星城二期 | E51: 张美丽 | F51: 362422199509222541 | G51: 张美丽 黄平 | H51: 赣（2021）吉安市不产证明第0010286号 | I51: 抵押登记证明 | J51: 60 | K51: 43644 | L51: 2049//6/28 | M51: 18160766377 | N51: 牛小美 | O51: =DATEDIF(K51,L51,"Y") -> #VALUE!
A52: 51 | B52: 20210518043699950Q05047 | C52: 3699950Q119066541971 | D52: 梦想星城三期 | E52: 夏侯庚招 | F52: 362401198707084913 | G52: 夏候庚招 彭琳 | H52: 赣（2021）吉安市不产证明第0010287号 | I52: 抵押登记证明 | J52: 49 | K52: 43645 | L52: 54603 | M52: 18221528982 | N52: 牛小美 | O52: =DATEDIF(K52,L52,"Y") -> 30
A53: 52 | B53: 20210518043699950Q05079 | C53: 3699950Q118050867743 | D53: 梦想星城三期 | E53: 郭志东 | F53: 362421199011263219 | G53: 郭志东 黄端红 | H53: 赣（2021）吉安市不产证明第0010245号 | I53: 抵押登记证明 | J53: 68 | K53: 43203 | L53: 54161 | M53: 18802599497 | N53: 郭元 | O53: =DATEDIF(K53,L53,"Y") -> 30
A54: 53 | B54: 20210518043699950Q05014 | C54: 3699950Q118123625341 | D54: 梦想星城三期 | E54: 肖仁 | F54: 362421198810035314 | G54: 肖仁 刘四妹 | H54: 赣（2021）吉安市不产证明第0010241号 | I54: 抵押登记证明 | J54: 70 | K54: 43466 | L54: 54424 | M54: 15720808994 | N54: 徐求芸 | O54: =DATEDIF(K54,L54,"Y") -> 30
A55: 54 | B55: 20210518043699950Q05049 | C55: 3699950Q119111430364 | D55: 梦想星城三期 | E55: 周小江 | F55: 362429199512125317 | G55: 周小江 朱琳 | H55: 赣（2021）吉安市不产证明第0010244号 | I55: 抵押登记证明 | J55: 54.6 | K55: 43775 | L55: 54733 | M55: 13699851980 | N55: 牛小美 | O55: =DATEDIF(K55,L55,"Y") -> 30
A56: 55 | B56: 20210518043699950Q05050 | C56: 3699950Q118123679491 | D56: 梦想星城三期 | E56: 肖海军 | F56: 362422198701254012 | G56: 肖海军 | H56: 赣（2021）吉安市不产证明第0010246号 | I56: 抵押登记证明 | J56: 63 | K56: 43451 | L56: 54409 | M56: 15813814066 | N56: 牛小美 | O56: =DATEDIF(K56,L56,"Y") -> 30
A57: 56 | B57: 20210518043699950Q05080 | C57: 3699950Q118123624647 | D57: 梦想星城三期 | E57: 吴蔚瑾 | F57: 362426199007172228 | G57: 吴蔚瑾 陈晓洋 | H57: 赣（2021）吉安市不产证明第0010247号 | I57: 抵押登记证明 | J57: 71 | K57: 43433 | L57: 54391 | M57: 18379690890 | N57: 郭元 | O57: =DATEDIF(K57,L57,"Y") -> 30
A58: 57 | B58: 20210518043699950Q05118 | C58: 3699950Q118050847726 | D58: 梦想星城三期 | E58: 吴淑英 | F58: 36242519881224502X | G58: 吴淑英 | H58: 赣（2021）吉安市不产证明第0010248号 | I58: 抵押登记证明 | J58: 67 | K58: 43245 | L58: 54203 | M58: 15384227784 | N58: 钟坤华 | O58: =DATEDIF(K58,L58,"Y") -> 30
A59: 58 | B59: 20210518043699950Q05132 | C59: 3699950Q119045519139 | D59: 梦想星城三期 | E59: 郭三莲 | F59: 362401198411254442 | G59: 郭三莲 胡德耀 | H59: 赣（2021）吉安市不产证明第0010250号 | I59: 抵押登记证明 | J59: 62 | K59: 43579 | L59: 54537 | M59: 13924585230 | N59: 钟坤华 | O59: =DATEDIF(K59,L59,"Y") -> 30
A60: 59 | B60: 20210518043699950Q05052 | C60: 3699950Q118050885042 | D60: 梦想星城三期 | E60: 曹涛生 | F60: 362421199203164151 | G60: 曹涛生 | H60: 赣（2021）吉安市不产证明第0010253号 | I60: 抵押登记证明 | J60: 60 | K60: 43217 | L60: 54175 | M60: 18711370565 | N60: 牛小美 | O60: =DATEDIF(K60,L60,"Y") -> 30
A61: 60 | B61: 20210518043699950Q05054 | C61: 3699950Q118050848364 | D61: 梦想星城三期 | E61: 刘文昌 | F61: 362401199811124932 | G61: 刘文昌 | H61: 赣（2021）吉安市不产证明第0010255号 | I61: 抵押登记证明 | J61: 40 | K61: 43217 | L61: 54175 | M61: 15879632557 | N61: 牛小美 | O61: =DATEDIF(K61,L61,"Y") -> 30
A62: 61 | B62: 20210518043699950Q05057 | C62: 3699950Q119035120371 | D62: 梦想星城三期 | E62: 郭文敢 | F62: 362421199410183515 | G62: 郭文敢 | H62: 赣（2021）吉安市不产证明第0010156号 | I62: 抵押登记证明 | J62: 50 | K62: 43552 | L62: 54510 | M62: 13151593866 | N62: 牛小美 | O62: =DATEDIF(K62,L62,"Y") -> 30
A63: 62 | B63: 20210518043699950Q05059 | C63: 3699950Q118071627805 | D63: 梦想星城三期 | E63: 龙继龙 | F63: 362429199311185313 | G63: 龙继龙 | H63: 赣（2021）吉安市不产证明第0010163号 | I63: 抵押登记证明 | J63: 56 | K63: 43266 | L63: 54224 | M63: 15879098243 | N63: 牛小美 | O63: =DATEDIF(K63,L63,"Y") -> 30
... A259: 258 | B259: 20210630043699950Q05037 | C259: 3699950Q118050880950 | D259: 梦想星城二期 | E259: 廖阳 | F259: 362423199008240537 | G259: 廖阳 周小翠 | H259: 赣（2021）吉安市不产证明第0020913号 | I259: 抵押登记证明 | J259: 73 | K259: 43217 | L259: 54175 | M259: 13128110976 | N259: 严姝玲 | O259: =DATEDIF(K259,L259,"Y") -> 30
A260: 259 | B260: 20210630043699950Q05030 | C260: 3699950Q119045527382 | D260: 梦想星城三期 | E260: 刘秋涛 | F260: 362421198707034110 | G260: 刘秋涛 赖求霞 | H260: 赣（2021）吉安市不产证明第0020914号 | I260: 抵押登记证明 | J260: 63 | K260: 43580 | L260: 2039//4/25 | M260: 13358373661 | N260: 徐求芸 | O260: =DATEDIF(K260,L260,"Y") -> #VALUE!
A261: 260 | B261: 20210630043699950Q05026 | C261: 3699950Q116124985104 | D261: 恒大帝景E-4 | E261: 王峣 | F261: 362401198704231017 | G261: 王峣 郭霞 | H261: 赣（2021）吉安市不产证明第0021265号 | I261: 抵押登记证明 | J261: 59 | K261: 42727 | L261: 53684 | M261: 15114057303 | N261: 黄静杰 | O261: =DATEDIF(K261,L261,"Y") -> 30
A262: 261 | B262: 20210630043699950Q05049 | C262: 36010316114117769262 | D262: 恒大帝景E-5 | E262: 刘忠敏 | F262: 362432198410081011 | G262: 刘忠敏 | H262: 赣（2021）吉安市不产证明第0021261号 | I262: 抵押登记证明 | J262: 54 | K262: 41954 | L262: 52912 | M262: 13713906850 | N262: 钟坤华 | O262: =DATEDIF(K262,L262,"Y") -> 30
A263: 262 | B263: 20210630043699950Q05021 | C263: 36010330116114627280 | D263: 润阳·环湖湾 | E263: 肖鹏翔 | F263: 362428198410121111 | G263: 肖鹏翔 张亚轩 | H263: 赣（2021）吉安市不产证明第0021259号 | I263: 抵押登记证明 | J263: 56 | K263: 42671 | L263: 49976 | M263: 15807963121 | N263: 牛小美 | O263: =DATEDIF(K263,L263,"Y") -> 20
A264: 263 | B264: 20210630043699950Q05005 | C264: 36010330116114478652 | D264: 润阳·环湖湾 | E264: 王俊菁 | F264: 362421198102106839 | G264: 王俊菁 肖秀华 | H264: 赣（2021）吉安市不产证明第0021258号 | I264: 抵押登记证明 | J264: 57 | K264: 42671 | L264: 49976 | M264: 13879677888 | N264: 郭元 | O264: =DATEDIF(K264,L264,"Y") -> 20
A265: 264 | B265: 20210630043699950Q05022 | C265: 36010330116104246530 | D265: 润阳·环湖湾 | E265: 万霖 | F265: 362401198211051018 | G265: 万霖 欧阳春连 | H265: 赣（2021）吉安市不产证明第0021263号 | I265: 抵押登记证明 | J265: 57 | K265: 42634 | L265: 48112 | M265: 15879663100 | N265: 牛小美 | O265: =DATEDIF(K265,L265,"Y") -> 15
A266: 265 | B266: 20210630043699950Q05023 | C266: 3699950Q120129933290 | D266: 吉安时代城（B-15地块） | E266: 曹阳 | F266: 362401199009091539 | G266: 曹阳 | H266: 赣（2021）吉安市不产证明第0021682号 | I266: 预告抵押登记证明 | J266: 35 | K266: 44169 | L266: 51474 | M266: 18510862375 | N266: 牛小美 | O266: =DATEDIF(K266,L266,"Y") -> 20
A267: 266 | B267: 20210630043699950Q05025 | C267: 3699950Q121010856209 | D267: 吉安时代城（B-15地块） | E267: 徐求兰 | F267: 362401199204185223 | G267: 徐求兰 | H267: 赣（2021）吉安市不产证明第0021678号 | I267: 预告抵押登记证明 | J267: 48 | K267: 44203 | L267: 51508 | M267: 13267234576 | N267: 牛小美 | O267: =DATEDIF(K267,L267,"Y") -> 20
A268: 267 | B268: 20210630043699950Q05039 | C268: 36010316115018164388 | D268: 滨江壹号（又称上江界）B区 | E268: 刘爱民 | F268: 362422198008223533 | G268: 刘爱民 唐君 | H268: 赣（2021）吉安市不产证明第0021069号 | I268: 抵押登记证明 | J268: 28 | K268: 41962 | L268: 45615 | M268: 18675718675 | N268: 郭元 | O268: =DATEDIF(K268,L268,"Y") -> 10
A269: 268 | B269: 20210712043601031605001 | C269: 36010239116073368436 | D269: 凯旋中央城北区 | E269: 杨言安 | F269: 36242119890311533X | G269: 滕慧敏 杨言安 | H269: 赣（2021）吉安市不动产证明第0022042号 | I269: 抵押登记证明 | J269: 46 | K269: 42549 | L269: 48027 | M269: 15364926048 | N269: 徐求芸 | O269: =DATEDIF(K269,L269,"Y") -> 15
A270: 269 | B270: 20210716043699950Q05003 | C270: 36010330116063004641 | D270: 凯旋世纪 | E270: 刘文萍 | F270: 362421198905011120 | G270: 俞卫平 刘文萍 | H270: 赣（2021）吉安市不动产证明第0022524号 | I270: 抵押登记证明 | J270: 29 | K270: 42510 | L270: 47988 | M270: 18070568401 | N270: 黄静杰 | O270: =DATEDIF(K270,L270,"Y") -> 15
A271: 270 | B271: 20210720043601031605002 | C271: 36010239116052807462 | D271: 凯旋世纪 | E271: 刘梦麒 | F271: 362401196211191011 | G271: 周丽萍 刘梦麒 | H271: 赣（2021）吉安市不动产证明第0023342号 | I271: 抵押登记证明 | J271: 44.5 | K271: 42500 | L271: 46152 | M271: 13807969359 | N271: 郭元 | O271: =DATEDIF(K271,L271,"Y") -> 10
A272: 271 | B272: 20210720043699950Q05002 | C272: 3699950Q121033203908 | D272: 中梁碧桂园.鹿鸣府 | E272: 康立钢 | F272: 362421197302230418 | G272: 刘成英 康立钢 | H272: 赣（2021）吉安市不动产证明第0022822号 | I272: 预告抵押登记证明 | J272: 56 | K272: 44281 | L272: 51951 | M272: 13857877596 | N272: 牛小美 | O272: =DATEDIF(K272,L272,"Y") -> 21
... A278: 277 | B278: 20210723043699950Q05001 | C278: 3699950Q121021884128 | D278: 吉安时代城（B-15地块） | E278: 谢兵兵 | F278: 362422198812191114 | G278: 谢兵兵 曾艳香 | H278: 赣（2021）吉安市不动产证明第0023852号 | I278: 预告抵押登记证明 | J278: 53 | K278: 44231 | L278: 55188 | M278: 13207969108 | N278: 巫淑芬 | O278: =DATEDIF(K278,L278,"Y") -> 30
A279: 278 | B279: 20210721043601030405001 | C279: 36010304121054785020 | D279: 滨江首府六期 | E279: 陈国平 | F279: 440923198405280787 | G279: 肖祖凉 陈国平 | H279: 赣（2021）吉安市不动产证明第0018987号 | I279: 预告抵押登记证明 | J279: 137 | K279: 44337 | L279: 2031/521 | M279: 18170615129 | N279: 赖丽君 | O279: =DATEDIF(K279,L279,"Y") -> #VALUE!
A280: 279 | B280: 20210723043601030405011 | C280: 36010304121075959663 | D280: 滨江首府六期 | E280: 周寒珂 | F280: 362422199212070049 | G280: 周寒珂 | H280: 赣（2021）吉安市不动产证明第0023015号 | I280: 预告抵押登记证明 | J280: 13 | K280: 44384 | L280: 48036 | M280: 18296665661 | N280: 赖丽君 | O280: =DATEDIF(K280,L280,"Y") -> 10
A281: 280 | B281: 20210723043601030405012 | C281: 36010304121065834174 | D281: 滨江首府六期 | E281: 余春华 | F281: 362426197102110085 | G281: 余春华 | H281: 赣（2021）吉安市不动产证明第0023011号 | I281: 预告抵押登记证明 | J281: 14.5 | K281: 44384 | L281: 48036 | M281: 13879658081 | N281: 赖丽君 | O281: =DATEDIF(K281,L281,"Y") -> 10
A282: 281 | B282: 20210723043601030405013 | C282: 36010304121075943212 | D282: 滨江首府六期 | E282: 王水莲 | F282: 36242219700107004X | G282: 王水莲 罗伍德 | H282: 赣（2021）吉安市不动产证明第0023013号 | I282: 预告抵押登记证明 | J282: 10 | K282: 44383 | L282: 48035 | M282: 18779665379 | N282: 赖丽君 | O282: =DATEDIF(K282,L282,"Y") -> 10
A283: 282 | B283: 20210723043601030405032 | C283: 未放款 | D283: 滨江首府 | E283: 刘智辉 | F283: 362429200103271511 | G283: 刘智辉 | H283: 赣（2021）吉安市不动产证明第0021144号 | I283: 预告抵押登记证明 | J283: 70 | K283: 44341 | L283: 55298 | O283: =DATEDIF(K283,L283,"Y") -> 30
A284: 283 | B284: 20210722043601030405043 | C284: 36010304121054913611 | D284: 滨江首府六期 | E284: 王细萍 | F284: 362401198508173622 | G284: 王细萍 | H284: 赣（2021）吉安市不动产证明第0018989号 | I284: 预告抵押登记证明 | J284: 14 | K284: 44348 | L284: 48000 | M284: 15879658668 | N284: 万淑红 | O284: =DATEDIF(K284,L284,"Y") -> 10
A285: 284 | B285: 20210722043601030405044 | C285: 36010304121055003774 | D285: 滨江首府四期（底商） | E285: 邱水芳 | F285: 362131197706054525 | G285: 朱五根 邱水芳 | H285: 赣（2021）吉安市不动产证明第0018991号 | I285: 预告抵押登记证明 | J285: 100 | K285: 44348 | L285: 48000 | M285: 13576835558 | N285: 万淑红 | O285: =DATEDIF(K285,L285,"Y") -> 10
A286: 285 | B286: 20210722043601030405045 | C286: 36010304118113210634 | D286: 滨江壹号(又称上江界）四期（B区） | E286: 张振学 | F286: 362425199008205013 | G286: 张振学 | H286: 赣（2021）吉安市不动产证明第0022844号 | I286: 抵押登记证明 | J286: 62 | K286: 43416 | L286: 54374 | M286: 15019128968 | N286: 万淑红 | O286: =DATEDIF(K286,L286,"Y") -> 30
A287: 286 | B287: 20210722043601030405046 | C287: 36010304118113433314 | D287: 滨江壹号(又称上江界）四期（B区） | E287: 刘明全 | F287: 36242219891105721X | G287: 刘明全 杨佳丽 | H287: 赣（2021）吉安市不动产证明第0022841号 | I287: 抵押登记证明 | J287: 50 | K287: 43433 | L287: 50738 | M287: 17779615076 | N287: 万淑红 | O287: =DATEDIF(K287,L287,"Y") -> 20
A288: 287 | B288: 20210721043601030405002 | C288: 36010304118050886966 | D288: 滨江壹号三期（又称上江界）A区 | E288: 罗金生 | F288: 362421197111112910 | G288: 罗金生 郭玉花 | H288: 赣（2021）吉安市不动产证明第0022846号 | I288: 抵押登记证明 | J288: 52.9 | K288: 43228 | L288: 49437 | M288: 18770968813 | N288: 赖丽君 | O288: =DATEDIF(K288,L288,"Y") -> 17
A289: 288 | B289: 20210723043601030405031 | C289: 36010304118113210055 | D289: 滨江壹号(又称上江界）四期（B区） | E289: 刘生安 | F289: 362421199708182654 | G289: 刘生安 | H289: 赣（2021）吉安市不动产证明第0022659号 | I289: 抵押登记证明 | J289: 58 | K289: 43416 | L289: 2048/11/12 | M289: 18825526801 | N289: 万淑红 | O289: =DATEDIF(K289,L289,"Y") -> 30
A290: 289 | B290: 20210721043601030405003 | C290: 36010304119076568732 | D290: 滨江壹号(又称上江界）四期（B区） | E290: 曾志星 | F290: 362421199212217411 | G290: 曾志星 刘琢 | H290: 赣（2021）吉安市不动产证明第0022660号 | I290: 抵押登记证明 | J290: 64 | K290: 43647 | L290: 2049/7/1 | M290: 17620813966 | N290: 赖丽君 | O290: =DATEDIF(K290,L290,"Y") -> 30
A291: 290 | B291: 20210721043601030405004 | C291: 36010304119014272294 | D291: 滨江壹号(又称上江界）四期（B区） | E291: 习小忠 | F291: 362422197208171139 | G291: 习小忠 张棉英 | H291: 赣（2021）吉安市不动产证明第0023142号 | I291: 抵押登记证明 | J291: 30 | K291: 43488 | L291: 47141 | M291: 13580274462 | N291: 赖丽君 | O291: =DATEDIF(K291,L291,"Y") -> 10
A292: 291 | B292: 20210722043601030405047 | C292: 36010304118113210769 | D292: 滨江壹号(又称上江界）四期（B区） | E292: 吴方珍 | F292: 362425199001273216 | G292: 吴方珍 曾玉石 | H292: 赣（2021）吉安市不动产证明第0023100号 | I292: 抵押登记证明 | J292: 60 | K292: 43416 | L292: 2028/11/12 | M292: 15970208663 | N292: 万淑红 | O292: =DATEDIF(K292,L292,"Y") -> 10
A293: 292 | B293: 20210722043601030405048 | C293: 36010304118020022961 | D293: 滨江壹号三期（又称上江界）A区 | E293: 吴冬兰 | F293: 362422197509036248 | G293: 吴冬兰 杨济冬 | H293: 赣（2021）吉安市不动产证明第0023097号 | I293: 抵押登记证明 | J293: 56 | K293: 43159 | L293: 2036/2/28 | M293: 15879651458 | N293: 万淑红 | O293: =DATEDIF(K293,L293,"Y") -> 18
A294: 293 | B294: 20210721043601030405005 | C294: 36010278117056803180 | D294: 滨江壹号A区 | E294: 郑思豪 | F294: 362422198505106717 | G294: 郑思豪 黄小燕 | H294: 赣（2021）吉安市不动产证明第0023096号 | I294: 抵押登记证明 | J294: 51.2 | K294: 42873 | L294: 2042/5/18 | M294: 18352986989 | N294: 赖丽君 | O294: =DATEDIF(K294,L294,"Y") -> 25
A295: 294 | B295: 20210721043601030405006 | C295: 36010278117066845690 | D295: 滨江壹号三期（又称上江界）A区 | E295: 彭五仔 | F295: 362422197511202532 | G295: 彭五仔 周雪兰 | H295: 赣（2021）吉安市不动产证明第0023098号 | I295: 抵押登记证明 | J295: 28 | K295: 42873 | L295: 2027/5/18 | M295: 13434970846 | N295: 赖丽君 | O295: =DATEDIF(K295,L295,"Y") -> 10
A296: 295 | B296: 20210721043601030405007 | C296: 36010304117025674996 | D296: 滨江壹号三期（又称上江界）A区 | E296: 王小勇 | F296: 362422198611213575 | G296: 王小勇 刘清清 | H296: 赣（2021）吉安市不动产证明第0023099号 | I296: 抵押登记证明 | J296: 35.8 | K296: 42769 | L296: 2037/2/3 | M296: 13631768578 | N296: 赖丽君 | O296: =DATEDIF(K296,L296,"Y") -> 20
A297: 296 | B297: 20210721043601030405008 | C297: 36010304118082063567 | D297: 滨江壹号三期（又称上江界）A区 | E297: 乐前海 | F297: 362421197501138358 | G297: 乐前海 雷小英 | H297: 赣（2021）吉安市不动产证明第0022843号 | I297: 抵押登记证明 | J297: 61.7 | K297: 43315 | L297: 50620 | M297: 13422967458 | N297: 赖丽君 | O297: =DATEDIF(K297,L297,"Y") -> 20
A298: 297 | B298: 20210721043601030405009 | C298: 36010304119024669836 | D298: 滨江壹号(又称上江界）四期（B区） | E298: 郭秋明 | F298: 362421197408173255 | G298: 郭秋明 刘三英 | H298: 赣（2021）吉安市不动产证明第0022655号 | I298: 抵押登记证明 | J298: 59 | K298: 43524 | L298: 2039/2/28 | M298: 18279692848 | N298: 赖丽君 | O298: =DATEDIF(K298,L298,"Y") -> 20
A299: 298 | B299: 20210721043699950Q05007 | C299: 36010278117056800602 | D299: 滨江壹号A区 | E299: 黄文忠 | F299: 36242219921101351X | G299: 黄文忠 | H299: 赣（2021）吉安市不动产证明第0022656号 | I299: 抵押登记证明 | J299: 20 | K299: 42866 | L299: 2027/5/11 | M299: 18607010054 | N299: 巫淑芬 | O299: =DATEDIF(K299,L299,"Y") -> 10
A300: 299 | B300: 20210723043601030405003 | C300: 36010304120097690359 | D300: 滨江壹号(又称上江界）四期（B区） | E300: 刘东仁 | F300: 362422199306254033 | G300: 刘东仁 杨柳 | H300: 赣（2021）吉安市不动产证明第0022653号 | I300: 抵押登记证明 | J300: 62 | K300: 44077 | L300: 2040/9/3 | M300: 15976459131 | N300: 赖丽君 | O300: =DATEDIF(K300,L300,"Y") -> 20
A301: 300 | B301: 20210723043601030405004 | C301: 36010304120044301225 | D301: 滨江壹号(又称上江界）四期（B区） | E301: 周仁 | F301: 362422199404253018 | G301: 周仁 | H301: 赣（2021）吉安市不动产证明第0022654号 | I301: 抵押登记证明 | J301: 40 | K301: 43937 | L301: 2040/4/16 | M301: 18925094616 | N301: 赖丽君 | O301: =DATEDIF(K301,L301,"Y") -> 20
A302: 301 | B302: 20210723043601030405005 | C302: 36010304120087556245 | D302: 滨江壹号(又称上江界）四期（B区） | E302: 叶敏 | F302: 362422199110118718 | G302: 叶敏 王蜜 | H302: 赣（2021）吉安市不动产证明第0022658号 | I302: 抵押登记证明 | J302: 65 | K302: 44072 | L302: 2045/8/29 | M302: 18170099113 | N302: 赖丽君 | O302: =DATEDIF(K302,L302,"Y") -> 25
A303: 302 | B303: 20210721043601030405010 | C303: 36010278117035775630 | D303: 滨江壹号三期（又称上江界）A区 | E303: 邓日平 | F303: 362425198803071216 | G303: 邓日平 王美美 | H303: 赣（2021）吉安市不动产证明第0022539号 | I303: 抵押登记证明 | J303: 25 | K303: 42788 | L303: 2027/2/22 | M303: 13868306397 | N303: 赖丽君 | O303: =DATEDIF(K303,L303,"Y") -> 10
A304: 303 | B304: 20210722043601030405049 | C304: 36010304117046116269 | D304: 滨江壹号三期（又称上江界）A区 | E304: 刘志军 | F304: 36242119870302381X | G304: 刘志军 王脚英 | H304: 赣（2021）吉安市不动产证明第0022538号 | I304: 抵押登记证明 | J304: 52 | K304: 43906 | L304: 2035/3/16 | M304: 13612931217 | N304: 万淑红 | O304: =DATEDIF(K304,L304,"Y") -> 15
A305: 304 | B305: 20210721043699950Q05008 | C305: 36010316115090585307 | D305: 滨江壹号（又称上江界）B区 | E305: 张春明 | F305: 360123198903110912 | G305: 张春明 | H305: 赣（2021）吉安市不动产证明第0022008号 | I305: 抵押登记证明 | J305: 35 | K305: 42235 | L305: 2035/8/19 | M305: 18679680910 | N305: 巫淑芬 | O305: =DATEDIF(K305,L305,"Y") -> 20
A306: 305 | B306: 20210721043601030405011 | C306: 36010304119045520429 | D306: 滨江壹号(又称上江界）四期（B区） | E306: 伍梅香 | F306: 36242919801008002X | G306: 伍梅香 彭利和 | H306: 赣（2021）吉安市不动产证明第0021446号 | I306: 抵押登记证明 | J306: 24 | K306: 43579 | L306: 2044/4/24 | M306: 18779600403 | N306: 赖丽君 | O306: =DATEDIF(K306,L306,"Y") -> 25
A307: 306 | B307: 20210721043601030405012 | C307: 36010304118040712905 | D307: 滨江壹号三期（又称上江界）A区 | E307: 刘家堤 | F307: 362421197610027139 | G307: 刘家堤 胡带招 | H307: 赣（2021）吉安市不动产证明第0022652号 | I307: 抵押登记证明 | J307: 65 | K307: 43214 | L307: 2038/4/24 | M307: 13925297233 | N307: 赖丽君 | O307: =DATEDIF(K307,L307,"Y") -> 20
A308: 307 | B308: 20210721043601030405013 | C308: 36010304117035952289 | D308: 滨江壹号三期（又称上江界）A区 | E308: 王昭礼 | F308: 362421198310296833 | G308: 王昭礼 彭喜风 | H308: 赣（2021）吉安市不动产证明第0022657号 | I308: 抵押登记证明 | J308: 46 | K308: 42802 | L308: 2032/3/8 | M308: 18818717628 | N308: 赖丽君 | O308: =DATEDIF(K308,L308,"Y") -> 15
A309: 308 | B309: 20210721043601030405014 | C309: 36010316115059515951 | D309: 滨江壹号（又称上江界）B区 | E309: 张小华 | F309: 36242119820202681X | G309: 张小华 陈艳 | H309: 赣（2021）吉安市不动产证明第0022085号 | I309: 抵押登记证明 | J309: 31 | K309: 42128 | L309: 2030/5/4 | M309: 15070664136 | N309: 赖丽君 | O309: =DATEDIF(K309,L309,"Y") -> 15
A310: 309 | B310: 20210723043601030405014 | C310: 36010316115038980212 | D310: 滨江壹号（又称上江界）B区 | E310: 曾朝辉 | F310: 362422199212093013 | G310: 曾朝辉 周春梅 | H310: 赣（2021）吉安市不动产证明第0022084号 | I310: 抵押登记证明 | J310: 37 | K310: 42081 | L310: 47560 | M310: 18025193687 | N310: 万淑红 | O310: =DATEDIF(K310,L310,"Y") -> 15
A311: 310 | B311: 20210721043699950Q05006 | C311: 36010316115038980337 | D311: 滨江壹号（又称上江界）B区 | E311: 罗友敬 | F311: 362421198608274119 | G311: 宋园玉 罗友敬 | H311: 赣（2021）吉安市不动产证明第0022004号 | I311: 抵押登记证明 | J311: 31 | K311: 42081 | L311: 47560 | M311: 18879680032 | N311: 黄静杰 | O311: =DATEDIF(K311,L311,"Y") -> 15
A312: 311 | B312: 20210721043699950Q05005 | C312: 3699950Q118082329863 | D312: 滨江壹号三期（又称上江界）A区 | E312: 张建华 | F312: 362421197610126815 | G312: 张建华 肖青兰 | H312: 赣（2021）吉安市不动产证明第0022214号 | I312: 抵押登记证明 | J312: 56 | K312: 43315 | L312: 50620 | M312: 13528201757 | N312: 黄静杰 | O312: =DATEDIF(K312,L312,"Y") -> 20
A313: 312 | B313: 20210723043601030405015 | C313: 36010304120033421597 | D313: 滨江壹号五期 | E313: 谢兴隆 | F313: 362421199505038310 | G313: 谢兴隆 张祖兰 | H313: 赣（2021）吉安市不动产证明第0022236号 | I313: 抵押登记证明 | J313: 40 | K313: 43900 | L313: 2050/3/10 | M313: 18370607868 | N313: 万淑红 | O313: =DATEDIF(K313,L313,"Y") -> 30
A314: 313 | B314: 20210722043601030405042 | C314: 36010304118071680295 | D314: 滨江壹号三期（又称上江界）A区 | E314: 李德生 | F314: 362422197603262559 | G314: 李德生 彭九香 | H314: 赣（2021）吉安市不动产证明第0022537号 | I314: 抵押登记证明 | J314: 59 | K314: 43290 | L314: 2038/7/9 | M314: 13755446168 | N314: 赖丽君 | O314: =DATEDIF(K314,L314,"Y") -> 20
A315: 314 | B315: 20210721043601030405016 | C315: 36010304118040712860 | D315: 滨江壹号三期（又称上江界）A区 | E315: 李聪 | F315: 362422199509223018 | G315: 李聪 周丹丹 | H315: 赣（2021）吉安市不动产证明第0022224号 | I315: 抵押登记证明 | J315: 54 | K315: 43214 | L315: 2048/4/24 | M315: 15779617174 | N315: 赖丽君 | O315: =DATEDIF(K315,L315,"Y") -> 30
A316: 315 | B316: 20210721043601030405017 | C316: 36010304118082275139 | D316: 滨江壹号三期（又称上江界）A区 | E316: 刘槟 | F316: 362422199712023011 | G316: 刘槟 | H316: 赣（2021）吉安市不动产证明第0022541号 | I316: 抵押登记证明 | J316: 29 | K316: 43336 | L316: 2028/8/24 | M316: 13580737453 | N316: 赖丽君 | O316: =DATEDIF(K316,L316,"Y") -> 10
A317: 316 | B317: 20210721043699950Q05010 | C317: 3699950Q118082329628 | D317: 滨江壹号三期（又称上江界）A区 | E317: 杨经武 | F317: 362422198707165459 | G317: 杨经武 赖文菲 | H317: 赣（2021）吉安市不动产证明第0022259号 | I317: 抵押登记证明 | J317: 50 | K317: 43336 | L317: 2048/8/24 | M317: 18202670906 | N317: 巫淑芬 | O317: =DATEDIF(K317,L317,"Y") -> 30
A318: 317 | B318: 20210721043601030405018 | C318: 36010304117066921121 | D318: 滨江壹号三期（又称上江界）A区 | E318: 胡雪冬 | F318: 362422199111211930 | G318: 胡雪冬 | H318: 赣（2021）吉安市不动产证明第0022543号 | I318: 抵押登记证明 | J318: 38 | K318: 42881 | L318: 2037/5/26 | M318: 13143710870 | N318: 赖丽君 | O318: =DATEDIF(K318,L318,"Y") -> 20
A319: 318 | B319: 20200830043699950Q05029 | C319: 3699950Q120055040824 | D319: 梦想星城（一期） | E319: 李娟 | F319: 362423199209110042 | G319: 李娟 肖兴龙 | H319: 赣（2021）吉安市不动产证明第0022235号 | I319: 抵押登记证明 | J319: 59.7 | K319: 43315 | L319: 50620 | M319: 15170888950 | N319: 郭元 | O319: =DATEDIF(K319,L319,"Y") -> 20
A320: 319 | B320: 20210721043601030405019 | C320: 36010304120033512558 | D320: 滨江壹号(又称上江界）四期（B区） | E320: 颜酉平 | F320: 362426197806207774 | G320: 颜酉平 户志英 | H320: 赣（2021）吉安市不动产证明第0022216号 | I320: 抵押登记证明 | J320: 40 | K320: 43904 | L320: 2035/3/14 | M320: 13826949232 | N320: 赖丽君 | O320: =DATEDIF(K320,L320,"Y") -> 15
A321: 320 | B321: 20210722043601030405001 | C321: 36010304117087508890 | D321: 滨江壹号三期（又称上江界）A区 | E321: 黄春平 | F321: 362422197403282539 | G321: 黄春平 周水红 | H321: 赣（2021）吉安市不动产证明第0022218号 | I321: 抵押登记证明 | J321: 48 | K321: 42928 | L321: 2032/7/12 | M321: 13692831350 | N321: 赖丽君 | O321: =DATEDIF(K321,L321,"Y") -> 15
A322: 321 | B322: 20210722043601030405002 | C322: 36010304118071745308 | D322: 滨江壹号三期（又称上江界）A区 | E322: 刘雪菲 | F322: 362422199001154023 | G322: 刘雪菲 戴水寿 | H322: 赣（2021）吉安市不动产证明第0022544号 | I322: 抵押登记证明 | J322: 49 | K322: 43293 | L322: 2043/7/12 | M322: 15179632713 | N322: 赖丽君 | O322: =DATEDIF(K322,L322,"Y") -> 25
A323: 322 | B323: 20210722043601030405003 | C323: 36010304119045520639 | D323: 滨江壹号(又称上江界）四期（B区） | E323: 吴让晖 | F323: 36242619830917841X | G323: 吴让晖 曾金群 | H323: 赣（2021）吉安市不动产证明第0022220号 | I323: 抵押登记证明 | J323: 47 | K323: 43579 | L323: 2034/4/24 | M323: 13671541391 | N323: 赖丽君 | O323: =DATEDIF(K323,L323,"Y") -> 15
A324: 323 | B324: 20210721043699950Q05011 | C324: 3699950Q118102898042 | D324: 滨江壹号三期（又称上江界）A区 | E324: 罗志红 | F324: 36242119970109351X | G324: 罗志红 | H324: 赣（2021）吉安市不动产证明第0022540号 | I324: 抵押登记证明 | J324: 53 | K324: 43386 | L324: 2038/10/13 | M324: 18870661516 | N324: 巫淑芬 | O324: =DATEDIF(K324,L324,"Y") -> 20
A325: 324 | B325: 20210722043601030405004 | C325: 36010304118040712730 | D325: 滨江壹号三期（又称上江界）A区 | E325: 刘小斌 | F325: 362422197908033570 | G325: 刘小斌 欧阳红苗 | H325: 赣（2021）吉安市不动产证明第0022233号 | I325: 抵押登记证明 | J325: 56 | K325: 43214 | L325: 2038/4/24 | M325: 13006856898 | N325: 赖丽君 | O325: =DATEDIF(K325,L325,"Y") -> 20
A326: 325 | B326: 20210723043601030405006 | C326: 36010304120076705398 | D326: 滨江壹号(又称上江界）四期（B区） | E326: 刘春妹 | F326: 362421198101103548 | G326: 刘春妹 陈斌生 | H326: 赣（2021）吉安市不动产证明第0022243号 | I326: 抵押登记证明 | J326: 55 | K326: 44035 | L326: 2040/7/23 | M326: 15770665882 | N326: 赖丽君 | O326: =DATEDIF(K326,L326,"Y") -> 20
A327: 326 | B327: 20210726043601030405001 | C327: 36010304120054889420 | D327: 滨江壹号(又称上江界）四期（B区） | E327: 康小军 | F327: 362421199109293512 | G327: 康小军 严芳 | H327: 赣（2021）吉安市不动产证明第0022239号 | I327: 抵押登记证明 | J327: 62 | K327: 43963 | L327: 2040/5/12 | M327: 13696984013 | N327: 万淑红 | O327: =DATEDIF(K327,L327,"Y") -> 20
A328: 327 | B328: 20210722043601030405005 | C328: 36010304119066282298 | D328: 滨江壹号(又称上江界）四期（B区） | E328: 张忠椿 | F328: 362421197811157431 | G328: 张忠椿 肖晓珍 | H328: 赣（2021）吉安市不动产证明第0022260号 | I328: 抵押登记证明 | J328: 60 | K328: 43630 | L328: 2043/6/14 | M328: 13530105709 | N328: 赖丽君 | O328: =DATEDIF(K328,L328,"Y") -> 24
A329: 328 | B329: 20210723043601030405016 | C329: 36010304118019746102 | D329: 滨江壹号三期（又称上江界）A区 | E329: 张远香 | F329: 362422198605065422 | G329: 张远香 | H329: 赣（2021）吉安市不动产证明第0022549号 | I329: 抵押登记证明 | J329: 44 | K329: 43132 | L329: 2038/2/1 | M329: 13677967649 | N329: 万淑红 | O329: =DATEDIF(K329,L329,"Y") -> 20
A330: 329 | B330: 20210723043601030405017 | C330: 36010304118123493649 | D330: 滨江壹号(又称上江界）四期（B区） | E330: 李小勇 | F330: 362425198211150017 | G330: 李小勇 曾茜 | H330: 赣（2021）吉安市不动产证明第0022082号 | I330: 抵押登记证明 | J330: 66.7 | K330: 43438 | L330: 2038/12/4 | M330: 13707962073 | N330: 万淑红 | O330: =DATEDIF(K330,L330,"Y") -> 20
A331: 330 | B331: 20210722043601030405006 | C331: 36010316115059515772 | D331: 滨江壹号（又称上江界）B区 | E331: 刘秋燕 | F331: 362421198809208329 | G331: 刘秋燕 | H331: 赣（2021）吉安市不动产证明第0022065号 | I331: 抵押登记证明 | J331: 33.5 | K331: 42130 | L331: 2035/5/6 | M331: 13979663873 | N331: 赖丽君 | O331: =DATEDIF(K331,L331,"Y") -> 20
... A335: 334 | B335: 20210722043601030405008 | C335: 36010304119077020766 | D335: 滨江壹号(又称上江界）四期（B区） | E335: 彭希汉 | F335: 362422199701075115 | G335: 彭希汉 | H335: 赣（2021）吉安市不动产证明第0021585号 | I335: 抵押登记证明 | J335: 55 | K335: 43676 | L335: 2049/7/30 | M335: 17346625387 | N335: 赖丽君 | O335: =DATEDIF(K335,L335,"Y") -> 30
A336: 335 | B336: 20210723043601030405020 | C336: 36010304117097936296 | D336: 滨江首府（三期） | E336: 黄琼 | F336: 452122198811055749 | G336: 黄琼 刘郎平 | H336: 赣（2021）吉安市不动产证明第0021103号 | I336: 抵押登记证明 | J336: 70 | K336: 42970 | L336: 53927 | M336: 13641490720 | N336: 万淑红 | O336: =DATEDIF(K336,L336,"Y") -> 30
A337: 336 | B337: 20210726043601030405002 | C337: 36010304120055272334 | D337: 滨江壹号(又称上江界）四期（B区） | E337: 刘卫明 | F337: 362421198910282312 | G337: 刘卫明 高志芳 | H337: 赣（2021）吉安市不动产证明第0021586号 | I337: 抵押登记证明 | J337: 51.7 | K337: 43978 | L337: 2040/5/27 | M337: 15800760372 | N337: 万淑红 | O337: =DATEDIF(K337,L337,"Y") -> 20
A338: 337 | B338: 20210722043601030405009 | C338: 36010304119035076723 | D338: 滨江壹号(又称上江界）四期（B区） | E338: 朱玉珍 | F338: 362421198503058321 | G338: 朱玉珍 王东平 | H338: 赣（2021）吉安市不动产证明第0021581号 | I338: 抵押登记证明 | J338: 50 | K338: 43551 | L338: 2044/3/27 | M338: 13412802517 | N338: 赖丽君 | O338: =DATEDIF(K338,L338,"Y") -> 25
A339: 338 | B339: 20210723043601030405007 | C339: 36010304120097933668 | D339: 滨江壹号(又称上江界）四期（B区） | E339: 李雄达 | F339: 362426198804178417 | G339: 李雄达 夏艳君 | H339: 赣（2021）吉安市不动产证明第0021582号 | I339: 抵押登记证明 | J339: 51 | K339: 44088 | L339: 2050/9/14 | M339: 18664300352 | N339: 赖丽君 | O339: =DATEDIF(K339,L339,"Y") -> 30
...

Sheet 车贷
A1: 序号 | B1: 封包号 | C1: 业务合同编号 | D1: 借款人 | E1: 抵押人 | F1: 贷种 | G1: 机动车登记编号 | H1: 机动车登记证书编号 | I1: 抵押金额（万元） | J1: 抵押登记日期 | K1: 借款期限 | L1: 客户经理 | M1: 工号 | N1: 放款日期 | O1: 车辆品牌 | P1: 登记日期
A2: 818 | B2: cd000000000000000000818 | C2: 36010304121119788040 | D2: 郭嘉文 | E2: 郭嘉文 | F2: 个人汽车消费贷款（合作平台） | G2: 赣DD22215 | H2: 360016733117 | I2: 10 | J2: 44532 | K2: 3 | L2: 赖丽君
A3: 819 | B3: cd000000000000000000819 | C3: 36010304121119803088 | D3: 阮文捷 | E3: 阮文捷 | F3: 个人汽车消费贷款（合作平台） | G3: 赣DR4656 | H3: 360016733109 | I3: 10 | J3: 44538 | K3: 3 | L3: 赖丽君
A4: 820 | B4: cd000000000000000000820 | C4: 36010304121120345719 | D4: 谢廖莎 | E4: 谢廖莎 | F4: 个人汽车消费贷款（合作平台） | G4: 赣D1816W | H4: 360014593842 | I4: 13 | J4: 44545 | K4: 5 | L4: 万淑红
A5: 821 | B5: cd000000000000000000821 | C5: 36010304121120828033 | D5: 肖汉英 | E5: 肖汉英 | F5: 个人汽车消费贷款（合作平台） | G5: 赣DCJ532 | H5: 360017464571 | I5: 15.4 | J5: 44583 | K5: 3 | L5: 万淑红
A6: 822 | B6: cd000000000000000000822 | C6: 36010304122033428267 | D6: 李深渊 | E6: 李深渊 | F6: 个人汽车消费贷款（合作平台） | G6: 赣DAB752 | H6: 360016757441 | I6: 10 | J6: 44648 | K6: 5 | L6: 万淑红
A7: 823 | B7: cd000000000000000000823 | C7: 36010278122044078424 | D7: 曾金华 | E7: 曾金华 | F7: 个人汽车消费贷款（快速） | G7: 赣D22V00 | H7: 360018810363 | I7: 7 | J7: 44664 | K7: 3 | L7: 谢文青
A8: 824 | B8: cd000000000000000000824 | C8: 2022041280002431 | D8: 曾卫明 | E8: 曾卫明 | F8: 汽车分期 | G8: 赣D676A8 | H8: 360016785898 | I8: 16 | J8: 44673 | K8: 5 | L8: 王婷
A9: 825 | B9: cd000000000000000000825 | C9: 2022042680001466 | D9: 范芳云 | E9: 范芳云 | F9: 汽车分期 | G9: 赣DQ9655 | H9: 360018864876 | I9: 10 | J9: 44680 | K9: 3 | L9: 郭玲风
A10: 826 | B10: cd000000000000000000826 | C10: 2022042580001203 | D10: 刘新美 | E10: 刘新美 | F10: 汽车分期 | G10: 赣DFD802 | H10: 360018864890 | I10: 25 | J10: 44679 | K10: 5 | L10: 郭玲风
A11: 827 | B11: cd000000000000000000827 | C11: 2022042580003264 | D11: 欧阳军军 | E11: 欧阳军军 | F11: 汽车分期 | G11: 赣D22U51 | H11: 360018864883 | I11: 33 | J11: 44679 | K11: 5 | L11: 郭玲风
A12: 828 | B12: cd000000000000000000828 | C12: 2022042580001570 | D12: 尹奕花 | E12: 尹奕花 | F12: 汽车分期 | G12: 赣DGB711 | H12: 360018864873 | I12: 20 | J12: 44680 | K12: 5 | L12: 郭玲风
A13: 829 | B13: cd000000000000000000829 | C13: 2022050780001519 | D13: 颜运林 | E13: 颜运林 | F13: 汽车分期 | G13: 赣DHT313 | H13: 360018863228 | I13: 14.9 | J13: 44690 | K13: 5 | L13: 谢文青
... A155: 971 | B155: cd000000000000000000971 | C155: 2022100780000805 | D155: 肖慧玲 | E155: 肖慧玲 | F155: 汽车分期 | G155: 赣D05A83 | H155: 360019439377 | I155: 30 | J155: 44845 | K155: 5 | L155: 黄艳
A156: 972 | B156: cd000000000000000000972 | C156: 2022101080001139 | D156: 欧阳燕虹 | E156: 欧阳燕虹 | F156: 汽车分期 | G156: 赣DEP373 | H156: 360018097752 | I156: 20.9 | J156: 44848 | K156: 5 | L156: 黄艳 | M156: 20080117330 | N156: 44847 | O156: 梅赛德斯-奔驰牌 | P156: 44848
A157: 973 | B157: cd000000000000000000973 | C157: 2022100980001074 | D157: 王嘉敏 | E157: 王嘉敏 | F157: 汽车分期 | G157: 赣D8547DS | H157: 360018816499 | I157: 20 | J157: 44848 | K157: 5 | L157: 黄艳 | M157: 20080117330 | N157: 44845 | O157: 梅赛德斯-奔驰牌 | P157: 44848
A158: 974 | B158: cd000000000000000000974 | C158: 2022100880000966 | D158: 王清和 | E158: 王清和 | F158: 汽车分期 | G158: 赣DEB968 | H158: 360018816497 | I158: 20 | J158: 44848 | K158: 5 | L158: 黄艳 | M158: 20080117330 | N158: 44847 | O158: 梅赛德斯-奔驰牌 | P158: 44848
A159: 975 | B159: cd000000000000000000975 | C159: 2022101280002257 | D159: 杨艺芳 | E159: 杨艺芳 | F159: 汽车分期 | G159: 赣DDA603 | H159: 360018097751 | I159: 15 | J159: 44848 | K159: 5 | L159: 黄艳 | M159: 20080117330 | N159: 44847 | O159: 梅赛德斯-奔驰牌 | P159: 44848
A160: 976 | B160: cd000000000000000000976 | C160: 2022100880000911 | D160: 曾新华 | E160: 曾新华 | F160: 汽车分期 | G160: 赣DBZ357 | H160: 360018097771 | I160: 20 | J160: 44851 | K160: 5 | L160: 黄艳 | M160: 20080117330 | N160: 44851 | O160: 梅赛德斯-奔驰牌 | P160: 44851
A161: 977 | B161: cd000000000000000000977 | C161: 2022101380000961 | D161: 林贵鸿 | E161: 林贵鸿 | F161: 汽车分期 | G161: 赣DGR310 | H161: 360018097772 | I161: 36 | J161: 44851 | K161: 5 | L161: 黄艳 | M161: 20080117330 | N161: 44851 | O161: 梅赛德斯-奔驰牌 | P161: 44851
A162: 978 | B162: cd000000000000000000978 | C162: 2022101780000674 | D162: 卢心月 | E162: 卢心月 | F162: 汽车分期 | G162: 赣DDQ516 | H162: 360018097788 | I162: 23 | J162: 44854 | K162: 5 | L162: 黄艳 | M162: 20080117330 | N162: 44852 | O162: 梅赛德斯-奔驰牌 | P162: 44854
A163: 979 | B163: cd000000000000000000979 | C163: 2022081280002921 | D163: 匡建华 | E163: 匡建华 | F163: 汽车分期 | G163: 赣DF87139 | H163: 360018858193 | I163: 20 | J163: 44844 | K163: 4 | L163: 胡涛 | M163: 20090703750 | N163: 44844 | O163: 赛力斯牌 | P163: 44844
A164: 980 | B164: cd000000000000000000980 | C164: 2022102380000929 | D164: 缪雪萍 | E164: 缪雪萍 | F164: 汽车分期 | G164: 赣DAU997 | H164: 360018097722 | I164: 25 | J164: 44860 | K164: 5 | L164: 黄艳 | M164: 20080117330 | N164: 44859 | O164: 梅赛德斯-奔驰牌 | P164: 44860
A165: 981 | B165: cd000000000000000000981 | C165: 2022082280001690 | D165: 王振 | E165: 王振 | F165: 汽车分期 | G165: 赣D59556 | H165: 360018816450 | I165: 25 | J165: 44805 | K165: 3 | L165: 黄艳
A166: 982 | B166: cd000000000000000000982 | C166: 36010278122100061670 | D166: 付雪兵 | E166: 付雪兵 | F166: 个人汽车消费贷款（快速） | G166: 赣D01Y20 | H166: 360018880190 | I166: 8 | J166: 44859 | K166: 5 | L166: 王婷 | M166: 20111138170 | N166: 44860 | O166: 本田牌 | P166: 44859
A167: 983 | B167: cd000000000000000000983 | C167: 2022102580000765 | D167: 刘云明 | E167: 刘云明 | F167: 汽车分期 | G167: 赣D903V6 | H167: 360018097729 | I167: 31 | J167: 44862 | K167: 5 | L167: 黄艳 | M167: 20080117330 | N167: 44860 | O167: 梅赛德斯-奔驰牌 | P167: 44862
A168: 984 | B168: cd000000000000000000984 | C168: 2022092980002861 | D168: 郭庭裕 | E168: 郭庭裕 | F168: 汽车分期 | G168: 赣D5559K | H168: 360018078446 | I168: 15 | J168: 44843 | K168: 5 | L168: 李俊 | M168: 20200856460 | N168: 44842 | O168: 凯迪拉克牌 | P168: 44843
A169: 985 | B169: cd000000000000000000985 | C169: 2022103080000882 | D169: 罗小勇 | E169: 罗小勇 | F169: 汽车分期 | G169: 赣D3E996 | H169: 360018097854 | I169: 20 | J169: 44867 | K169: 5 | L169: 黄艳 | M169: 20080117330 | N169: 44867 | O169: 梅赛德斯-奔驰牌 | P169: 44867
A170: 986 | B170: cd000000000000000000986 | C170: 2022103080000434 | D170: 吴亮明 | E170: 吴亮明 | F170: 汽车分期 | G170: 赣DGB808 | H170: 360016764429 | I170: 18 | J170: 44867 | K170: 3 | L170: 梅洁 | M170: 20090741840 | N170: 44866 | O170: 梅赛德斯-奔驰牌 | P170: 44867
A171: 987 | B171: cd000000000000000000987 | C171: 2022102880001529 | D171: 谢玮 | E171: 谢玮 | F171: 汽车分期 | G171: 赣D2518Z | H171: 360018097862 | I171: 20 | J171: 44868 | K171: 3 | L171: 黄艳 | M171: 20080117330 | N171: 44866 | O171: 梅赛德斯-奔驰牌 | P171: 44868
A172: 988 | B172: cd000000000000000000988 | C172: 2022103080000365 | D172: 杨坤 | E172: 杨坤 | F172: 汽车分期 | G172: 赣D8232Z | H172: 360018097861 | I172: 15 | J172: 44868 | K172: 5 | L172: 梅洁 | M172: 20090741840 | N172: 44867 | O172: 梅赛德斯-奔驰牌 | P172: 44868
A173: 989 | B173: cd000000000000000000989 | C173: 2022103080000273 | D173: 蒋邦纲 | E173: 蒋邦纲 | F173: 汽车分期 | G173: 赣DGB126 | H173: 360018097570 | I173: 24.8 | J173: 44872 | K173: 5 | L173: 梅洁 | M173: 20090741840 | N173: 44867 | O173: 梅赛德斯-奔驰牌 | P173: 44872
A174: 990 | B174: cd000000000000000000990 | C174: 2022102580003553 | D174: 李艳 | E174: 李艳 | F174: 汽车分期 | G174: 赣D68S30 | H174: 360018097867 | I174: 30 | J174: 44872 | K174: 5 | L174: 黄艳 | M174: 20080117330 | N174: 44862 | O174: 梅赛德斯-奔驰牌 | P174: 44872
A175: 991 | B175: cd000000000000000000991 | C175: 2022110180001773 | D175: 喻小兰 | E175: 喻小兰 | F175: 汽车分期 | G175: 赣DEJ638 | H175: 360018097567 | I175: 17.5 | J175: 44869 | K175: 5 | L175: 黄艳 | M175: 20080117330 | N175: 44869 | O175: 梅赛德斯-奔驰牌 | P175: 44869
A176: 992 | B176: cd000000000000000000992 | C176: 2022102580003006 | D176: 朱芬芬 | E176: 朱芬芬 | F176: 汽车分期 | G176: 赣DGT822 | H176: 360018097863 | I176: 23 | J176: 44868 | K176: 5 | L176: 黄艳 | M176: 20080117330 | N176: 44862 | O176: 梅赛德斯-奔驰牌 | P176: 44868
A177: 993 | B177: cd000000000000000000993 | C177: 2022071280001411 | D177: 黄波 | E177: 黄波 | F177: 汽车分期 | G177: 赣H9K730 | H177: 360017516505 | I177: 15 | J177: 44875 | K177: 5 | L177: 谢文青 | M177: 20110321710 | N177: 44756 | O177: 凯迪拉克牌 | P177: 44781
... A198: 1014 | B198: cd000000000000000001014 | C198: 2022112380001524 | D198: 杨美英 | E198: 杨美英 | F198: 汽车分期 | G198: 赣D5235M | H198: 360018097541 | I198: 30 | J198: 44890 | K198: 5 | L198: 严利 | M198: 20210843420 | N198: 44889 | O198: 梅赛德斯-奔驰牌 | P198: 44890
A199: 1015 | B199: cd000000000000000001015 | C199: 2022110780001845 | D199: 罗小年 | E199: 罗小年 | F199: 汽车分期 | G199: 赣DDH520 | H199: 360018853148 | I199: 12 | J199: 44895 | K199: 5 | L199: 李俊 | M199: 20200856460 | N199: 44880 | O199: 凯迪拉克牌 | P199: 44895 | Q199: 20230222FQ3600006301001
A200: 1016 | B200: cd000000000000000001016 | C200: 2022113080001308 | D200: 李江娅 | E200: 李江娅 | F200: 汽车分期 | G200: 赣D55672 | H200: 360018097849 | I200: 25 | J200: 44901 | K200: 5 | L200: 严利 | M200: 20210843420 | N200: 44901 | O200: 梅赛德斯-奔驰牌 | P200: 44901
A201: 1017 | B201: cd000000000000000001017 | C201: 2022112480002205 | D201: 王丽娟 | E201: 王丽娟 | F201: 汽车分期 | G201: 赣DHY890 | H201: 360018097836 | I201: 15.3 | J201: 44896 | K201: 5 | L201: 严利 | M201: 20210843420 | N201: 44894 | O201: 梅赛德斯-奔驰牌 | P201: 44895
A202: 1018 | B202: cd000000000000000001018 | C202: 2022120480000414 | D202: 温丽玲 | E202: 温丽玲 | F202: 汽车分期 | G202: 赣D5972 | H202: 360018097661 | I202: 20 | J202: 44904 | K202: 5 | L202: 严利 | M202: 20210843420 | N202: 44902 | O202: 梅赛德斯-奔驰牌 | P202: 44904
A203: 1019 | B203: cd000000000000000001019 | C203: 2022120480000487 | D203: 谢路明 | E203: 谢路明 | F203: 汽车分期 | G203: 赣DHU098 | H203: 360018097662 | I203: 19.46 | J203: 44904 | K203: 5 | L203: 严利 | M203: 20210843420 | N203: 44902 | O203: 梅赛德斯-奔驰牌 | P203: 44904
A204: 1020 | B204: cd000000000000000001020 | C204: 2022112980001391 | D204: 徐玲玲 | E204: 徐玲玲 | F204: 汽车分期 | G204: 赣DCD670 | H204: 360018097545 | I204: 20 | J204: 44900 | K204: 5 | L204: 严利 | M204: 20210843420 | N204: 44895 | O204: 梅赛德斯-奔驰牌 | P204: 44900
A205: 1021 | B205: cd000000000000000001021 | C205: 2022120580000215 | D205: 邹采宝 | E205: 邹采宝 | F205: 汽车分期 | G205: 赣DHZ518 | H205: 360018097847 | I205: 30 | J205: 44901 | K205: 5 | L205: 严利 | M205: 20210843420 | N205: 44901 | O205: 梅赛德斯-奔驰牌 | P205: 44901
A206: 1022 | B206: cd000000000000000001022 | C206: 2022111180001216 | D206: 李美玲 | E206: 李美玲 | F206: 汽车分期 | G206: 赣DHH758 | H206: 360018083136 | I206: 20 | J206: 44890 | K206: 5 | L206: 胡涛 | M206: 20090703750 | N206: 44889 | O206: 奥迪牌 | P206: 44890
A207: 1023 | B207: cd000000000000000001023 | C207: 2022111280001002 | D207: 钟小青 | E207: 钟小青 | F207: 汽车分期 | G207: 赣DDH083 | H207: 360018097957 | I207: 20 | J207: 44904 | K207: 5 | L207: 严利 | M207: 20210843420 | N207: 44903 | O207: 梅赛德斯-奔驰牌 | P207: 44904
A208: 1024 | B208: cd000000000000000001024 | C208: 2022120980001458 | D208: 左光华 | E208: 左光华 | F208: 汽车分期 | G208: 赣DEY816 | H208: 360018097964 | I208: 20 | J208: 44907 | K208: 5 | L208: 严利 | M208: 20210843420 | N208: 44907 | O208: 梅赛德斯-奔驰牌 | P208: 44907
A209: 1025 | B209: cd000000000000000001025 | C209: 2022121180000440 | D209: 林桂文 | E209: 林桂文 | F209: 汽车分期 | G209: 赣D7822J | H209: 36009425990 | I209: 80 | J209: 44915 | K209: 5 | L209: 梅洁 | M209: 20090741840 | N209: 44914 | O209: 梅赛德斯-奔驰牌 | P209: 44915
A210: 1026 | B210: cd000000000000000001026 | C210: 2022121280000640 | D210: 赵静 | E210: 赵静 | F210: 汽车分期 | G210: 赣D5518F | H210: 360018097914 | I210: 20 | J210: 44923 | K210: 5 | L210: 梅洁 | M210: 20090741840 | N210: 44915 | O210: 梅赛德斯-奔驰牌 | P210: 44923
A211: 1027 | B211: cd000000000000000001027 | C211: 2022121280002010 | D211: 刘远强 | E211: 刘远强 | F211: 汽车分期 | G211: 赣D72677 | H211: 360018097987 | I211: 20 | J211: 44915 | K211: 5 | L211: 严利 | M211: 20210843420 | N211: 44909 | O211: 梅赛德斯-奔驰牌 | P211: 44915
A212: 1028 | B212: cd000000000000000001028 | C212: 2022121280001559 | D212: 卢云华 | E212: 卢云华 | F212: 汽车分期 | G212: 赣DHV960 | H212: 360018097913 | I212: 30 | J212: 44922 | K212: 5 | L212: 严利 | M212: 20210843420 | N212: 44922 | O212: 梅赛德斯-奔驰牌 | P212: 44922
A213: 1029 | B213: cd000000000000000001029 | C213: 2022120980002380 | D213: 宋清 | E213: 宋清 | F213: 汽车分期 | G213: 赣D233V2 | H213: 360018097975 | I213: 15 | J213: 44910 | K213: 5 | L213: 严利 | M213: 20210843420 | N213: 44908 | O213: 梅赛德斯-奔驰牌 | P213: 44910
A214: 1030 | B214: cd000000000000000001030 | C214: 2022121180000681 | D214: 王秀兰 | E214: 王秀兰 | F214: 汽车分期 | G214: 赣DBC156 | H214: 360018097682 | I214: 30.5 | J214: 44909 | K214: 5 | L214: 严利 | M214: 20210843420 | N214: 44908 | O214: 梅赛德斯-奔驰牌 | P214: 44909
A215: 1031 | B215: cd000000000000000001031 | C215: 36010278122121859730 | D215: 赖章平 | E215: 赖章平 | F215: 个人汽车消费贷款（快速） | G215: 赣D8805X | H215: 360018887071 | I215: 60 | J215: 44915 | K215: 3 | L215: 王婷
A216: 1032 | B216: cd000000000000000001032 | C216: 2023010380000301 | D216: 曾琳慧添 | E216: 曾琳慧添 | F216: 汽车分期 | G216: 赣D2000Y | H216: 360018097639 | I216: 15 | J216: 44930 | K216: 5 | L216: 严利 | M216: 20210843420 | N216: 44930 | O216: 梅赛德斯-奔驰牌 | P216: 44930
A217: 1033 | B217: cd000000000000000001033 | C217: 2022122980001073 | D217: 曾珊珊 | E217: 曾珊珊 | F217: 汽车分期 | G217: 赣D6369N | H217: 360018097933 | I217: 20 | J217: 44930 | K217: 5 | L217: 严利 | M217: 20210843420 | N217: 44929 | O217: 梅赛德斯-奔驰牌 | P217: 44930
A218: 1034 | B218: cd000000000000000001034 | C218: 2022113080001041 | D218: 王小梅 | E218: 王小梅 | F218: 汽车分期 | G218: 赣D516X8 | H218: 360018097922 | I218: 15 | J218: 44929 | K218: 3 | L218: 梅洁 | M218: 20090741840 | N218: 44915 | O218: 梅赛德斯-奔驰牌 | P218: 44929
A219: 1035 | B219: cd000000000000000001035 | C219: 2022122880000940 | D219: 朱冬兰 | E219: 朱冬兰 | F219: 汽车分期 | G219: 赣D11S90 | H219: 360018097637 | I219: 20 | J219: 44930 | K219: 5 | L219: 严利 | M219: 20210843420 | N219: 44927 | O219: 梅赛德斯-奔驰牌 | P219: 44930
A220: 1036 | B220: cd000000000000000001036 | C220: 2022121780000267 | D220: 刘芳 | E220: 刘芳 | F220: 汽车分期 | G220: 赣DDW837 | H220: 360018097634 | I220: 25 | J220: 44930 | K220: 3 | L220: 严利 | M220: 20210843420 | N220: 44930 | O220: 梅赛德斯-奔驰牌 | P220: 44930
A221: 1037 | B221: cd000000000000000001037 | C221: 2022122080000420 | D221: 钟海峰 | E221: 钟海峰 | F221: 汽车分期 | G221: 赣D36S76 | H221: 360018097633 | I221: 20 | J221: 44930 | K221: 5 | L221: 严利 | M221: 20210843420 | N221: 44922 | O221: 梅赛德斯-奔驰牌 | P221: 44930
A222: 1038 | B222: cd000000000000000001038 | C222: 36010278122122447290 | D222: 李刚 | E222: 李刚 | F222: 个人汽车消费贷款（快速） | G222: 赣D628B7 | H222: 360018836560 | I222: 13.5 | J222: 44935 | K222: 3 | L222: 王婷 | M222: 20111138170 | N222: 44936 | O222: 丰田牌 | P222: 44931
A223: 1039 | B223: cd000000000000000001039 | C223: 2023010280000285 | D223: 邓煌生 | E223: 邓煌生 | F223: 汽车分期 | G223: 赣D2563M | H223: 360019425900 | I223: 49.9 | J223: 44935 | K223: 5 | L223: 严利 | M223: 20210843420 | N223: 44932 | O223: 梅赛德斯-奔驰 | P223: 44935
A224: 1040 | B224: cd000000000000000001040 | C224: 2023010580001476 | D224: 刘清 | E224: 刘清 | F224: 汽车分期 | G224: 赣DDJ017 | H224: 360019499750 | I224: 20 | J224: 44935 | K224: 5 | L224: 严利 | M224: 20210843420 | N224: 44932 | O224: 梅赛德斯-奔驰 | P224: 44935
A225: 1041 | B225: cd000000000000000001041 | C225: 2022122780000410 | D225: 夏贵阳 | E225: 夏贵阳 | F225: 汽车分期 | G225: 赣DBP537 | H225: 360019425853 | I225: 40 | J225: 44935 | K225: 5 | L225: 严利 | M225: 20210843420 | N225: 44927 | O225: 梅赛德斯-奔驰 | P225: 44935
A226: 1042 | B226: cd000000000000000001042 | C226: 2023010480001373 | D226: 郭圣涛 | E226: 郭圣涛 | F226: 汽车分期 | G226: 赣DQ7198 | H226: 360019499727 | I226: 20 | J226: 44937 | K226: 5 | L226: 严利 | M226: 20210843420 | N226: 44936 | O226: 梅赛德斯-奔驰牌 | P226: 44937
A227: 1043 | B227: cd000000000000000001043 | C227: 2022122980000563 | D227: 李红仔 | E227: 李红仔 | F227: 汽车分期 | G227: 赣DEK500 | H227: 360018836665 | I227: 15 | J227: 44930 | K227: 5 | L227: 李俊 | M227: 20200856460 | N227: 44927 | O227: 凯迪拉克牌 | P227: 44930
... A247: 1063 | B247: cd000000000000000001063 | C247: 2023020280000673 | D247: 王国良 | E247: 王国良 | F247: 汽车分期 | G247: 赣D269V8 | H247: 360018843437 | I247: 10 | J247: 44960 | K247: 3 | L247: 张薇 | M247: 20110935710 | N247: 44960 | O247: 领克牌 | P247: 44960
A248: 1064 | B248: cd000000000000000001064 | C248: 2022082880000924 | D248: 王山英 | E248: 王山英 | F248: 汽车分期 | G248: 赣D33440 | H248: 360018078439 | I248: 15 | J248: 44842 | K248: 3 | L248: 刘涛
A249: 1065 | B249: 20230227FQ3600006301001 | C249: 2023022180004425 | D249: 罗经祥 | E249: 罗经祥 | F249: 汽车分期 | G249: 赣DDT909 | H249: 360019439906 | I249: 8 | J249: 44979 | K249: 3 | L249: 李俊 | M249: 20200856460 | N249: 44980 | O249: 北京现代牌 | P249: 44979
A250: 1066 | B250: 20230306FQ3600006301001 | C250: 2023022080001507 | D250: 张春暖 | E250: 张春暖 | F250: 汽车分期 | G250: 赣DFA221 | H250: 360018843038 | I250: 8.8 | J250: 44978 | K250: 5 | L250: 黄艳 | M250: 20080117330 | N250: 44978 | O250: 东风日产 | P250: 44978
A251: 1067 | B251: 20230320FQ3600006301001 | C251: 2023011380001221 | D251: 黄丹 | E251: 黄丹 | F251: 汽车分期 | G251: 赣DS4895 | H251: 360018843235 | I251: 8 | J251: 44942 | K251: 5 | L251: 李俊 | M251: 20200856460 | N251: 44940 | O251: 领克牌 | P251: 44942
A252: 1068 | B252: 20230320FQ3600006301002 | C252: 2023022580001695 | D252: 刘怡菁 | E252: 刘怡菁 | F252: 汽车分期 | G252: 赣D8290M | H252: 360019391127 | I252: 10 | J252: 44991 | K252: 5 | L252: 梁洁 | M252: 20090742070 | N252: 44987 | O252: 宝马牌 | P252: 44991
A253: 1069 | B253: 20230320FQ3600006301003 | C253: 2023030480001020 | D253: 习平 | E253: 习平 | F253: 汽车分期 | G253: 赣DDQ636 | H253: 360019431042 | I253: 20 | J253: 44992 | K253: 5 | L253: 李俊 | M253: 20200856460 | N253: 44992 | O253: 奥迪牌 | P253: 44992
A254: 1070 | B254: 20230320FQ3600006301004 | C254: 2023022680001153 | D254: 肖国华 | E254: 肖国华 | F254: 汽车分期 | G254: 赣D1T069 | H254: 360019439955 | I254: 28 | J254: 44987 | K254: 5 | L254: 李俊 | M254: 20200856460 | N254: 44986 | O254: 奥迪牌 | P254: 44987
A255: 1071 | B255: 20230320FQ3600006301005 | C255: 2023022380004027 | D255: 肖文英 | E255: 肖文英 | F255: 汽车分期 | G255: 赣DCC219 | H255: 360019439977 | I255: 21 | J255: 44985 | K255: 5 | L255: 胡涛 | M255: 20090703750 | N255: 44981 | O255: 奥迪牌 | P255: 44985
A256: 1072 | B256: 20230320FQ3600006301006 | C256: 2023022680001325 | D256: 张小燕 | E256: 张小燕 | F256: 汽车分期 | G256: 赣D7933L | H256: 360019439961 | I256: 19 | J256: 44986 | K256: 5 | L256: 李俊 | M256: 20200856460 | N256: 44985 | O256: 奥迪牌 | P256: 44986
A257: 1073 | B257: 20230320FQ3600006301007 | C257: 2023030580001074 | D257: 钟梦庄 | E257: 钟梦庄 | F257: 汽车分期 | G257: 赣DNL835 | H257: 360019391188 | I257: 25 | J257: 44993 | K257: 5 | L257: 梁洁 | M257: 20090742070 | N257: 44993 | O257: 宝马牌 | P257: 44993
A258: 1074 | B258: 20230331FQ3600006301001 | C258: 2023021180001444 | D258: 胡文香 | E258: 胡文香 | F258: 汽车分期 | G258: 赣D5008W | H258: 360019439927 | I258: 15 | J258: 44971 | K258: 5 | L258: 严利 | M258: 20210843420 | N258: 44971 | O258: 奥迪牌 | P258: 44971
A259: 1075 | B259: 20230331FQ3600006301002 | C259: 2023030580000537 | D259: 陈小红 | E259: 陈小红 | F259: 汽车分期 | G259: 赣D171V6 | H259: 360019431020 | I259: 14 | J259: 44995 | K259: 5 | L259: 李俊 | M259: 20200856460 | N259: 44995 | O259: 奥迪牌 | P259: 44995
A260: 1076 | B260: 20230331FQ3600006301003 | C260: 2023031180001190 | D260: 胡梅林 | E260: 胡梅林 | F260: 汽车分期 | G260: 赣D559W0 | H260: 360019431096 | I260: 17 | J260: 45001 | K260: 5 | L260: 李俊 | M260: 20200856460 | N260: 44998 | O260: 奥迪牌 | P260: 45001
... A333: 1149 | B333: 20230525FQ3600006301003 | C333: 2023042380003302 | D333: 赵勇 | E333: 赵勇 | F333: 汽车分期 | G333: 赣D57600 | H333: 360019499831 | I333: 22 | J333: 45043 | K333: 5 | L333: 严利 | M333: 20210843420 | N333: 45043 | O333: 梅赛德斯-奔驰牌 | P333: 45043
A334: 1150 | B334: 20230525FQ3600006301004 | C334: 2023042480003860 | D334: 周娟萍 | E334: 周娟萍 | F334: 汽车分期 | G334: 赣D5E526 | H334: 36019431322 | I334: 13 | J334: 45050 | K334: 5 | L334: 严利 | M334: 20210843420 | N334: 45045 | O334: 奥迪牌 | P334: 45050
A335: 1151 | B335: 20230525FQ3600006301005 | C335: 2023042380001703 | D335: 朱春燕 | E335: 朱春燕 | F335: 汽车分期 | G335: 赣DZJ282 | H335: 360019499555 | I335: 15 | J335: 45050 | K335: 5 | L335: 严利 | M335: 20210843420 | N335: 45051 | O335: 梅赛德斯-奔驰牌 | P335: 45050
A336: 1152 | B336: 20230525FQ3600006301006 | C336: 2023041280003033 | D336: 左星明 | E336: 左星明 | F336: 汽车分期 | G336: 赣D62F06 | H336: 360019431298 | I336: 20 | J336: 45033 | K336: 5 | L336: 严利 | M336: 20210843420 | N336: 45030 | O336: 奥迪牌 | P336: 45033
A337: 1153 | B337: cd000000000000000001153 | C337: 36010278123057053165 | D337: 郭兰玉 | E337: 郭兰玉 | F337: 汽车贷款 | G337: 赣D658W1 | H337: 360018860288 | I337: 5 | J337: 45057 | K337: 3 | L337: 王婷 | M337: 20111138170 | N337: 45057 | O337: 丰田牌 | P337: 45057
A338: 1154 | B338: 20230525FQ3600006301007 | C338: 2023050680000753 | D338: 李伟 | E338: 李伟 | F338: 汽车分期 | G338: 赣D2D226 | H338: 360019431425 | I338: 10 | J338: 45054 | K338: 3 | L338: 李俊 | M338: 20200856460 | N338: 45054 | O338: 北京现代牌 | P338: 45054
A339: 1155 | B339: 20230525FQ3600006301008 | C339: 2023051880001719 | D339: 曾琼 | E339: 曾琼 | F339: 汽车分期 | G339: 赣DNL806 | H339: 360019473569 | I339: 10 | J339: 45064 | K339: 5 | L339: 黄艳 | M339: 20080117330 | N339: 45064 | O339: 东风日产牌 | P339: 45064
A340: 1156 | B340: 20230525FQ3600006301009 | C340: 2023051380001587 | D340: 陈关 | E340: 陈关 | F340: 汽车分期 | G340: 赣DMW201 | H340: 360019430045 | I340: 29 | J340: 45063 | K340: 5 | L340: 李俊 | M340: 20200856460 | N340: 45063 | O340: 奥迪牌 | P340: 45063
A341: 1157 | B341: 20230525FQ3600006301010 | C341: 2023033180006608 | D341: 丁建军 | E341: 丁建军 | F341: 汽车分期 | G341: 赣DLS379 | H341: 360019431238 | I341: 25.5 | J341: 45026 | K341: 5 | L341: 李俊 | M341: 20200856460 | N341: 45022 | O341: 奥迪牌 | P341: 45026
A342: 1158 | B342: 20230525FQ3600006301011 | C342: 2023051380002680 | D342: 黄婉婷 | E342: 黄婉婷 | F342: 汽车分期 | G342: 赣D03D71 | H342: 360019430038 | I342: 13 | J342: 45064 | K342: 5 | L342: 李俊 | M342: 20200856460 | N342: 45061 | O342: 奥迪牌 | P342: 45064
A343: 1159 | B343: 20230525FQ3600006301012 | C343: 2023051280004100 | D343: 李慧星 | E343: 李慧星 | F343: 汽车分期 | G343: 赣D5752Y | H343: 360019491795 | I343: 10 | J343: 45063 | K343: 5 | L343: 梁洁 | M343: 20090742070 | N343: 45061 | O343: 宝马牌 | P343: 45063
A344: 1160 | B344: 20230525FQ3600006301013 | C344: 2023050380002178 | D344: 刘成 | E344: 刘成 | F344: 汽车分期 | G344: 赣DSK546 | H344: 360019431480 | I344: 16 | J344: 45058 | K344: 5 | L344: 梁洁 | M344: 20090742070 | N344: 45057 | O344: 奥迪牌 | P344: 45058
A345: 1161 | B345: 20230525FQ3600006301014 | C345: 2023051280001983 | D345: 王美燕 | E345: 王美燕 | F345: 汽车分期 | G345: 赣D3Q088 | H345: 360019491638 | I345: 24.3 | J345: 45064 | K345: 5 | L345: 梁洁 | M345: 20090742070 | N345: 45062 | O345: 宝马牌 | P345: 45064
A346: 1162 | B346: 20230525FQ3600006301015 | C346: 2023050480001621 | D346: 王生龙 | E346: 王生龙 | F346: 汽车分期 | G346: 赣D126Q0 | H346: 360019430049 | I346: 24 | J346: 45061 | K346: 5 | L346: 黄艳 | M346: 20080117330 | N346: 45052 | O346: 奥迪牌 | P346: 45061
... A414: 1230 | B414: 20230711FQ3600006301003 | C414: 2023053080003431 | D414: 胡烈武 | E414: 胡烈武 | F414: 汽车分期 | G414: 赣DPH881 | H414: 360019457787 | I414: 25 | J414: 45089 | K414: 5 | L414: 严利 | M414: 20210843420 | N414: 45079 | O414: 梅赛德斯-奔驰牌 | P414: 45089
A415: 1231 | B415: 20230711FQ3600006301004 | C415: 2023061380003117 | D415: 黄广兴 | E415: 黄广兴 | F415: 汽车分期 | G415: 赣DJN109 | H415: 36019457908 | I415: 20 | J415: 45093 | K415: 5 | L415: 严利 | M415: 20210843420 | N415: 45092 | O415: 梅赛德斯-奔驰牌 | P415: 45093
A416: 1232 | B416: 20230711FQ3600006301005 | C416: 2023060780004651 | D416: 刘家明 | E416: 刘家明 | F416: 汽车分期 | G416: 赣DM5993 | H416: 360019457769 | I416: 20 | J416: 45092 | K416: 5 | L416: 严利 | M416: 20210843420 | N416: 45089 | O416: 梅赛德斯-奔驰牌 | P416: 45092
A417: 1233 | B417: 20230711FQ3600006301006 | C417: 2023052480003853 | D417: 龙洋 | E417: 龙洋 | F417: 汽车分期 | G417: 赣D09T06 | H417: 360019490502 | I417: 20 | J417: 45078 | K417: 5 | L417: 贺雄英 | M417: 20110321640 | N417: 45077 | O417: 梅赛德斯-奔驰牌 | P417: 45078
A418: 1234 | B418: 20230711FQ3600006301007 | C418: 2023053080007336 | D418: 欧阳建鑫 | E418: 欧阳建鑫 | F418: 汽车分期 | G418: 赣D00P32 | H418: 360019457619 | I418: 25 | J418: 45079 | K418: 5 | L418: 严利 | M418: 20210843420 | N418: 45079 | O418: 梅赛德斯-奔驰牌 | P418: 45079
A419: 1235 | B419: 20230719FQ3600006301001 | C419: 2023051480000417 | D419: 宋晓丽 | E419: 宋晓丽 | F419: 汽车分期 | G419: 赣D58E61 | H419: 360019430012 | I419: 25 | J419: 45070 | K419: 5 | L419: 李俊 | M419: 20200856460 | N419: 45062 | O419: 奥迪牌 | P419: 45070
...

Sheet 船舶
A1: 序号 | B1: 封包号 | C1: 业务合同编号 | D1: 借款人 | E1: 抵押人 | F1: 贷种 | G1: 船名 | H1: 船舶识别号 | I1: 抵押权登记号码 | J1: 抵押金额（万元） | K1: 抵押日期 | L1: 客户经理 | M1: 江西省吉安市地方海事局
A2: 1 | B2: 24012316043600006304001 | C2: 36010304224011341999 | D2: 龚冲冲 | E2: 江西赣鸿航运有限公司 | F2: 极速贷抵押额度 | G2: 赣鸿99 | H2: CN20079391186 | I2: DY3502240002 | J2: 50 | K2: 45314 | L2: 邓卫民

Sheet 汽车分期
A1: 客户姓名 | B1: 放款日期 | C1: 联系电话 | D1: 分享卡号 | E1: 归属分支行 | F1: 车辆品牌 | G1: 车辆类型1 | H1: 合作方式2 | I1: 车辆权证编码 | J1: 上牌地 | K1: 车辆产权登记日期 | L1: 抵押登记日期 | M1: 抵押权证入库日期 | N1: 抵押权证出库日期 | O1: 业务合同编号 | P1: 机动车登记编号 | Q1: 机动车登记证书编号 | R1: 抵押金额（万元） | S1: 借款期限 | T1: 客户经理 | U1: 备注 | V1: 押品编号
A2: 曾卫明 | B2: 44665 | C2: 13879636025 | D2: 6228110084348796 | E2: 吉安市青原大道支行 | F2: 凯迪拉克 | G2: 一手自用车 | H2: 直客式 | I2: cd000000000000000000824 | J2: 吉安市 | K2: 44673 | L2: 44673 | M2: 44680 | O2: 2022041280002431 | P2: 赣D676A8 | Q2: 360016785898 | R2: 16 | S2: 5 | T2: 王婷 | U2: 240700 | V2: YP360000632302230232
A3: 范芳云 | B3: 44678 | C3: 13367964455 | D3: 6228110084364314 | E3: 吉安市分行 | F3: 梅赛德斯-奔驰牌 | G3: 一手自用车 | H3: 直客式 | I3: cd000000000000000000825 | J3: 吉安市 | K3: 44680 | L3: 44680 | M3: 44691 | O3: 2022042680001466 | P3: 赣DQ9655 | Q3: 360018864876 | R3: 10 | S3: 3 | T3: 郭玲风 | V3: YP360000632302230231
A4: 刘新美 | B4: 44678 | C4: 19169726378 | D4: 6228110084364256 | E4: 吉安市分行 | F4: 梅赛德斯-奔驰牌 | G4: 一手自用车 | H4: 直客式 | I4: cd000000000000000000826 | J4: 吉安市 | K4: 44679 | L4: 44679 | M4: 44691 | O4: 2022042580001203 | P4: 赣DFD802 | Q4: 360018864890 | R4: 25 | S4: 5 | T4: 郭玲风 | V4: YP360000632302230230
A5: 欧阳军军 | B5: 44678 | C5: 13576888887 | D5: 6228110084364330 | E5: 吉安市分行 | F5: 梅赛德斯-奔驰牌 | G5: 一手自用车 | H5: 直客式 | I5: cd000000000000000000827 | J5: 吉安市 | K5: 44679 | L5: 44679 | M5: 44691 | O5: 2022042580003264 | P5: 赣D22U51 | Q5: 360018864883 | R5: 33 | S5: 5 | T5: 郭玲风 | V5: YP360000632302230229
A6: 尹奕花 | B6: 44679 | C6: 15779619088 | D6: 6228110084367051 | E6: 吉安市分行 | F6: 梅赛德斯-奔驰牌 | G6: 一手自用车 | H6: 直客式 | I6: cd000000000000000000828 | J6: 吉安市 | K6: 44680 | L6: 44680 | M6: 44691 | O6: 2022042580001570 | P6: 赣DGB711 | Q6: 360018864873 | R6: 20 | S6: 5 | T6: 郭玲风 | V6: YP360000632302230228
A7: 颜运林 | B7: 44690 | C7: 15521824043 | D7: 6228110084375484 | E7: 吉安市青原大道支行 | F7: 凯迪拉克 | G7: 一手自用车 | H7: 直客式 | I7: cd000000000000000000829 | J7: 吉安市 | K7: 44690 | L7: 44680 | M7: 44697 | O7: 2022050780001519 | P7: 赣DHT313 | Q7: 360018863228 | R7: 14.9 | S7: 5 | T7: 谢文青 | V7: YP360000632302230227
A8: 赖章红 | B8: 44686 | C8: 13979696853 | D8: 6228110084366780 | E8: 吉安市分行 | F8: 凯迪拉克 | G8: 一手自用车 | H8: 直客式 | I8: cd000000000000000000830 | J8: 吉安市 | K8: 44692 | L8: 44692 | M8: 44697 | O8: 2022042980003295 | P8: 赣DAG326 | Q8: 360016781899 | R8: 22 | S8: 5 | T8: 郭玲风 | V8: YP360000632302230226
A9: 项海珍 | B9: 44693 | C9: 15079668829 | D9: 6228110084380674 | E9: 吉安市分行 | F9: 梅赛德斯-奔驰牌 | G9: 一手自用车 | H9: 直客式 | I9: cd000000000000000000831 | J9: 吉安市 | K9: 44694 | L9: 44694 | M9: 44697 | O9: 2022051080001878 | P9: 赣DIQ388 | Q9: 360018864732 | R9: 24 | S9: 3 | T9: 郭玲风 | V9: YP360000632302230225
A10: 胡阳斌 | B10: 44700 | C10: 18160763149 | D10: 6228110084388800 | E10: 吉安市青原大道支行 | F10: 凯迪拉克 | G10: 一手自用车 | H10: 直客式 | I10: cd000000000000000000832 | J10: 吉安市 | K10: 44699 | L10: 44699 | M10: 44706 | N10: 44775 | O10: 2022051580001032 | P10: 赣DHQ283 | Q10: 360018863277 | R10: 19 | S10: 5 | T10: 谢文青 | V10: YP360000632302230224
A11: 杨敬云 | B11: 44705 | C11: 13397066777 | D11: 6228110084400647 | E11: 吉安市分行 | F11: 梅赛德斯-奔驰牌 | G11: 一手自用车 | H11: 直客式 | I11: cd000000000000000000833 | J11: 吉安市 | K11: 44706 | L11: 44706 | M11: 44708 | O11: 2022051880002193 | P11: 赣DBH607 | Q11: 360018842141 | R11: 47 | S11: 5 | T11: 郭玲风 | V11: YP360000632302230223
A12: 罗晓武 | B12: 44708 | C12: 18507967797 | D12: 6228110084414044 | E12: 吉安市分行 | F12: 梅赛德斯-奔驰牌 | G12: 一手自用车 | H12: 直客式 | I12: cd000000000000000000834 | J12: 吉安市 | K12: 44712 | L12: 44712 | M12: 44714 | O12: 2022052480002606 | P12: 赣DF5096 | Q12: 360018057395 | R12: 28 | S12: 5 | T12: 郭玲风 | V12: YP360000632302230222
A13: 曹江湖 | B13: 44713 | C13: 13237965999 | D13: 6228110084418078 | E13: 吉安市分行 | F13: 梅赛德斯-奔驰牌 | G13: 一手自用车 | H13: 直客式 | I13: cd000000000000000000835 | J13: 吉安市 | K13: 44714 | L13: 44714 | M13: 44722 | O13: 2022052680003454 | P13: 赣DFQ557 | Q13: 360018842159 | R13: 70 | S13: 5 | T13: 梅洁 | V13: YP360000632302230221
A14: 刘金秀 | B14: 44718 | C14: 15107910552 | D14: 6228110084421908 | E14: 吉安市分行 | F14: 梅赛德斯-奔驰牌 | G14: 一手自用车 | H14: 直客式 | I14: cd000000000000000000836 | J14: 吉安市 | K14: 44719 | L14: 44719 | M14: 44722 | O14: 2022060180002955 | P14: 赣DCG225 | Q14: 360018057160 | R14: 20 | S14: 4 | T14: 梅洁 | V14: YP360000632302230220
A15: 夏候耀鹏 | B15: 44720 | C15: 13033297463 | D15: 6228110084434620 | E15: 吉安市青原大道支行 | F15: 凯迪拉克 | G15: 一手自用车 | H15: 直客式 | I15: cd000000000000000000837 | J15: 吉安市 | K15: 44720 | L15: 44720 | M15: 44729 | O15: 2022060780002506 | P15: 赣D7IY77 | Q15: 360018858671 | R15: 10 | S15: 3 | T15: 谢文青 | V15: YP360000632302230217
A16: 张连文 | B16: 44712 | C16: 18321635592 | D16: 6228110084422195 | E16: 吉安市青原大道支行 | F16: 凯迪拉克 | G16: 一手自用车 | H16: 直客式 | I16: cd000000000000000000838 | J16: 吉安市 | K16: 44713 | L16: 44713 | M16: 44729 | O16: 2022052780004503 | P16: 赣DDA652 | Q16: 360018858782 | R16: 10 | S16: 5 | T16: 王婷 | V16: YP360000632302230209
A17: 杨玲 | B17: 44719 | C17: 15970232023 | D17: 6228110084407311 | E17: 吉安市分行 | F17: 梅赛德斯-奔驰牌 | G17: 一手自用车 | H17: 直客式 | I17: cd000000000000000000839 | J17: 吉安市 | K17: 44719 | L17: 44719 | M17: 44729 | O17: 2022052380003438 | P17: 赣DFY367 | Q17: 360018057423 | R17: 22.5 | S17: 5 | T17: 郭玲风 | V17: YP360000632302230219
A18: 张飘兵 | B18: 44722 | C18: 15907960601 | D18: 6228110084441385 | E18: 吉安市分行 | F18: 梅赛德斯-奔驰牌 | G18: 一手自用车 | H18: 直客式 | I18: cd000000000000000000840 | J18: 吉安市 | K18: 44725 | L18: 44725 | M18: 44729 | O18: 2022060480000553 | P18: 赣DM1360 | Q18: 360018859242 | R18: 50 | S18: 4 | T18: 梅洁 | V18: YP360000632302230218
A19: 曾钦湖 | B19: 44722 | C19: 19907993218 | D19: 6228110084447200 | E19: 吉安市城北支行 | F19: 凯迪拉克 | G19: 一手自用车 | H19: 直客式 | I19: cd000000000000000000841 | J19: 萍乡市 | K19: 44726 | L19: 44726 | M19: 44739 | O19: 2022060980005184 | P19: 赣JE0307 | Q19: 360017035866 | R19: 15 | S19: 3 | T19: 周颖 | V19: YP360000632302230215
A20: 刘云甫 | B20: 44722 | C20: 13979628258 | D20: 6228110084441617 | E20: 吉安市分行 | F20: 梅赛德斯-奔驰牌 | G20: 一手自用车 | H20: 直客式 | I20: cd000000000000000000842 | J20: 吉安市 | K20: 44727 | L20: 44727 | M20: 44739 | O20: 2022060780002698 | P20: 赣D16Z89 | Q20: 360018057308 | R20: 30 | S20: 5 | T20: 梅洁 | V20: YP360000632302230216
A21: 段德泓 | B21: 44726 | C21: 18870659464 | D21: 6228110084449925 | E21: 吉安市城北支行 | F21: 奥迪牌 | G21: 一手自用车 | H21: 直客式 | I21: cd000000000000000000843 | J21: 吉安市 | K21: 44727 | L21: 44727 | M21: 44739 | O21: 2022061380002260 | P21: 赣D01S70 | Q21: 360018072842 | R21: 15 | S21: 3 | T21: 徐求芸 | V21: YP360000632302230213
A22: 刘益平 | B22: 44726 | C22: 13929052766 | D22: 6228110084444587 | E22: 吉安市城北支行 | F22: 奥迪牌 | G22: 一手自用车 | H22: 直客式 | I22: cd000000000000000000844 | J22: 吉安市 | K22: 44727 | L22: 44727 | M22: 44739 | O22: 2022061080003441 | P22: 赣DFY922 | Q22: 360018072833 | R22: 14.98 | S22: 3 | T22: 徐求芸 | V22: YP360000632302230214
A23: 戴平 | B23: 44726 | C23: 13879631787 | D23: 6228110084454404 | E23: 吉安市青原大道支行 | F23: 凯迪拉克 | G23: 一手自用车 | H23: 直客式 | I23: cd000000000000000000845 | J23: 吉安市 | K23: 44727 | L23: 44727 | M23: 44739 | O23: 2022061380001757 | P23: 赣D96V15 | Q23: 360018858504 | R23: 10 | S23: 5 | T23: 谢文青 | V23: YP360000632302230212
A24: 刘舟 | B24: 44727 | C24: 15170206904 | D24: 6228110084450857 | E24: 吉安市青原大道支行 | F24: 凯迪拉克 | G24: 一手自用车 | H24: 直客式 | I24: cd000000000000000000846 | J24: 吉安市 | K24: 44727 | L24: 44727 | M24: 44739 | O24: 2022061280000375 | P24: 赣DFM638 | Q24: 360018858886 | R24: 15 | S24: 5 | T24: 谢文青 | V24: YP360000632302230211
A25: 周子燕 | B25: 44720 | C25: 13979641188 | D25: 6228110084434760 | E25: 吉安市青原大道支行 | F25: 沃尔沃 | G25: 一手自用车 | H25: 直客式 | I25: cd000000000000000000847 | J25: 吉安市 | K25: 44727 | L25: 44727 | M25: 44739 | O25: 2022060780003220 | P25: 赣D3551W | Q25: 360016712168 | R25: 17 | S25: 3 | T25: 王婷 | V25: YP360000632302230210
A26: 姚亮 | B26: 44732 | C26: 18107061010 | D26: 6228110084469204 | E26: 吉安市青原大道支行 | F26: 丰田牌 | G26: 一手自用车 | H26: 直客式 | I26: cd000000000000000000848 | J26: 吉安市 | K26: 44732 | L26: 44732 | M26: 44739 | O26: 2022061780003464 | P26: 赣D5207M | Q26: 360018057440 | R26: 15 | S26: 3 | T26: 谢文青 | V26: YP360000632302230207
A27: 冯秋根 | B27: 44727 | C27: 13879654628 | D27: 6228110084459015 | E27: 吉安市青原大道支行 | F27: 凯迪拉克 | G27: 一手自用车 | H27: 直客式 | I27: cd000000000000000000849 | J27: 吉安市 | K27: 44728 | L27: 44728 | M27: 44739 | O27: 2022061380001705 | P27: 赣DE1888 | Q27: 360018858878 | R27: 27 | S27: 5 | T27: 谢文青 | V27: YP360000632302230206
... A51: 肖少敏 | B51: 44727 | C51: 13907961276 | D51: 6228110084455492 | E51: 吉安市城北支行 | F51: 奥迪牌 | G51: 一手自用车 | H51: 直客式 | I51: cd000000000000000000873 | J51: 吉安市 | K51: 44736 | L51: 44736 | M51: 44750 | O51: 2022061480001852 | P51: 赣D1Q888 | Q51: 360018072922 | R51: 15 | S51: 3 | T51: 周颖 | V51: YP360000632302230187
A52: 黄丽萍 | B52: 44746 | D52: 622811******5022 | E52: 吉安市分行 | F52: 梅赛德斯-奔驰牌 | G52: 一手自用车 | H52: 直客式 | I52: cd000000000000000000874 | J52: 吉安市 | K52: 44746 | L52: 44746 | M52: 44750 | O52: 2022062980002904 | P52: 赣DGF877 | Q52: 360018057296 | R52: 35.8 | S52: 5 | T52: 梅洁 | V52: YP360000632302230183
A53: 罗亮 | B53: 44742 | C53: 15179629668 | D53: 6228110084503481 | E53: 吉安市分行 | F53: 梅赛德斯-奔驰牌 | G53: 一手自用车 | H53: 直客式 | I53: cd000000000000000000875 | J53: 吉安市 | K53: 44746 | L53: 44746 | M53: 44750 | O53: 2022062880003946 | P53: 赣DL8800 | Q53: 360018057058 | R53: 35 | S53: 5 | T53: 梅洁 | V53: YP360000632302230182
A54: 涂林荣 | B54: 44742 | C54: 13970672798 | D54: 6228110084501899 | E54: 吉安市分行 | F54: 梅赛德斯-奔驰牌 | G54: 一手自用车 | H54: 直客式 | I54: cd000000000000000000876 | J54: 吉安市 | K54: 44746 | L54: 44746 | M54: 44750 | O54: 2022062980001609 | P54: 赣DDV772 | Q54: 360018057064 | R54: 24.58 | S54: 5 | T54: 梅洁 | V54: YP360000632207080001
A55: 肖辉 | B55: 44741 | C55: 13600189334 | D55: 6228110084505163 | E55: 吉安市青原大道支行 | F55: 凯迪拉克 | G55: 一手自用车 | H55: 直客式 | I55: cd000000000000000000877 | J55: 吉安市 | K55: 44741 | L55: 44741 | M55: 44754 | O55: 2022062980000539 | P55: 赣DEC011 | Q55: 360018072394 | R55: 15 | S55: 5 | T55: 谢文青 | V55: YP360000632302230181
A56: 颜轶群 | B56: 44740 | C56: 18779619192 | D56: 6228110084499300 | E56: 吉安市青原大道支行 | F56: 领克 | G56: 一手自用车 | H56: 直客式 | I56: cd000000000000000000878 | J56: 吉安市 | K56: 44741 | L56: 44741 | M56: 44754 | O56: 2022062880001586 | P56: 赣DNG965 | Q56: 360018873720 | R56: 15 | S56: 5 | T56: 谢文青 | V56: YP360000632302230180
A57: 杨舟 | B57: 44742 | C57: 15949689119 | D57: 6228110084471572 | E57: 吉安市青原大道支行 | F57: 凯迪拉克 | G57: 一手自用车 | H57: 直客式 | I57: cd000000000000000000879 | J57: 吉安市 | K57: 44746 | L57: 44746 | M57: 44754 | O57: 2022062080002875 | P57: 赣DHX298 | Q57: 360018866266 | R57: 15 | S57: 5 | T57: 谢文青 | V57: YP360000632302230179
A58: 刘金明 | B58: 44746 | D58: 622811******8435 | E58: 吉安市青原大道支行 | F58: 凯迪拉克 | G58: 一手自用车 | H58: 直客式 | I58: cd000000000000000000880 | J58: 吉安市 | K58: 44746 | L58: 44746 | M58: 44754 | O58: 2022062780001742 | P58: 赣DHP001 | Q58: 360018072464 | R58: 20 | S58: 5 | T58: 谢文青 | V58: YP360000632302230178
A59: 肖俊 | B59: 44741 | D59: 622811******5163 | E59: 吉安市青原大道支行 | F59: 凯迪拉克 | G59: 一手自用车 | H59: 直客式 | I59: cd000000000000000000881 | J59: 吉安市 | K59: 44742 | L59: 44742 | M59: 44754 | O59: 2022062980000539 | P59: 赣DEH239 | Q59: 360018835997 | R59: 15 | S59: 5 | T59: 谢文青 | V59: YP360000632302230181
A60: 易莉 | B60: 44741 | C60: 13319343334 | D60: 6228110084503200 | E60: 吉安市青原大道支行 | F60: 凯迪拉克 | G60: 一手自用车 | H60: 直客式 | I60: cd000000000000000000882 | J60: 宜春市 | K60: 44748 | L60: 44748 | M60: 44757 | O60: 2022062880002023 | P60: 赣CPA167 | Q60: 360014956976 | R60: 15 | S60: 5 | T60: 谢文青 | V60: YP360000632302230164
A61: 黄文豪 | B61: 44753 | D61: 622811******8893 | E61: 吉安市分行 | F61: 梅赛德斯-奔驰牌 | G61: 一手自用车 | H61: 直客式 | I61: cd000000000000000000883 | J61: 吉安市 | K61: 44753 | L61: 44753 | M61: 44757 | O61: 2022070780002566 | P61: 赣D9852N | Q61: 360018057328 | R61: 10 | S61: 3 | T61: 梅洁 | V61: YP360000632302230175
A62: 刘富根 | B62: 44746 | D62: 622811******7494 | E62: 吉安市分行 | F62: 梅赛德斯-奔驰牌 | G62: 一手自用车 | H62: 直客式 | I62: cd000000000000000000884 | J62: 吉安市 | K62: 44749 | L62: 44749 | M62: 44757 | O62: 2022062880002501 | P62: 赣DFY360 | Q62: 360018057218 | R62: 12 | S62: 3 | T62: 梅洁 | V62: YP360000632302230174
A63: 梁文鸿 | B63: 44748 | D63: 622811******9305 | E63: 吉安市青原大道支行 | F63: 凯迪拉克 | G63: 一手自用车 | H63: 直客式 | I63: cd000000000000000000885 | J63: 吉安市 | K63: 44753 | L63: 44753 | M63: 44757 | O63: 2022070580001705 | P63: 赣D84826 | Q63: 360018072307 | R63: 10 | S63: 3 | T63: 王婷 | V63: YP360000632302230172
A64: 刘佳祺 | B64: 44748 | D64: 622811******6640 | E64: 吉安市青原大道支行 | F64: 凯迪拉克 | G64: 一手自用车 | H64: 直客式 | I64: cd000000000000000000886 | J64: 吉安市 | K64: 44749 | L64: 44749 | M64: 44757 | O64: 2022070580001376 | P64: 赣DFS212 | Q64: 360018072139 | R64: 15 | S64: 5 | T64: 王婷 | V64: YP360000632302230173
A65: 朱晓梅 | B65: 44741 | C65: 13340169876 | D65: 6228110084495506 | E65: 吉安市井冈山大道支行 | F65: 宝马牌 | G65: 一手自用车 | H65: 直客式 | I65: cd000000000000000000887 | J65: 萍乡市 | K65: 44748 | L65: 44748 | M65: 44757 | O65: 2022062680001006 | P65: 赣JJ7063 | Q65: 360017008902 | R65: 22.6 | S65: 5 | T65: 梁洁 | V65: YP360000632302230162
A66: 朱燕飞 | B66: 44753 | D66: 622811******3117 | E66: 吉安市分行 | F66: 梅赛德斯-奔驰牌 | G66: 一手自用车 | H66: 直客式 | I66: cd000000000000000000888 | J66: 吉安市 | K66: 44755 | L66: 44755 | M66: 44757 | O66: 2022070680000656 | P66: 赣DEJ753 | Q66: 360018057496 | R66: 15 | S66: 3 | T66: 梅洁 | V66: YP360000632302230163
A67: 兰舒亭 | B67: 44753 | D67: 622811******8041 | E67: 吉安市城北支行 | F67: 奥迪牌 | G67: 一手自用车 | H67: 直客式 | I67: cd000000000000000000889 | J67: 吉安市 | K67: 44753 | L67: 44753 | M67: 44761 | O67: 2022070780002126 | P67: 赣D8880N | Q67: 360018835826 | R67: 10 | S67: 3 | T67: 胡涛 | V67: YP360000632302230170
A68: 曾令池 | B68: 44746 | D68: 622811******8522 | E68: 吉安市城北支行 | F68: 奥迪牌 | G68: 一手自用车 | H68: 直客式 | I68: cd000000000000000000890 | J68: 吉安市 | K68: 44746 | L68: 44746 | M68: 44761 | O68: 2022063080002580 | P68: 赣D7A940 | Q68: 360018835965 | R68: 10 | S68: 3 | T68: 郭元 | V68: YP360000632302230171
A69: 肖华 | B69: 44753 | D69: 622811******4610 | E69: 吉安市城北支行 | F69: 奥迪牌 | G69: 一手自用车 | H69: 直客式 | I69: cd000000000000000000891 | J69: 吉安市 | K69: 44754 | L69: 44754 | M69: 44761 | O69: 2022070880002414 | P69: 赣D9957Z | Q69: 360018835813 | R69: 12 | S69: 5 | T69: 胡涛 | V69: YP360000632302230169
A70: 嬴时贵 | B70: 44748 | D70: 622811******5510 | E70: 吉安市青原大道支行 | F70: 凯迪拉克 | G70: 一手自用车 | H70: 直客式 | I70: cd000000000000000000892 | J70: 吉安市 | K70: 44748 | L70: 44748 | M70: 44761 | O70: 2022062980003881 | P70: 赣DHU359 | Q70: 360018072376 | R70: 15 | S70: 5 | T70: 谢文青 | V70: YP360000632302230168
A71: 熊艳霞 | B71: 44753 | D71: 622811******4156 | E71: 吉安市青原大道支行 | F71: 丰田牌 | G71: 一手自用车 | H71: 直客式 | I71: cd000000000000000000893 | J71: 吉安市 | K71: 44753 | L71: 44753 | M71: 44761 | O71: 2022070680001200 | P71: 赣DHV152 | Q71: 360018057335 | R71: 14.4 | S71: 3 | T71: 谢文青 | V71: YP360000632302230167
A72: 黄志群 | B72: 44751 | D72: 622811******4263 | E72: 吉安市青原大道支行 | F72: 凯迪拉克 | G72: 一手自用车 | H72: 直客式 | I72: cd000000000000000000894 | J72: 吉安市 | K72: 44754 | L72: 44754 | M72: 44761 | O72: 2022070780000968 | P72: 赣D5H389 | Q72: 360018072408 | R72: 10 | S72: 3 | T72: 王婷 | V72: YP360000632302230166
A73: 李恪庆 | B73: 44753 | D73: 622811******4628 | E73: 吉安市青原大道支行 | F73: 凯迪拉克 | G73: 一手自用车 | H73: 直客式 | I73: cd000000000000000000895 | J73: 吉安市 | K73: 44754 | L73: 44754 | M73: 44768 | O73: 2022070880002805 | P73: 赣DGW151 | Q73: 360018072409 | R73: 15 | S73: 5 | T73: 王婷 | V73: YP360000632302230165
A74: 张雪 | B74: 44761 | D74: 622811******2414 | E74: 吉安市井冈山大道支行 | F74: 宝马牌 | G74: 一手自用车 | H74: 直客式 | I74: cd000000000000000000896 | J74: 吉安市 | K74: 44763 | L74: 44763 | M74: 44768 | O74: 2022071380003471 | P74: 赣DFQ029 | Q74: 360016758908 | R74: 25 | S74: 5 | T74: 曾宁 | V74: YP360000632302230161
A75: 李期宁 | B75: 44741 | C75: 15107066131 | D75: 6228110084492925 | E75: 吉安市青原大道支行 | F75: 凯迪拉克 | G75: 一手自用车 | H75: 直客式 | I75: cd000000000000000000897 | J75: 吉安市 | K75: 44749 | L75: 44749 | M75: 44768 | O75: 2022062780001457 | P75: 赣DK2522 | Q75: 360018056177 | R75: 10 | S75: 3 | T75: 谢文青 | V75: YP360000632302230158
A76: 刘春辉 | B76: 44754 | D76: 622811******8230 | E76: 吉安市青原大道支行 | F76: 凯迪拉克 | G76: 一手自用车 | H76: 直客式 | I76: cd000000000000000000898 | J76: 吉安市 | K76: 44755 | L76: 44755 | M76: 44768 | O76: 2022071180001921 | P76: 赣D10N58 | Q76: 360018072130 | R76: 15 | S76: 5 | T76: 谢文青 | V76: YP360000632302230157
A77: 蒋玉芳 | B77: 44740 | C77: 18007962826 | D77: 6228110084495373 | E77: 吉安市城北支行 | F77: 奥迪牌 | G77: 一手自用车 | H77: 直客式 | I77: cd000000000000000000899 | J77: 吉安市 | K77: 44741 | L77: 44741 | M77: 44768 | O77: 2022062580001480 | P77: 赣D9916Z | Q77: 360018835922 | R77: 15 | S77: 5 | T77: 胡涛 | V77: YP360000632302230160
A78: 谢鸿 | B78: 44741 | C78: 18679669552 | D78: 6228110084498476 | E78: 吉安市城北支行 | F78: 奥迪牌 | G78: 一手自用车 | H78: 直客式 | I78: cd000000000000000000900 | J78: 吉安市 | K78: 44742 | L78: 44742 | M78: 44768 | O78: 2022062880002634 | P78: 赣D8970M | Q78: 360018835917 | R78: 12 | S78: 5 | T78: 胡涛 | V78: YP360000632302230159
A79: 包丽红 | B79: 44761 | D79: 622811******1720 | E79: 吉安市分行 | F79: 梅赛德斯-奔驰牌 | G79: 一手自用车 | H79: 直客式 | I79: cd000000000000000000901 | J79: 吉安市 | K79: 44762 | L79: 44762 | M79: 44770 | O79: 2022071780000447 | P79: 赣D828F2 | Q79: 360018057053 | R79: 27.6 | S79: 3 | T79: 黄艳 | V79: YP360000632302230149
A80: 陈建桑 | B80: 44755 | D80: 622811******9154 | E80: 吉安市分行 | F80: 梅赛德斯-奔驰牌 | G80: 一手自用车 | H80: 直客式 | I80: cd000000000000000000902 | J80: 吉安市 | K80: 44757 | L80: 44757 | M80: 44770 | O80: 2022071280002145 | P80: 赣D178B6 | Q80: 360018057482 | R80: 15 | S80: 3 | T80: 梅洁 | V80: YP360000632302230148
A81: 李娜 | B81: 44756 | D81: 622811******9477 | E81: 吉安市分行 | F81: 梅赛德斯-奔驰牌 | G81: 一手自用车 | H81: 直客式 | I81: cd000000000000000000903 | J81: 吉安市 | K81: 44763 | L81: 44763 | M81: 44770 | O81: 2022071280002449 | P81: 赣DCL799 | Q81: 360018057107 | R81: 32.64 | S81: 5 | T81: 梅洁 | V81: YP360000632302230155
A82: 刘昌飞 | B82: 44760 | D82: 622811******2323 | E82: 吉安市分行 | F82: 梅赛德斯-奔驰牌 | G82: 一手自用车 | H82: 直客式 | I82: cd000000000000000000904 | J82: 吉安市 | K82: 44761 | L82: 44761 | M82: 44770 | N82: 45001 | O82: 2022071480001831 | P82: 赣DDY808 | Q82: 360018057265 | R82: 28 | S82: 5 | T82: 梅洁 | V82: YP360000632302230156
A83: 毛玮 | B83: 44753 | D83: 622811******2830 | E83: 吉安市分行 | F83: 梅赛德斯-奔驰牌 | G83: 一手自用车 | H83: 直客式 | I83: cd000000000000000000905 | J83: 吉安市 | K83: 44757 | L83: 44757 | M83: 44770 | O83: 2022062980003172 | P83: 赣D02V66 | Q83: 360018057479 | R83: 20 | S83: 5 | T83: 梅洁 | V83: YP360000632302230150
A84: 帅海军 | B84: 44761 | D84: 622811******4809 | E84: 吉安市分行 | F84: 梅赛德斯-奔驰牌 | G84: 一手自用车 | H84: 直客式 | I84: cd000000000000000000906 | J84: 吉安市 | K84: 44763 | L84: 44763 | M84: 44770 | O84: 2022070980001129 | P84: 赣D8J542 | Q84: 360016758924 | R84: 49.9 | S84: 5 | T84: 梅洁 | V84: YP360000632302230152
A85: 吴志军 | B85: 44763 | D85: 622811******2057 | E85: 吉安市分行 | F85: 梅赛德斯-奔驰牌 | G85: 一手自用车 | H85: 直客式 | I85: cd000000000000000000907 | J85: 吉安市 | K85: 44764 | L85: 44764 | M85: 44770 | O85: 2022072080001343 | P85: 赣DEL769 | Q85: 360018057104 | R85: 27.8 | S85: 5 | T85: 黄艳 | V85: YP360000632302230151
A86: 高海松 | B86: 44757 | D86: 622811******0947 | E86: 吉安市青原大道支行 | F86: 凯迪拉克 | G86: 一手自用车 | H86: 直客式 | I86: cd000000000000000000908 | J86: 吉安市 | K86: 44757 | L86: 44757 | M86: 44770 | O86: 2022071280003051 | P86: 赣DBG752 | Q86: 360018072045 | R86: 12 | S86: 5 | T86: 王婷 | V86: YP360000632302230153
A87: 钟庆 | B87: 44763 | D87: 622811******6851 | E87: 吉安市城北支行 | F87: 奥迪牌 | G87: 一手自用车 | H87: 直客式 | I87: cd000000000000000000909 | J87: 吉安市 | K87: 44764 | L87: 44764 | M87: 44770 | O87: 2022071880002374 | P87: 赣DGW566 | Q87: 360018835714 | R87: 15 | S87: 5 | T87: 胡涛 | V87: YP360000632302230154
A88: 罗小平 | B88: 44768 | D88: 622811******2105 | E88: 吉安市分行 | F88: 梅赛德斯-奔驰牌 | G88: 一手自用车 | H88: 直客式 | I88: cd000000000000000000910 | J88: 吉安市 | K88: 44769 | L88: 44769 | M88: 44774 | O88: 2022072480000125 | P88: 赣D3V886 | Q88: 360018816424 | R88: 35.6 | S88: 3 | T88: 黄艳 | V88: YP360000632302230147
A89: 彭小惠 | B89: 44764 | D89: 622811******3378 | E89: 吉安市分行 | F89: 梅赛德斯-奔驰牌 | G89: 一手自用车 | H89: 直客式 | I89: cd000000000000000000911 | J89: 吉安市 | K89: 44767 | L89: 44767 | M89: 44774 | O89: 2022072180001259 | P89: 赣D73U60 | Q89: 360018057471 | R89: 16 | S89: 3 | T89: 黄艳 | V89: YP360000632302230146
A90: 肖瑛 | B90: 44764 | D90: 622811******4673 | E90: 吉安市分行 | F90: 梅赛德斯-奔驰牌 | G90: 一手自用车 | H90: 直客式 | I90: cd000000000000000000912 | J90: 吉安市 | K90: 44764 | L90: 44764 | M90: 44774 | O90: 2022071980002214 | P90: 赣D4C666 | Q90: 360016758937 | R90: 58 | S90: 5 | T90: 黄艳 | V90: YP360000632302230145
A91: 陈清发 | B91: 44764 | D91: 622811******4491 | E91: 吉安市分行 | F91: 梅赛德斯-奔驰牌 | G91: 一手自用车 | H91: 直客式 | I91: cd000000000000000000913 | J91: 吉安市 | K91: 44769 | L91: 44769 | M91: 44774 | O91: 2022072180001755 | P91: 赣DBD307 | Q91: 360018057452 | R91: 30 | S91: 5 | T91: 黄艳 | V91: YP360000632302230142
A92: 夏荣明 | B92: 44764 | D92: 622811******3485 | E92: 吉安市分行 | F92: 梅赛德斯-奔驰牌 | G92: 一手自用车 | H92: 直客式 | I92: cd000000000000000000914 | J92: 吉安市 | K92: 44769 | L92: 44769 | M92: 44774 | O92: 2022072180001857 | P92: 赣DGU526 | Q92: 360018816054 | R92: 22.5 | S92: 5 | T92: 黄艳 | V92: YP360000632302230141
A93: 廖水龙 | B93: 44769 | D93: 622811******0661 | E93: 吉安市分行 | F93: 梅赛德斯-奔驰牌 | G93: 一手自用车 | H93: 直客式 | I93: cd000000000000000000915 | J93: 吉安市 | K93: 44770 | L93: 44770 | M93: 44774 | O93: 2022072680001953 | P93: 赣DL6000 | Q93: 360018849289 | R93: 30 | S93: 3 | T93: 梅洁 | V93: YP360000632302230139
A94: 钟传明 | B94: 44767 | D94: 622811******2552 | E94: 吉安市青原大道支行 | F94: 凯迪拉克 | G94: 一手自用车 | H94: 直客式 | I94: cd000000000000000000916 | J94: 新余市 | K94: 44769 | L94: 44769 | M94: 44774 | O94: 2022072180003136 | P94: 赣K87Q82 | Q94: 360017866396 | R94: 22.5 | S94: 5 | T94: 王婷 | V94: YP360000632302230138
... A134: 王静 | B134: 44830 | D134: 622811******6341 | E134: 吉安市分行 | F134: 梅赛德斯-奔驰牌 | G134: 一手自用车 | H134: 直客式 | I134: cd000000000000000000956 | J134: 吉安市 | K134: 44831 | L134: 44831 | M134: 44836 | O134: 2022080280000603 | P134: 赣D2363W | Q134: 360018816356 | R134: 20 | S134: 5 | T134: 黄艳 | V134: YP360000632302230103
A135: 王振 | B135: 44804 | D135: 622811******4506 | E135: 吉安市分行 | F135: 梅赛德斯-奔驰牌 | G135: 一手自用车 | H135: 直客式 | I135: cd000000000000000000957 | J135: 吉安市 | K135: 44805 | L135: 44805 | M135: 44836 | N135: 44866 | O135: 2022082280001690 | P135: 赣DBE685 | Q135: 360018816450 | R135: 25 | S135: 3 | T135: 黄艳 | U135: 未结清出库，客户更换车牌号码 | V135: YP360000632302230101
A136: 袁丽霞 | B136: 44797 | D136: 622811******4530 | E136: 吉安市分行 | F136: 梅赛德斯-奔驰牌 | G136: 一手自用车 | H136: 直客式 | I136: cd000000000000000000958 | J136: 吉安市 | K136: 44802 | L136: 44802 | M136: 44836 | O136: 2022082280002115 | P136: 赣D13Z01 | Q136: 360018816348 | R136: 25 | S136: 5 | T136: 黄艳 | V136: YP360000632302230108
A137: 刘波 | B137: 44830 | D137: 622811******8980 | E137: 吉安市分行 | F137: 梅赛德斯-奔驰牌 | G137: 一手自用车 | H137: 直客式 | I137: cd000000000000000000959 | J137: 吉安市 | K137: 44833 | L137: 44833 | M137: 44845 | O137: 2022083180001681 | P137: 赣D24888 | Q137: 360019439226 | R137: 46 | S137: 3 | T137: 梅洁 | V137: YP360000632302230099
A138: 廖传亮 | B138: 44842 | D138: 622811******9421 | E138: 吉安市分行 | F138: 梅赛德斯-奔驰牌 | G138: 一手自用车 | H138: 直客式 | I138: cd000000000000000000960 | J138: 吉安市 | K138: 44842 | L138: 44842 | M138: 44845 | O138: 2022082580002724 | P138: 赣D0544K | Q138: 360018816097 | R138: 30 | S138: 5 | T138: 梅洁 | V138: YP360000632302230098
A139: 黄美英 | B139: 44844 | D139: 622811******7236 | E139: 吉安市分行 | F139: 梅赛德斯-奔驰牌 | G139: 一手自用车 | H139: 直客式 | I139: cd000000000000000000961 | J139: 吉安市 | K139: 44844 | L139: 44844 | M139: 44845 | O139: 2022100380000961 | P139: 赣DV5566 | Q139: 360018816470 | R139: 16 | S139: 5 | T139: 黄艳 | V139: YP360000632302230097
A140: 王山英 | B140: 44842 | D140: 622811******1499 | E140: 吉安市分行 | F140: 凯迪拉克 | G140: 一手自用车 | H140: 直客式 | I140: cd000000000000000000962 | J140: 吉安市 | K140: 44842 | L140: 44842 | M140: 44845 | N140: 44980 | O140: 2022082880000924 | P140: 赣D33440 | Q140: 360018078439 | R140: 15 | S140: 3 | T140: 刘涛 | V140: YP360000632302230096
A141: 杨桂俊 | B141: 44844 | D141: 622811******1743 | E141: 吉安市分行 | F141: 梅赛德斯-奔驰牌 | G141: 一手自用车 | H141: 直客式 | I141: cd000000000000000000963 | J141: 吉安市 | K141: 44844 | L141: 44844 | M141: 44845 | O141: 2022092980003474 | P141: 赣DBV578 | Q141: 360018816473 | R141: 30 | S141: 5 | T141: 黄艳 | V141: YP360000632302230090
A142: 蔡小波 | B142: 44842 | D142: 622811******7185 | E142: 吉安市分行 | F142: 赛力斯牌 | G142: 一手自用车 | H142: 直客式 | I142: cd000000000000000000964 | J142: 吉安市 | K142: 44842 | L142: 44842 | M142: 44848 | O142: 2022082480001290 | P142: 赣DF17178 | Q142: 360018858258 | R142: 18 | S142: 4 | T142: 胡涛 | V142: YP360000632302230094
A143: 陈峰 | B143: 44842 | D143: 622811******8903 | E143: 吉安市分行 | F143: 奥迪牌 | G143: 一手自用车 | H143: 直客式 | I143: cd000000000000000000965 | J143: 吉安市 | K143: 44842 | L143: 44842 | M143: 44848 | O143: 2022082480001269 | P143: 赣D2988Y | Q143: 360018858257 | R143: 20 | S143: 5 | T143: 周颖 | V143: YP360000632302230092
A144: 周娟 | B144: 44842 | D144: 622811******3727 | E144: 吉安市分行 | F144: 奥迪牌 | G144: 一手自用车 | H144: 直客式 | I144: cd000000000000000000966 | J144: 吉安市 | K144: 44842 | L144: 44842 | M144: 44848 | O144: 2022083080001739 | P144: 赣D235C6 | Q144: 360018858254 | R144: 20 | S144: 3 | T144: 胡涛 | V144: YP360000632302230091
A145: 周军发 | B145: 44804 | D145: 622811******7197 | E145: 吉安市分行 | F145: 奥迪牌 | G145: 一手自用车 | H145: 直客式 | I145: cd000000000000000000967 | J145: 吉安市 | K145: 44805 | L145: 44843 | M145: 44848 | O145: 2022081480000810 | P145: 赣DHH165 | Q145: 360018858381 | R145: 20 | S145: 3 | T145: 胡涛 | V145: YP360000632302230093
A146: 翟荣 | B146: 44831 | D146: 622811******7958 | E146: 吉安市分行 | F146: 宝马牌 | G146: 一手自用车 | H146: 直客式 | I146: cd000000000000000000968 | J146: 吉安市 | K146: 44846 | L146: 44846 | M146: 44848 | O146: 2022083180002324 | P146: 赣D8168S | Q146: 360018837384 | R146: 22 | S146: 5 | T146: 梁洁 | V146: YP360000632302230089
A147: 李亚薇 | B147: 44844 | D147: 622811******0122 | E147: 吉安市分行 | F147: 梅赛德斯-奔驰牌 | G147: 一手自用车 | H147: 直客式 | I147: cd000000000000000000969 | J147: 吉安市 | K147: 44845 | L147: 44845 | M147: 44848 | O147: 2022100780000522 | P147: 赣DFP011 | Q147: 360018816479 | R147: 15.4 | S147: 3 | T147: 黄艳 | V147: YP360000632302230088
A148: 宋子卉 | B148: 44844 | D148: 622811******9620 | E148: 吉安市分行 | F148: 梅赛德斯-奔驰牌 | G148: 一手自用车 | H148: 直客式 | I148: cd000000000000000000970 | J148: 吉安市 | K148: 44846 | L148: 44846 | M148: 44848 | O148: 2022100580000588 | P148: 赣DGP526 | Q148: 360018816486 | R148: 14.7 | S148: 5 | T148: 黄艳 | V148: YP360000632302230087
A149: 肖慧玲 | B149: 44843 | D149: 622811******9298 | E149: 吉安市分行 | F149: 梅赛德斯-奔驰牌 | G149: 一手自用车 | H149: 直客式 | I149: cd000000000000000000971 | J149: 吉安市 | K149: 44845 | L149: 44845 | M149: 44848 | O149: 2022100780000805 | P149: 赣D05A83 | Q149: 360019439377 | R149: 30 | S149: 5 | T149: 黄艳 | V149: YP360000632302230080
A150: 欧阳燕虹 | B150: 44847 | D150: 622811******3058 | E150: 吉安市分行 | F150: 梅赛德斯-奔驰牌 | G150: 一手自用车 | H150: 直客式 | I150: cd000000000000000000972 | J150: 吉安市 | K150: 44848 | L150: 44848 | M150: 44860 | O150: 2022101080001139 | P150: 赣DEP373 | Q150: 360018097752 | R150: 20.9 | S150: 5 | T150: 黄艳 | V150: YP360000632302230081
A151: 王嘉敏 | B151: 44845 | D151: 622811******3117 | E151: 吉安市分行 | F151: 梅赛德斯-奔驰牌 | G151: 一手自用车 | H151: 直客式 | I151: cd000000000000000000973 | J151: 吉安市 | K151: 44848 | L151: 44848 | M151: 44860 | O151: 2022100980001074 | P151: 赣D8547DS | Q151: 360018816499 | R151: 20 | S151: 5 | T151: 黄艳 | V151: YP360000632302230083
A152: 王清和 | B152: 44847 | D152: 622811******8621 | E152: 吉安市分行 | F152: 梅赛德斯-奔驰牌 | G152: 一手自用车 | H152: 直客式 | I152: cd000000000000000000974 | J152: 吉安市 | K152: 44848 | L152: 44848 | M152: 44860 | O152: 2022100880000966 | P152: 赣DEB968 | Q152: 360018816497 | R152: 20 | S152: 5 | T152: 黄艳 | V152: YP360000632302230082
... A162: 罗小勇 | B162: 44867 | D162: 622811******2100 | E162: 吉安市分行 | F162: 梅赛德斯-奔驰牌 | G162: 一手自用车 | H162: 直客式 | I162: cd000000000000000000985 | J162: 吉安市 | K162: 44867 | L162: 44867 | M162: 44869 | O162: 2022103080000882 | P162: 赣D3E996 | Q162: 360018097854 | R162: 20 | S162: 5 | T162: 黄艳 | V162: YP360000632302230074
A163: 吴亮明 | B163: 44866 | D163: 622811******1889 | E163: 吉安市分行 | F163: 梅赛德斯-奔驰牌 | G163: 一手自用车 | H163: 直客式 | I163: cd000000000000000000986 | J163: 吉安市 | K163: 44867 | L163: 44867 | M163: 44869 | N163: 45013 | O163: 2022103080000434 | P163: 赣DGB808 | Q163: 360016764429 | R163: 18 | S163: 3 | T163: 梅洁 | V163: YP360000632302230076
A164: 谢玮 | B164: 44866 | D164: 622811******4080 | E164: 吉安市分行 | F164: 梅赛德斯-奔驰牌 | G164: 一手自用车 | H164: 直客式 | I164: cd000000000000000000987 | J164: 吉安市 | K164: 44868 | L164: 44868 | M164: 44869 | O164: 2022102880001529 | P164: 赣D2518Z | Q164: 360018097862 | R164: 20 | S164: 3 | T164: 黄艳 | V164: YP360000632302230073
A165: 杨坤 | B165: 44867 | D165: 622811******1871 | E165: 吉安市分行 | F165: 梅赛德斯-奔驰牌 | G165: 一手自用车 | H165: 直客式 | I165: cd000000000000000000988 | J165: 吉安市 | K165: 44868 | L165: 44868 | M165: 44869 | O165: 2022103080000365 | P165: 赣D8232Z | Q165: 360018097861 | R165: 15 | S165: 5 | T165: 梅洁 | V165: YP360000632302230075
A166: 蒋邦纲 | B166: 44867 | D166: 622811******4460 | E166: 吉安市分行 | F166: 梅赛德斯-奔驰牌 | G166: 一手自用车 | H166: 直客式 | I166: cd000000000000000000989 | J166: 吉安市 | K166: 44872 | L166: 44872 | M166: 44879 | O166: 2022103080000273 | P166: 赣DGB126 | Q166: 360018097570 | R166: 24.8 | S166: 5 | T166: 梅洁 | V166: YP360000632302230067
A167: 李艳 | B167: 44862 | D167: 622811******6781 | E167: 吉安市分行 | F167: 梅赛德斯-奔驰牌 | G167: 一手自用车 | H167: 直客式 | I167: cd000000000000000000990 | J167: 吉安市 | K167: 44872 | L167: 44872 | M167: 44879 | O167: 2022102580003553 | P167: 赣D68S30 | Q167: 360018097867 | R167: 30 | S167: 5 | T167: 黄艳 | V167: YP360000632302230068
A168: 喻小兰 | B168: 44869 | D168: 622811******7752 | E168: 吉安市分行 | F168: 梅赛德斯-奔驰牌 | G168: 一手自用车 | H168: 直客式 | I168: cd000000000000000000991 | J168: 吉安市 | K168: 44869 | L168: 44869 | M168: 44879 | O168: 2022110180001773 | P168: 赣DEJ638 | Q168: 360018097567 | R168: 17.5 | S168: 5 | T168: 黄艳 | V168: YP360000632302230069
A169: 朱芬芬 | B169: 44862 | D169: 622811******6765 | E169: 吉安市分行 | F169: 梅赛德斯-奔驰牌 | G169: 一手自用车 | H169: 直客式 | I169: cd000000000000000000992 | J169: 吉安市 | K169: 44868 | L169: 44868 | M169: 44879 | O169: 2022102580003006 | P169: 赣DGT822 | Q169: 360018097863 | R169: 23 | S169: 5 | T169: 黄艳 | V169: YP360000632302230070
A170: 黄波 | B170: 44756 | D170: 622811******9105 | E170: 吉安市分行 | F170: 凯迪拉克牌 | G170: 一手自用车 | H170: 直客式 | I170: cd000000000000000000993 | J170: 吉安市 | K170: 44781 | L170: 44875 | M170: 44879 | O170: 2022071280001411 | P170: 赣H9K730 | Q170: 360017516505 | R170: 15 | S170: 5 | T170: 谢文青 | V170: YP360000632302230062
A171: 戴素芬 | B171: 44875 | D171: 622811******5399 | E171: 吉安市分行 | F171: 梅赛德斯-奔驰牌 | G171: 一手自用车 | H171: 直客式 | I171: cd000000000000000000994 | J171: 吉安市 | K171: 44875 | L171: 44875 | M171: 44879 | O171: 2022110980000850 | P171: 赣D8157Y | Q171: 360018097890 | R171: 15 | S171: 3 | T171: 黄艳 | V171: YP360000632302230063
...

Sheet 汽车分期 (2)
A1: 业务合同编号 | B1: 客户姓名 | C1: 放款日期 | D1: 联系电话 | E1: 分享卡号 | F1: 归属分支行 | G1: 车辆品牌 | H1: 车辆类型1 | I1: 合作方式2 | J1: 车辆权证编码 | K1: 上牌地 | L1: 车辆产权登记日期 | M1: 抵押登记日期 | N1: 抵押权证入库日期 | O1: 抵押权证出库日期 | P1: 机动车登记编号 | Q1: 机动车登记证书编号 | R1: 抵押金额（万元） | S1: 借款期限 | T1: 客户经理 | U1: 备注 | V1: 押品编号
A2: 2022041280002431 | B2: 曾卫明 | C2: 44665 | D2: 13879636025 | E2: 6228110084348796 | F2: 吉安市青原大道支行 | G2: 凯迪拉克 | H2: 一手自用车 | I2: 直客式 | J2: cd000000000000000000824 | K2: 吉安市 | L2: 44673 | M2: 44673 | N2: 44680 | P2: 赣D676A8 | Q2: 360016785898 | R2: 16 | S2: 5 | T2: 王婷 | U2: 240700 | V2: YP360000632302230232
A3: 2022042680001466 | B3: 范芳云 | C3: 44678 | D3: 13367964455 | E3: 6228110084364314 | F3: 吉安市分行 | G3: 梅赛德斯-奔驰牌 | H3: 一手自用车 | I3: 直客式 | J3: cd000000000000000000825 | K3: 吉安市 | L3: 44680 | M3: 44680 | N3: 44691 | P3: 赣DQ9655 | Q3: 360018864876 | R3: 10 | S3: 3 | T3: 郭玲风 | V3: YP360000632302230231
A4: 2022042580001203 | B4: 刘新美 | C4: 44678 | D4: 19169726378 | E4: 6228110084364256 | F4: 吉安市分行 | G4: 梅赛德斯-奔驰牌 | H4: 一手自用车 | I4: 直客式 | J4: cd000000000000000000826 | K4: 吉安市 | L4: 44679 | M4: 44679 | N4: 44691 | P4: 赣DFD802 | Q4: 360018864890 | R4: 25 | S4: 5 | T4: 郭玲风 | V4: YP360000632302230230
A5: 2022042580003264 | B5: 欧阳军军 | C5: 44678 | D5: 13576888887 | E5: 6228110084364330 | F5: 吉安市分行 | G5: 梅赛德斯-奔驰牌 | H5: 一手自用车 | I5: 直客式 | J5: cd000000000000000000827 | K5: 吉安市 | L5: 44679 | M5: 44679 | N5: 44691 | P5: 赣D22U51 | Q5: 360018864883 | R5: 33 | S5: 5 | T5: 郭玲风 | V5: YP360000632302230229
A6: 2022042580001570 | B6: 尹奕花 | C6: 44679 | D6: 15779619088 | E6: 6228110084367051 | F6: 吉安市分行 | G6: 梅赛德斯-奔驰牌 | H6: 一手自用车 | I6: 直客式 | J6: cd000000000000000000828 | K6: 吉安市 | L6: 44680 | M6: 44680 | N6: 44691 | P6: 赣DGB711 | Q6: 360018864873 | R6: 20 | S6: 5 | T6: 郭玲风 | V6: YP360000632302230228
A7: 2022050780001519 | B7: 颜运林 | C7: 44690 | D7: 15521824043 | E7: 6228110084375484 | F7: 吉安市青原大道支行 | G7: 凯迪拉克 | H7: 一手自用车 | I7: 直客式 | J7: cd000000000000000000829 | K7: 吉安市 | L7: 44690 | M7: 44680 | N7: 44697 | P7: 赣DHT313 | Q7: 360018863228 | R7: 14.9 | S7: 5 | T7: 谢文青 | V7: YP360000632302230227
A8: 2022042980003295 | B8: 赖章红 | C8: 44686 | D8: 13979696853 | E8: 6228110084366780 | F8: 吉安市分行 | G8: 凯迪拉克 | H8: 一手自用车 | I8: 直客式 | J8: cd000000000000000000830 | K8: 吉安市 | L8: 44692 | M8: 44692 | N8: 44697 | P8: 赣DAG326 | Q8: 360016781899 | R8: 22 | S8: 5 | T8: 郭玲风 | V8: YP360000632302230226
A9: 2022051080001878 | B9: 项海珍 | C9: 44693 | D9: 15079668829 | E9: 6228110084380674 | F9: 吉安市分行 | G9: 梅赛德斯-奔驰牌 | H9: 一手自用车 | I9: 直客式 | J9: cd000000000000000000831 | K9: 吉安市 | L9: 44694 | M9: 44694 | N9: 44697 | P9: 赣DIQ388 | Q9: 360018864732 | R9: 24 | S9: 3 | T9: 郭玲风 | V9: YP360000632302230225
A10: 2022051580001032 | B10: 胡阳斌 | C10: 44700 | D10: 18160763149 | E10: 6228110084388800 | F10: 吉安市青原大道支行 | G10: 凯迪拉克 | H10: 一手自用车 | I10: 直客式 | J10: cd000000000000000000832 | K10: 吉安市 | L10: 44699 | M10: 44699 | N10: 44706 | O10: 44775 | P10: 赣DHQ283 | Q10: 360018863277 | R10: 19 | S10: 5 | T10: 谢文青 | V10: YP360000632302230224
A11: 2022051880002193 | B11: 杨敬云 | C11: 44705 | D11: 13397066777 | E11: 6228110084400647 | F11: 吉安市分行 | G11: 梅赛德斯-奔驰牌 | H11: 一手自用车 | I11: 直客式 | J11: cd000000000000000000833 | K11: 吉安市 | L11: 44706 | M11: 44706 | N11: 44708 | P11: 赣DBH607 | Q11: 360018842141 | R11: 47 | S11: 5 | T11: 郭玲风 | V11: YP360000632302230223
A12: 2022052480002606 | B12: 罗晓武 | C12: 44708 | D12: 18507967797 | E12: 6228110084414044 | F12: 吉安市分行 | G12: 梅赛德斯-奔驰牌 | H12: 一手自用车 | I12: 直客式 | J12: cd000000000000000000834 | K12: 吉安市 | L12: 44712 | M12: 44712 | N12: 44714 | P12: 赣DF5096 | Q12: 360018057395 | R12: 28 | S12: 5 | T12: 郭玲风 | V12: YP360000632302230222
A13: 2022052680003454 | B13: 曹江湖 | C13: 44713 | D13: 13237965999 | E13: 6228110084418078 | F13: 吉安市分行 | G13: 梅赛德斯-奔驰牌 | H13: 一手自用车 | I13: 直客式 | J13: cd000000000000000000835 | K13: 吉安市 | L13: 44714 | M13: 44714 | N13: 44722 | P13: 赣DFQ557 | Q13: 360018842159 | R13: 70 | S13: 5 | T13: 梅洁 | V13: YP360000632302230221
A14: 2022060180002955 | B14: 刘金秀 | C14: 44718 | D14: 15107910552 | E14: 6228110084421908 | F14: 吉安市分行 | G14: 梅赛德斯-奔驰牌 | H14: 一手自用车 | I14: 直客式 | J14: cd000000000000000000836 | K14: 吉安市 | L14: 44719 | M14: 44719 | N14: 44722 | P14: 赣DCG225 | Q14: 360018057160 | R14: 20 | S14: 4 | T14: 梅洁 | V14: YP360000632302230220
A15: 2022060780002506 | B15: 夏候耀鹏 | C15: 44720 | D15: 13033297463 | E15: 6228110084434620 | F15: 吉安市青原大道支行 | G15: 凯迪拉克 | H15: 一手自用车 | I15: 直客式 | J15: cd000000000000000000837 | K15: 吉安市 | L15: 44720 | M15: 44720 | N15: 44729 | P15: 赣D7IY77 | Q15: 360018858671 | R15: 10 | S15: 3 | T15: 谢文青 | V15: YP360000632302230217
A16: 2022052780004503 | B16: 张连文 | C16: 44712 | D16: 18321635592 | E16: 6228110084422195 | F16: 吉安市青原大道支行 | G16: 凯迪拉克 | H16: 一手自用车 | I16: 直客式 | J16: cd000000000000000000838 | K16: 吉安市 | L16: 44713 | M16: 44713 | N16: 44729 | P16: 赣DDA652 | Q16: 360018858782 | R16: 10 | S16: 5 | T16: 王婷 | V16: YP360000632302230209
A17: 2022052380003438 | B17: 杨玲 | C17: 44719 | D17: 15970232023 | E17: 6228110084407311 | F17: 吉安市分行 | G17: 梅赛德斯-奔驰牌 | H17: 一手自用车 | I17: 直客式 | J17: cd000000000000000000839 | K17: 吉安市 | L17: 44719 | M17: 44719 | N17: 44729 | P17: 赣DFY367 | Q17: 360018057423 | R17: 22.5 | S17: 5 | T17: 郭玲风 | V17: YP360000632302230219
A18: 2022060480000553 | B18: 张飘兵 | C18: 44722 | D18: 15907960601 | E18: 6228110084441385 | F18: 吉安市分行 | G18: 梅赛德斯-奔驰牌 | H18: 一手自用车 | I18: 直客式 | J18: cd000000000000000000840 | K18: 吉安市 | L18: 44725 | M18: 44725 | N18: 44729 | P18: 赣DM1360 | Q18: 360018859242 | R18: 50 | S18: 4 | T18: 梅洁 | V18: YP360000632302230218
A19: 2022060980005184 | B19: 曾钦湖 | C19: 44722 | D19: 19907993218 | E19: 6228110084447200 | F19: 吉安市城北支行 | G19: 凯迪拉克 | H19: 一手自用车 | I19: 直客式 | J19: cd000000000000000000841 | K19: 萍乡市 | L19: 44726 | M19: 44726 | N19: 44739 | P19: 赣JE0307 | Q19: 360017035866 | R19: 15 | S19: 3 | T19: 周颖 | V19: YP360000632302230215
A20: 2022060780002698 | B20: 刘云甫 | C20: 44722 | D20: 13979628258 | E20: 6228110084441617 | F20: 吉安市分行 | G20: 梅赛德斯-奔驰牌 | H20: 一手自用车 | I20: 直客式 | J20: cd000000000000000000842 | K20: 吉安市 | L20: 44727 | M20: 44727 | N20: 44739 | P20: 赣D16Z89 | Q20: 360018057308 | R20: 30 | S20: 5 | T20: 梅洁 | V20: YP360000632302230216
A21: 2022061380002260 | B21: 段德泓 | C21: 44726 | D21: 18870659464 | E21: 6228110084449925 | F21: 吉安市城北支行 | G21: 奥迪牌 | H21: 一手自用车 | I21: 直客式 | J21: cd000000000000000000843 | K21: 吉安市 | L21: 44727 | M21: 44727 | N21: 44739 | P21: 赣D01S70 | Q21: 360018072842 | R21: 15 | S21: 3 | T21: 徐求芸 | V21: YP360000632302230213
A22: 2022061080003441 | B22: 刘益平 | C22: 44726 | D22: 13929052766 | E22: 6228110084444587 | F22: 吉安市城北支行 | G22: 奥迪牌 | H22: 一手自用车 | I22: 直客式 | J22: cd000000000000000000844 | K22: 吉安市 | L22: 44727 | M22: 44727 | N22: 44739 | P22: 赣DFY922 | Q22: 360018072833 | R22: 14.98 | S22: 3 | T22: 徐求芸 | V22: YP360000632302230214
A23: 2022061380001757 | B23: 戴平 | C23: 44726 | D23: 13879631787 | E23: 6228110084454404 | F23: 吉安市青原大道支行 | G23: 凯迪拉克 | H23: 一手自用车 | I23: 直客式 | J23: cd000000000000000000845 | K23: 吉安市 | L23: 44727 | M23: 44727 | N23: 44739 | P23: 赣D96V15 | Q23: 360018858504 | R23: 10 | S23: 5 | T23: 谢文青 | V23: YP360000632302230212
A24: 2022061280000375 | B24: 刘舟 | C24: 44727 | D24: 15170206904 | E24: 6228110084450857 | F24: 吉安市青原大道支行 | G24: 凯迪拉克 | H24: 一手自用车 | I24: 直客式 | J24: cd000000000000000000846 | K24: 吉安市 | L24: 44727 | M24: 44727 | N24: 44739 | P24: 赣DFM638 | Q24: 360018858886 | R24: 15 | S24: 5 | T24: 谢文青 | V24: YP360000632302230211
A25: 2022060780003220 | B25: 周子燕 | C25: 44720 | D25: 13979641188 | E25: 6228110084434760 | F25: 吉安市青原大道支行 | G25: 沃尔沃 | H25: 一手自用车 | I25: 直客式 | J25: cd000000000000000000847 | K25: 吉安市 | L25: 44727 | M25: 44727 | N25: 44739 | P25: 赣D3551W | Q25: 360016712168 | R25: 17 | S25: 3 | T25: 王婷 | V25: YP360000632302230210
A26: 2022061780003464 | B26: 姚亮 | C26: 44732 | D26: 18107061010 | E26: 6228110084469204 | F26: 吉安市青原大道支行 | G26: 丰田牌 | H26: 一手自用车 | I26: 直客式 | J26: cd000000000000000000848 | K26: 吉安市 | L26: 44732 | M26: 44732 | N26: 44739 | P26: 赣D5207M | Q26: 360018057440 | R26: 15 | S26: 3 | T26: 谢文青 | V26: YP360000632302230207
A27: 2022061380001705 | B27: 冯秋根 | C27: 44727 | D27: 13879654628 | E27: 6228110084459015 | F27: 吉安市青原大道支行 | G27: 凯迪拉克 | H27: 一手自用车 | I27: 直客式 | J27: cd000000000000000000849 | K27: 吉安市 | L27: 44728 | M27: 44728 | N27: 44739 | P27: 赣DE1888 | Q27: 360018858878 | R27: 27 | S27: 5 | T27: 谢文青 | V27: YP360000632302230206
... A51: 2022061480001852 | B51: 肖少敏 | C51: 44727 | D51: 13907961276 | E51: 6228110084455492 | F51: 吉安市城北支行 | G51: 奥迪牌 | H51: 一手自用车 | I51: 直客式 | J51: cd000000000000000000873 | K51: 吉安市 | L51: 44736 | M51: 44736 | N51: 44750 | P51: 赣D1Q888 | Q51: 360018072922 | R51: 15 | S51: 3 | T51: 周颖 | V51: YP360000632302230187
A52: 2022062980002904 | B52: 黄丽萍 | C52: 44746 | E52: 622811******5022 | F52: 吉安市分行 | G52: 梅赛德斯-奔驰牌 | H52: 一手自用车 | I52: 直客式 | J52: cd000000000000000000874 | K52: 吉安市 | L52: 44746 | M52: 44746 | N52: 44750 | P52: 赣DGF877 | Q52: 360018057296 | R52: 35.8 | S52: 5 | T52: 梅洁 | V52: YP360000632302230183
A53: 2022062880003946 | B53: 罗亮 | C53: 44742 | D53: 15179629668 | E53: 6228110084503481 | F53: 吉安市分行 | G53: 梅赛德斯-奔驰牌 | H53: 一手自用车 | I53: 直客式 | J53: cd000000000000000000875 | K53: 吉安市 | L53: 44746 | M53: 44746 | N53: 44750 | P53: 赣DL8800 | Q53: 360018057058 | R53: 35 | S53: 5 | T53: 梅洁 | V53: YP360000632302230182
A54: 2022062980001609 | B54: 涂林荣 | C54: 44742 | D54: 13970672798 | E54: 6228110084501899 | F54: 吉安市分行 | G54: 梅赛德斯-奔驰牌 | H54: 一手自用车 | I54: 直客式 | J54: cd000000000000000000876 | K54: 吉安市 | L54: 44746 | M54: 44746 | N54: 44750 | P54: 赣DDV772 | Q54: 360018057064 | R54: 24.58 | S54: 5 | T54: 梅洁 | V54: YP360000632207080001
A55: 2022062980000539 | B55: 肖辉 | C55: 44741 | D55: 13600189334 | E55: 6228110084505163 | F55: 吉安市青原大道支行 | G55: 凯迪拉克 | H55: 一手自用车 | I55: 直客式 | J55: cd000000000000000000877 | K55: 吉安市 | L55: 44741 | M55: 44741 | N55: 44754 | P55: 赣DEC011 | Q55: 360018072394 | R55: 15 | S55: 5 | T55: 谢文青 | V55: YP360000632302230181
A56: 2022062880001586 | B56: 颜轶群 | C56: 44740 | D56: 18779619192 | E56: 6228110084499300 | F56: 吉安市青原大道支行 | G56: 领克 | H56: 一手自用车 | I56: 直客式 | J56: cd000000000000000000878 | K56: 吉安市 | L56: 44741 | M56: 44741 | N56: 44754 | P56: 赣DNG965 | Q56: 360018873720 | R56: 15 | S56: 5 | T56: 谢文青 | V56: YP360000632302230180
A57: 2022062080002875 | B57: 杨舟 | C57: 44742 | D57: 15949689119 | E57: 6228110084471572 | F57: 吉安市青原大道支行 | G57: 凯迪拉克 | H57: 一手自用车 | I57: 直客式 | J57: cd000000000000000000879 | K57: 吉安市 | L57: 44746 | M57: 44746 | N57: 44754 | P57: 赣DHX298 | Q57: 360018866266 | R57: 15 | S57: 5 | T57: 谢文青 | V57: YP360000632302230179
A58: 2022062780001742 | B58: 刘金明 | C58: 44746 | E58: 622811******8435 | F58: 吉安市青原大道支行 | G58: 凯迪拉克 | H58: 一手自用车 | I58: 直客式 | J58: cd000000000000000000880 | K58: 吉安市 | L58: 44746 | M58: 44746 | N58: 44754 | P58: 赣DHP001 | Q58: 360018072464 | R58: 20 | S58: 5 | T58: 谢文青 | V58: YP360000632302230178
A59: 2022062980000539 | B59: 肖俊 | C59: 44741 | E59: 622811******5163 | F59: 吉安市青原大道支行 | G59: 凯迪拉克 | H59: 一手自用车 | I59: 直客式 | J59: cd000000000000000000881 | K59: 吉安市 | L59: 44742 | M59: 44742 | N59: 44754 | P59: 赣DEH239 | Q59: 360018835997 | R59: 15 | S59: 5 | T59: 谢文青 | V59: YP360000632302230181
A60: 2022062880002023 | B60: 易莉 | C60: 44741 | D60: 13319343334 | E60: 6228110084503200 | F60: 吉安市青原大道支行 | G60: 凯迪拉克 | H60: 一手自用车 | I60: 直客式 | J60: cd000000000000000000882 | K60: 宜春市 | L60: 44748 | M60: 44748 | N60: 44757 | P60: 赣CPA167 | Q60: 360014956976 | R60: 15 | S60: 5 | T60: 谢文青 | V60: YP360000632302230164
A61: 2022070780002566 | B61: 黄文豪 | C61: 44753 | E61: 622811******8893 | F61: 吉安市分行 | G61: 梅赛德斯-奔驰牌 | H61: 一手自用车 | I61: 直客式 | J61: cd000000000000000000883 | K61: 吉安市 | L61: 44753 | M61: 44753 | N61: 44757 | P61: 赣D9852N | Q61: 360018057328 | R61: 10 | S61: 3 | T61: 梅洁 | V61: YP360000632302230175
A62: 2022062880002501 | B62: 刘富根 | C62: 44746 | E62: 622811******7494 | F62: 吉安市分行 | G62: 梅赛德斯-奔驰牌 | H62: 一手自用车 | I62: 直客式 | J62: cd000000000000000000884 | K62: 吉安市 | L62: 44749 | M62: 44749 | N62: 44757 | P62: 赣DFY360 | Q62: 360018057218 | R62: 12 | S62: 3 | T62: 梅洁 | V62: YP360000632302230174
A63: 2022070580001705 | B63: 梁文鸿 | C63: 44748 | E63: 622811******9305 | F63: 吉安市青原大道支行 | G63: 凯迪拉克 | H63: 一手自用车 | I63: 直客式 | J63: cd000000000000000000885 | K63: 吉安市 | L63: 44753 | M63: 44753 | N63: 44757 | P63: 赣D84826 | Q63: 360018072307 | R63: 10 | S63: 3 | T63: 王婷 | V63: YP360000632302230172
A64: 2022070580001376 | B64: 刘佳祺 | C64: 44748 | E64: 622811******6640 | F64: 吉安市青原大道支行 | G64: 凯迪拉克 | H64: 一手自用车 | I64: 直客式 | J64: cd000000000000000000886 | K64: 吉安市 | L64: 44749 | M64: 44749 | N64: 44757 | P64: 赣DFS212 | Q64: 360018072139 | R64: 15 | S64: 5 | T64: 王婷 | V64: YP360000632302230173
A65: 2022062680001006 | B65: 朱晓梅 | C65: 44741 | D65: 13340169876 | E65: 6228110084495506 | F65: 吉安市井冈山大道支行 | G65: 宝马牌 | H65: 一手自用车 | I65: 直客式 | J65: cd000000000000000000887 | K65: 萍乡市 | L65: 44748 | M65: 44748 | N65: 44757 | P65: 赣JJ7063 | Q65: 360017008902 | R65: 22.6 | S65: 5 | T65: 梁洁 | V65: YP360000632302230162
A66: 2022070680000656 | B66: 朱燕飞 | C66: 44753 | E66: 622811******3117 | F66: 吉安市分行 | G66: 梅赛德斯-奔驰牌 | H66: 一手自用车 | I66: 直客式 | J66: cd000000000000000000888 | K66: 吉安市 | L66: 44755 | M66: 44755 | N66: 44757 | P66: 赣DEJ753 | Q66: 360018057496 | R66: 15 | S66: 3 | T66: 梅洁 | V66: YP360000632302230163
A67: 2022070780002126 | B67: 兰舒亭 | C67: 44753 | E67: 622811******8041 | F67: 吉安市城北支行 | G67: 奥迪牌 | H67: 一手自用车 | I67: 直客式 | J67: cd000000000000000000889 | K67: 吉安市 | L67: 44753 | M67: 44753 | N67: 44761 | P67: 赣D8880N | Q67: 360018835826 | R67: 10 | S67: 3 | T67: 胡涛 | V67: YP360000632302230170
A68: 2022063080002580 | B68: 曾令池 | C68: 44746 | E68: 622811******8522 | F68: 吉安市城北支行 | G68: 奥迪牌 | H68: 一手自用车 | I68: 直客式 | J68: cd000000000000000000890 | K68: 吉安市 | L68: 44746 | M68: 44746 | N68: 44761 | P68: 赣D7A940 | Q68: 360018835965 | R68: 10 | S68: 3 | T68: 郭元 | V68: YP360000632302230171
A69: 2022070880002414 | B69: 肖华 | C69: 44753 | E69: 622811******4610 | F69: 吉安市城北支行 | G69: 奥迪牌 | H69: 一手自用车 | I69: 直客式 | J69: cd000000000000000000891 | K69: 吉安市 | L69: 44754 | M69: 44754 | N69: 44761 | P69: 赣D9957Z | Q69: 360018835813 | R69: 12 | S69: 5 | T69: 胡涛 | V69: YP360000632302230169
A70: 2022062980003881 | B70: 嬴时贵 | C70: 44748 | E70: 622811******5510 | F70: 吉安市青原大道支行 | G70: 凯迪拉克 | H70: 一手自用车 | I70: 直客式 | J70: cd000000000000000000892 | K70: 吉安市 | L70: 44748 | M70: 44748 | N70: 44761 | P70: 赣DHU359 | Q70: 360018072376 | R70: 15 | S70: 5 | T70: 谢文青 | V70: YP360000632302230168
A71: 2022070680001200 | B71: 熊艳霞 | C71: 44753 | E71: 622811******4156 | F71: 吉安市青原大道支行 | G71: 丰田牌 | H71: 一手自用车 | I71: 直客式 | J71: cd000000000000000000893 | K71: 吉安市 | L71: 44753 | M71: 44753 | N71: 44761 | P71: 赣DHV152 | Q71: 360018057335 | R71: 14.4 | S71: 3 | T71: 谢文青 | V71: YP360000632302230167
A72: 2022070780000968 | B72: 黄志群 | C72: 44751 | E72: 622811******4263 | F72: 吉安市青原大道支行 | G72: 凯迪拉克 | H72: 一手自用车 | I72: 直客式 | J72: cd000000000000000000894 | K72: 吉安市 | L72: 44754 | M72: 44754 | N72: 44761 | P72: 赣D5H389 | Q72: 360018072408 | R72: 10 | S72: 3 | T72: 王婷 | V72: YP360000632302230166
A73: 2022070880002805 | B73: 李恪庆 | C73: 44753 | E73: 622811******4628 | F73: 吉安市青原大道支行 | G73: 凯迪拉克 | H73: 一手自用车 | I73: 直客式 | J73: cd000000000000000000895 | K73: 吉安市 | L73: 44754 | M73: 44754 | N73: 44768 | P73: 赣DGW151 | Q73: 360018072409 | R73: 15 | S73: 5 | T73: 王婷 | V73: YP360000632302230165
A74: 2022071380003471 | B74: 张雪 | C74: 44761 | E74: 622811******2414 | F74: 吉安市井冈山大道支行 | G74: 宝马牌 | H74: 一手自用车 | I74: 直客式 | J74: cd000000000000000000896 | K74: 吉安市 | L74: 44763 | M74: 44763 | N74: 44768 | P74: 赣DFQ029 | Q74: 360016758908 | R74: 25 | S74: 5 | T74: 曾宁 | V74: YP360000632302230161
A75: 2022062780001457 | B75: 李期宁 | C75: 44741 | D75: 15107066131 | E75: 6228110084492925 | F75: 吉安市青原大道支行 | G75: 凯迪拉克 | H75: 一手自用车 | I75: 直客式 | J75: cd000000000000000000897 | K75: 吉安市 | L75: 44749 | M75: 44749 | N75: 44768 | P75: 赣DK2522 | Q75: 360018056177 | R75: 10 | S75: 3 | T75: 谢文青 | V75: YP360000632302230158
A76: 2022071180001921 | B76: 刘春辉 | C76: 44754 | E76: 622811******8230 | F76: 吉安市青原大道支行 | G76: 凯迪拉克 | H76: 一手自用车 | I76: 直客式 | J76: cd000000000000000000898 | K76: 吉安市 | L76: 44755 | M76: 44755 | N76: 44768 | P76: 赣D10N58 | Q76: 360018072130 | R76: 15 | S76: 5 | T76: 谢文青 | V76: YP360000632302230157
A77: 2022062580001480 | B77: 蒋玉芳 | C77: 44740 | D77: 18007962826 | E77: 6228110084495373 | F77: 吉安市城北支行 | G77: 奥迪牌 | H77: 一手自用车 | I77: 直客式 | J77: cd000000000000000000899 | K77: 吉安市 | L77: 44741 | M77: 44741 | N77: 44768 | P77: 赣D9916Z | Q77: 360018835922 | R77: 15 | S77: 5 | T77: 胡涛 | V77: YP360000632302230160
A78: 2022062880002634 | B78: 谢鸿 | C78: 44741 | D78: 18679669552 | E78: 6228110084498476 | F78: 吉安市城北支行 | G78: 奥迪牌 | H78: 一手自用车 | I78: 直客式 | J78: cd000000000000000000900 | K78: 吉安市 | L78: 44742 | M78: 44742 | N78: 44768 | P78: 赣D8970M | Q78: 360018835917 | R78: 12 | S78: 5 | T78: 胡涛 | V78: YP360000632302230159
A79: 2022071780000447 | B79: 包丽红 | C79: 44761 | E79: 622811******1720 | F79: 吉安市分行 | G79: 梅赛德斯-奔驰牌 | H79: 一手自用车 | I79: 直客式 | J79: cd000000000000000000901 | K79: 吉安市 | L79: 44762 | M79: 44762 | N79: 44770 | P79: 赣D828F2 | Q79: 360018057053 | R79: 27.6 | S79: 3 | T79: 黄艳 | V79: YP360000632302230149
A80: 2022071280002145 | B80: 陈建桑 | C80: 44755 | E80: 622811******9154 | F80: 吉安市分行 | G80: 梅赛德斯-奔驰牌 | H80: 一手自用车 | I80: 直客式 | J80: cd000000000000000000902 | K80: 吉安市 | L80: 44757 | M80: 44757 | N80: 44770 | P80: 赣D178B6 | Q80: 360018057482 | R80: 15 | S80: 3 | T80: 梅洁 | V80: YP360000632302230148
A81: 2022071280002449 | B81: 李娜 | C81: 44756 | E81: 622811******9477 | F81: 吉安市分行 | G81: 梅赛德斯-奔驰牌 | H81: 一手自用车 | I81: 直客式 | J81: cd000000000000000000903 | K81: 吉安市 | L81: 44763 | M81: 44763 | N81: 44770 | P81: 赣DCL799 | Q81: 360018057107 | R81: 32.64 | S81: 5 | T81: 梅洁 | V81: YP360000632302230155
A82: 2022071480001831 | B82: 刘昌飞 | C82: 44760 | E82: 622811******2323 | F82: 吉安市分行 | G82: 梅赛德斯-奔驰牌 | H82: 一手自用车 | I82: 直客式 | J82: cd000000000000000000904 | K82: 吉安市 | L82: 44761 | M82: 44761 | N82: 44770 | O82: 45001 | P82: 赣DDY808 | Q82: 360018057265 | R82: 28 | S82: 5 | T82: 梅洁 | V82: YP360000632302230156
A83: 2022062980003172 | B83: 毛玮 | C83: 44753 | E83: 622811******2830 | F83: 吉安市分行 | G83: 梅赛德斯-奔驰牌 | H83: 一手自用车 | I83: 直客式 | J83: cd000000000000000000905 | K83: 吉安市 | L83: 44757 | M83: 44757 | N83: 44770 | P83: 赣D02V66 | Q83: 360018057479 | R83: 20 | S83: 5 | T83: 梅洁 | V83: YP360000632302230150
A84: 2022070980001129 | B84: 帅海军 | C84: 44761 | E84: 622811******4809 | F84: 吉安市分行 | G84: 梅赛德斯-奔驰牌 | H84: 一手自用车 | I84: 直客式 | J84: cd000000000000000000906 | K84: 吉安市 | L84: 44763 | M84: 44763 | N84: 44770 | P84: 赣D8J542 | Q84: 360016758924 | R84: 49.9 | S84: 5 | T84: 梅洁 | V84: YP360000632302230152
A85: 2022072080001343 | B85: 吴志军 | C85: 44763 | E85: 622811******2057 | F85: 吉安市分行 | G85: 梅赛德斯-奔驰牌 | H85: 一手自用车 | I85: 直客式 | J85: cd000000000000000000907 | K85: 吉安市 | L85: 44764 | M85: 44764 | N85: 44770 | P85: 赣DEL769 | Q85: 360018057104 | R85: 27.8 | S85: 5 | T85: 黄艳 | V85: YP360000632302230151
A86: 2022071280003051 | B86: 高海松 | C86: 44757 | E86: 622811******0947 | F86: 吉安市青原大道支行 | G86: 凯迪拉克 | H86: 一手自用车 | I86: 直客式 | J86: cd000000000000000000908 | K86: 吉安市 | L86: 44757 | M86: 44757 | N86: 44770 | P86: 赣DBG752 | Q86: 360018072045 | R86: 12 | S86: 5 | T86: 王婷 | V86: YP360000632302230153
A87: 2022071880002374 | B87: 钟庆 | C87: 44763 | E87: 622811******6851 | F87: 吉安市城北支行 | G87: 奥迪牌 | H87: 一手自用车 | I87: 直客式 | J87: cd000000000000000000909 | K87: 吉安市 | L87: 44764 | M87: 44764 | N87: 44770 | P87: 赣DGW566 | Q87: 360018835714 | R87: 15 | S87: 5 | T87: 胡涛 | V87: YP360000632302230154
A88: 2022072480000125 | B88: 罗小平 | C88: 44768 | E88: 622811******2105 | F88: 吉安市分行 | G88: 梅赛德斯-奔驰牌 | H88: 一手自用车 | I88: 直客式 | J88: cd000000000000000000910 | K88: 吉安市 | L88: 44769 | M88: 44769 | N88: 44774 | P88: 赣D3V886 | Q88: 360018816424 | R88: 35.6 | S88: 3 | T88: 黄艳 | V88: YP360000632302230147
A89: 2022072180001259 | B89: 彭小惠 | C89: 44764 | E89: 622811******3378 | F89: 吉安市分行 | G89: 梅赛德斯-奔驰牌 | H89: 一手自用车 | I89: 直客式 | J89: cd000000000000000000911 | K89: 吉安市 | L89: 44767 | M89: 44767 | N89: 44774 | P89: 赣D73U60 | Q89: 360018057471 | R89: 16 | S89: 3 | T89: 黄艳 | V89: YP360000632302230146
A90: 2022071980002214 | B90: 肖瑛 | C90: 44764 | E90: 622811******4673 | F90: 吉安市分行 | G90: 梅赛德斯-奔驰牌 | H90: 一手自用车 | I90: 直客式 | J90: cd000000000000000000912 | K90: 吉安市 | L90: 44764 | M90: 44764 | N90: 44774 | P90: 赣D4C666 | Q90: 360016758937 | R90: 58 | S90: 5 | T90: 黄艳 | V90: YP360000632302230145
A91: 2022072180001755 | B91: 陈清发 | C91: 44764 | E91: 622811******4491 | F91: 吉安市分行 | G91: 梅赛德斯-奔驰牌 | H91: 一手自用车 | I91: 直客式 | J91: cd000000000000000000913 | K91: 吉安市 | L91: 44769 | M91: 44769 | N91: 44774 | P91: 赣DBD307 | Q91: 360018057452 | R91: 30 | S91: 5 | T91: 黄艳 | V91: YP360000632302230142
A92: 2022072180001857 | B92: 夏荣明 | C92: 44764 | E92: 622811******3485 | F92: 吉安市分行 | G92: 梅赛德斯-奔驰牌 | H92: 一手自用车 | I92: 直客式 | J92: cd000000000000000000914 | K92: 吉安市 | L92: 44769 | M92: 44769 | N92: 44774 | P92: 赣DGU526 | Q92: 360018816054 | R92: 22.5 | S92: 5 | T92: 黄艳 | V92: YP360000632302230141
A93: 2022072680001953 | B93: 廖水龙 | C93: 44769 | E93: 622811******0661 | F93: 吉安市分行 | G93: 梅赛德斯-奔驰牌 | H93: 一手自用车 | I93: 直客式 | J93: cd000000000000000000915 | K93: 吉安市 | L93: 44770 | M93: 44770 | N93: 44774 | P93: 赣DL6000 | Q93: 360018849289 | R93: 30 | S93: 3 | T93: 梅洁 | V93: YP360000632302230139
A94: 2022072180003136 | B94: 钟传明 | C94: 44767 | E94: 622811******2552 | F94: 吉安市青原大道支行 | G94: 凯迪拉克 | H94: 一手自用车 | I94: 直客式 | J94: cd000000000000000000916 | K94: 新余市 | L94: 44769 | M94: 44769 | N94: 44774 | P94: 赣K87Q82 | Q94: 360017866396 | R94: 22.5 | S94: 5 | T94: 王婷 | V94: YP360000632302230138
... A134: 2022080280000603 | B134: 王静 | C134: 44830 | E134: 622811******6341 | F134: 吉安市分行 | G134: 梅赛德斯-奔驰牌 | H134: 一手自用车 | I134: 直客式 | J134: cd000000000000000000956 | K134: 吉安市 | L134: 44831 | M134: 44831 | N134: 44836 | P134: 赣D2363W | Q134: 360018816356 | R134: 20 | S134: 5 | T134: 黄艳 | V134: YP360000632302230103
A135: 2022082280001690 | B135: 王振 | C135: 44804 | E135: 622811******4506 | F135: 吉安市分行 | G135: 梅赛德斯-奔驰牌 | H135: 一手自用车 | I135: 直客式 | J135: cd000000000000000000957 | K135: 吉安市 | L135: 44805 | M135: 44805 | N135: 44836 | O135: 44866 | P135: 赣DBE685 | Q135: 360018816450 | R135: 25 | S135: 3 | T135: 黄艳 | U135: 未结清出库，客户更换车牌号码 | V135: YP360000632302230101
A136: 2022082280002115 | B136: 袁丽霞 | C136: 44797 | E136: 622811******4530 | F136: 吉安市分行 | G136: 梅赛德斯-奔驰牌 | H136: 一手自用车 | I136: 直客式 | J136: cd000000000000000000958 | K136: 吉安市 | L136: 44802 | M136: 44802 | N136: 44836 | P136: 赣D13Z01 | Q136: 360018816348 | R136: 25 | S136: 5 | T136: 黄艳 | V136: YP360000632302230108
A137: 2022083180001681 | B137: 刘波 | C137: 44830 | E137: 622811******8980 | F137: 吉安市分行 | G137: 梅赛德斯-奔驰牌 | H137: 一手自用车 | I137: 直客式 | J137: cd000000000000000000959 | K137: 吉安市 | L137: 44833 | M137: 44833 | N137: 44845 | P137: 赣D24888 | Q137: 360019439226 | R137: 46 | S137: 3 | T137: 梅洁 | V137: YP360000632302230099
A138: 2022082580002724 | B138: 廖传亮 | C138: 44842 | E138: 622811******9421 | F138: 吉安市分行 | G138: 梅赛德斯-奔驰牌 | H138: 一手自用车 | I138: 直客式 | J138: cd000000000000000000960 | K138: 吉安市 | L138: 44842 | M138: 44842 | N138: 44845 | P138: 赣D0544K | Q138: 360018816097 | R138: 30 | S138: 5 | T138: 梅洁 | V138: YP360000632302230098
A139: 2022100380000961 | B139: 黄美英 | C139: 44844 | E139: 622811******7236 | F139: 吉安市分行 | G139: 梅赛德斯-奔驰牌 | H139: 一手自用车 | I139: 直客式 | J139: cd000000000000000000961 | K139: 吉安市 | L139: 44844 | M139: 44844 | N139: 44845 | P139: 赣DV5566 | Q139: 360018816470 | R139: 16 | S139: 5 | T139: 黄艳 | V139: YP360000632302230097
A140: 2022082880000924 | B140: 王山英 | C140: 44842 | E140: 622811******1499 | F140: 吉安市分行 | G140: 凯迪拉克 | H140: 一手自用车 | I140: 直客式 | J140: cd000000000000000000962 | K140: 吉安市 | L140: 44842 | M140: 44842 | N140: 44845 | O140: 44980 | P140: 赣D33440 | Q140: 360018078439 | R140: 15 | S140: 3 | T140: 刘涛 | V140: YP360000632302230096
A141: 2022092980003474 | B141: 杨桂俊 | C141: 44844 | E141: 622811******1743 | F141: 吉安市分行 | G141: 梅赛德斯-奔驰牌 | H141: 一手自用车 | I141: 直客式 | J141: cd000000000000000000963 | K141: 吉安市 | L141: 44844 | M141: 44844 | N141: 44845 | P141: 赣DBV578 | Q141: 360018816473 | R141: 30 | S141: 5 | T141: 黄艳 | V141: YP360000632302230090
A142: 2022082480001290 | B142: 蔡小波 | C142: 44842 | E142: 622811******7185 | F142: 吉安市分行 | G142: 赛力斯牌 | H142: 一手自用车 | I142: 直客式 | J142: cd000000000000000000964 | K142: 吉安市 | L142: 44842 | M142: 44842 | N142: 44848 | P142: 赣DF17178 | Q142: 360018858258 | R142: 18 | S142: 4 | T142: 胡涛 | V142: YP360000632302230094
A143: 2022082480001269 | B143: 陈峰 | C143: 44842 | E143: 622811******8903 | F143: 吉安市分行 | G143: 奥迪牌 | H143: 一手自用车 | I143: 直客式 | J143: cd000000000000000000965 | K143: 吉安市 | L143: 44842 | M143: 44842 | N143: 44848 | P143: 赣D2988Y | Q143: 360018858257 | R143: 20 | S143: 5 | T143: 周颖 | V143: YP360000632302230092
A144: 2022083080001739 | B144: 周娟 | C144: 44842 | E144: 622811******3727 | F144: 吉安市分行 | G144: 奥迪牌 | H144: 一手自用车 | I144: 直客式 | J144: cd000000000000000000966 | K144: 吉安市 | L144: 44842 | M144: 44842 | N144: 44848 | P144: 赣D235C6 | Q144: 360018858254 | R144: 20 | S144: 3 | T144: 胡涛 | V144: YP360000632302230091
A145: 2022081480000810 | B145: 周军发 | C145: 44804 | E145: 622811******7197 | F145: 吉安市分行 | G145: 奥迪牌 | H145: 一手自用车 | I145: 直客式 | J145: cd000000000000000000967 | K145: 吉安市 | L145: 44805 | M145: 44843 | N145: 44848 | P145: 赣DHH165 | Q145: 360018858381 | R145: 20 | S145: 3 | T145: 胡涛 | V145: YP360000632302230093
A146: 2022083180002324 | B146: 翟荣 | C146: 44831 | E146: 622811******7958 | F146: 吉安市分行 | G146: 宝马牌 | H146: 一手自用车 | I146: 直客式 | J146: cd000000000000000000968 | K146: 吉安市 | L146: 44846 | M146: 44846 | N146: 44848 | P146: 赣D8168S | Q146: 360018837384 | R146: 22 | S146: 5 | T146: 梁洁 | V146: YP360000632302230089
A147: 2022100780000522 | B147: 李亚薇 | C147: 44844 | E147: 622811******0122 | F147: 吉安市分行 | G147: 梅赛德斯-奔驰牌 | H147: 一手自用车 | I147: 直客式 | J147: cd000000000000000000969 | K147: 吉安市 | L147: 44845 | M147: 44845 | N147: 44848 | P147: 赣DFP011 | Q147: 360018816479 | R147: 15.4 | S147: 3 | T147: 黄艳 | V147: YP360000632302230088
A148: 2022100580000588 | B148: 宋子卉 | C148: 44844 | E148: 622811******9620 | F148: 吉安市分行 | G148: 梅赛德斯-奔驰牌 | H148: 一手自用车 | I148: 直客式 | J148: cd000000000000000000970 | K148: 吉安市 | L148: 44846 | M148: 44846 | N148: 44848 | P148: 赣DGP526 | Q148: 360018816486 | R148: 14.7 | S148: 5 | T148: 黄艳 | V148: YP360000632302230087
A149: 2022100780000805 | B149: 肖慧玲 | C149: 44843 | E149: 622811******9298 | F149: 吉安市分行 | G149: 梅赛德斯-奔驰牌 | H149: 一手自用车 | I149: 直客式 | J149: cd000000000000000000971 | K149: 吉安市 | L149: 44845 | M149: 44845 | N149: 44848 | P149: 赣D05A83 | Q149: 360019439377 | R149: 30 | S149: 5 | T149: 黄艳 | V149: YP360000632302230080
A150: 2022101080001139 | B150: 欧阳燕虹 | C150: 44847 | E150: 622811******3058 | F150: 吉安市分行 | G150: 梅赛德斯-奔驰牌 | H150: 一手自用车 | I150: 直客式 | J150: cd000000000000000000972 | K150: 吉安市 | L150: 44848 | M150: 44848 | N150: 44860 | P150: 赣DEP373 | Q150: 360018097752 | R150: 20.9 | S150: 5 | T150: 黄艳 | V150: YP360000632302230081
A151: 2022100980001074 | B151: 王嘉敏 | C151: 44845 | E151: 622811******3117 | F151: 吉安市分行 | G151: 梅赛德斯-奔驰牌 | H151: 一手自用车 | I151: 直客式 | J151: cd000000000000000000973 | K151: 吉安市 | L151: 44848 | M151: 44848 | N151: 44860 | P151: 赣D8547DS | Q151: 360018816499 | R151: 20 | S151: 5 | T151: 黄艳 | V151: YP360000632302230083
A152: 2022100880000966 | B152: 王清和 | C152: 44847 | E152: 622811******8621 | F152: 吉安市分行 | G152: 梅赛德斯-奔驰牌 | H152: 一手自用车 | I152: 直客式 | J152: cd000000000000000000974 | K152: 吉安市 | L152: 44848 | M152: 44848 | N152: 44860 | P152: 赣DEB968 | Q152: 360018816497 | R152: 20 | S152: 5 | T152: 黄艳 | V152: YP360000632302230082
... A162: 2022103080000882 | B162: 罗小勇 | C162: 44867 | E162: 622811******2100 | F162: 吉安市分行 | G162: 梅赛德斯-奔驰牌 | H162: 一手自用车 | I162: 直客式 | J162: cd000000000000000000985 | K162: 吉安市 | L162: 44867 | M162: 44867 | N162: 44869 | P162: 赣D3E996 | Q162: 360018097854 | R162: 20 | S162: 5 | T162: 黄艳 | V162: YP360000632302230074
A163: 2022103080000434 | B163: 吴亮明 | C163: 44866 | E163: 622811******1889 | F163: 吉安市分行 | G163: 梅赛德斯-奔驰牌 | H163: 一手自用车 | I163: 直客式 | J163: cd000000000000000000986 | K163: 吉安市 | L163: 44867 | M163: 44867 | N163: 44869 | O163: 45013 | P163: 赣DGB808 | Q163: 360016764429 | R163: 18 | S163: 3 | T163: 梅洁 | V163: YP360000632302230076
A164: 2022102880001529 | B164: 谢玮 | C164: 44866 | E164: 622811******4080 | F164: 吉安市分行 | G164: 梅赛德斯-奔驰牌 | H164: 一手自用车 | I164: 直客式 | J164: cd000000000000000000987 | K164: 吉安市 | L164: 44868 | M164: 44868 | N164: 44869 | P164: 赣D2518Z | Q164: 360018097862 | R164: 20 | S164: 3 | T164: 黄艳 | V164: YP360000632302230073
A165: 2022103080000365 | B165: 杨坤 | C165: 44867 | E165: 622811******1871 | F165: 吉安市分行 | G165: 梅赛德斯-奔驰牌 | H165: 一手自用车 | I165: 直客式 | J165: cd000000000000000000988 | K165: 吉安市 | L165: 44868 | M165: 44868 | N165: 44869 | P165: 赣D8232Z | Q165: 360018097861 | R165: 15 | S165: 5 | T165: 梅洁 | V165: YP360000632302230075
A166: 2022103080000273 | B166: 蒋邦纲 | C166: 44867 | E166: 622811******4460 | F166: 吉安市分行 | G166: 梅赛德斯-奔驰牌 | H166: 一手自用车 | I166: 直客式 | J166: cd000000000000000000989 | K166: 吉安市 | L166: 44872 | M166: 44872 | N166: 44879 | P166: 赣DGB126 | Q166: 360018097570 | R166: 24.8 | S166: 5 | T166: 梅洁 | V166: YP360000632302230067
A167: 2022102580003553 | B167: 李艳 | C167: 44862 | E167: 622811******6781 | F167: 吉安市分行 | G167: 梅赛德斯-奔驰牌 | H167: 一手自用车 | I167: 直客式 | J167: cd000000000000000000990 | K167: 吉安市 | L167: 44872 | M167: 44872 | N167: 44879 | P167: 赣D68S30 | Q167: 360018097867 | R167: 30 | S167: 5 | T167: 黄艳 | V167: YP360000632302230068
A168: 2022110180001773 | B168: 喻小兰 | C168: 44869 | E168: 622811******7752 | F168: 吉安市分行 | G168: 梅赛德斯-奔驰牌 | H168: 一手自用车 | I168: 直客式 | J168: cd000000000000000000991 | K168: 吉安市 | L168: 44869 | M168: 44869 | N168: 44879 | P168: 赣DEJ638 | Q168: 360018097567 | R168: 17.5 | S168: 5 | T168: 黄艳 | V168: YP360000632302230069
A169: 2022102580003006 | B169: 朱芬芬 | C169: 44862 | E169: 622811******6765 | F169: 吉安市分行 | G169: 梅赛德斯-奔驰牌 | H169: 一手自用车 | I169: 直客式 | J169: cd000000000000000000992 | K169: 吉安市 | L169: 44868 | M169: 44868 | N169: 44879 | P169: 赣DGT822 | Q169: 360018097863 | R169: 23 | S169: 5 | T169: 黄艳 | V169: YP360000632302230070
A170: 2022071280001411 | B170: 黄波 | C170: 44756 | E170: 622811******9105 | F170: 吉安市分行 | G170: 凯迪拉克牌 | H170: 一手自用车 | I170: 直客式 | J170: cd000000000000000000993 | K170: 吉安市 | L170: 44781 | M170: 44875 | N170: 44879 | P170: 赣H9K730 | Q170: 360017516505 | R170: 15 | S170: 5 | T170: 谢文青 | V170: YP360000632302230062
A171: 2022110980000850 | B171: 戴素芬 | C171: 44875 | E171: 622811******5399 | F171: 吉安市分行 | G171: 梅赛德斯-奔驰牌 | H171: 一手自用车 | I171: 直客式 | J171: cd000000000000000000994 | K171: 吉安市 | L171: 44875 | M171: 44875 | N171: 44879 | P171: 赣D8157Y | Q171: 360018097890 | R171: 15 | S171: 3 | T171: 黄艳 | V171: YP360000632302230063
...
